Workbook

Sheet Overview
A1: Tesla Model 3 Highland 2026 SOP9 - Audio Upgrade BOM v2.0 Final Asset-Integrated
A2: v2.0 finalizes the engineering reference around the verified SOP9 collector capture. 241/241 manifest-listed assets passed byte-size and SHA-256 validation. All 15 target speaker connectors have metadata and terminal faceviews. Combined target location-image coverage is 14/15: X586 and X595 are retained from the prior built-in capture because the latest Tesla endpoint returned 403; X566 remains a visual-only HTTP 403 gap. Physical connector population/fitment in the delivered vehicle remains an installation-time check. HELIX V EIGHTEEN lead architecture, supplier sourcing comparisons and Pioneer/MATCH/HELIX sub-amplifier options are preserved.
A4: Budget minimum | B4: 3000 | D4: Current lead architecture / sourcing decision
A5: Budget maximum | B5: 3500 | D5: CURRENT LEAD: HELIX V EIGHTEEN DSP (18 amplified / 20 DSP) because it can finish all 15 cabin positions without a second cabin amplifier. Preserve Audison/V TWELVE/NEXT V EIGHT routes as alternatives. Exact SOP9 connector population and interposer pinning remain a physical-install verification item. Final 15-channel full-active requires bypass/rewire of the passive L/R crossover supplied in the K200.2TES4 package.
A6: Aanbevolen BOM totaal | B6: =SUM(BOM_Recommended!N5:N15)
A7: Budgetruimte | B7: =B5-B6
A8: Aantal cabin speakers | B8: =SUM(BOM_Recommended!D5:D15)
A9: Prijspeildatum | B9: 2026-09-10
A10: USD→EUR koers | B10: 0.860404
A11: Best current DE total | B11: =B6-1290+1205.9 | C11: NL DSP scenario | D11: =B6-1290+1349
A12: Beslispunten vóór definitieve bestelling
A13: 1. Pioneer subsystem identified: TS-WX1220AH donor hardware. Reuse 2×30 cm woofers + original Class-D amp; original Pioneer enclosure is NOT used. Resolve Tesla 15.5 V vs Pioneer 15.1 V max before direct power connection.
A14: 2. SOP9 reference connector metadata/pinouts are now captured and verified in v2.0. During installation verify which PAUDIO-only positions/connectors are physically populated in this exact vehicle before repinning the PP-TES/interposer; do not cut the Tesla loom.
A15: 3. 80 mm front-door en 50 mm headliner FlexMount/custom adapters fysiek proefpassen; budget bevat een adapter/pigtail-reserve.
A16: 4. Headliner L/R: PAUDIO-only X569/X579. Use AUX 2ch from Audison DSP OUT unless the PAUDIO MCU/wire path is proven usable on this BAUDIO car.
A17: 5. Prijzen zijn momentopnamen; verzendkosten/importheffingen zijn alleen meegenomen waar expliciet bekend.
A19: Kooproute voor BOM-totaal €3.393: DSP uit Duitsland (€1.290), DRC MP CAN uit NL (€179), Highland frontkit + PP-TES uit Duitsland, overige HELIX drivers via DE/EU. Verzendkosten zijn niet in het BOM-totaal opgenomen tenzij een shop ze expliciet gratis aanbiedt.
A21: MBC v1.1 aanvulling – zie MBC_Configurator, MBC_Focal_Set, MBC_Audison_Set en MBC_Quote_Mails.
A22: v1.2 correctie: bestaande Audison BEST FIT blijft leidend. Nieuwe shopprijzen en PowerBass/Ground Zero/V EIGHTEEN zijn toegevoegd als vergelijkingsroutes; geen eerdere optie is verwijderd.
A24: SOP9 EPC EVIDENCE UPDATE - 2026-09-02
A25: Verified BAUDIO 9 | B25: Front door base woofers X568/X578, tweeters X565/X575, IP L/C/R X566/X595/X576 and rear doors X586/X591.
A26: PAUDIO-only additions | B26: Front 80mm X570/X580, parcel shelf X588/X593 and headliners X569/X579. PAUDIO uses premium woofer endpoints X567/X577 instead of BAUDIO X568/X578.
A27: Headliner correction | B27: X569/X579 are shown only on the PAUDIO option branch. The BAUDIO build must not assume ready/active OEM headliner channels; route them via auxiliary amplification unless activation/wiring is verified.
A28: Audison impact | B28: The prior 11 Audison feeds remain valid for the original grouped map; add two AUX headliner feeds from Audison DSP OUT. Auxiliary amp model/price is still TBD and is NOT included in the old €3,393 baseline.
A29: Decision discipline | B29: HELIX V EIGHTEEN remains a clean 18-channel alternative, not an automatic replacement. Focal/DLS/MUSWAY/ESX/MATCH/PowerBass comparisons remain preserved.
A31: PIONEER TS-WX1220AH DONOR SUBSYSTEM - 2026-09-05
A32: Retained hardware | B32: 2 × original Pioneer ø30 cm / 12-inch woofers + original integrated Class-D amplifier removed from one TS-WX1220AH.
A33: Not retained | B33: Original Pioneer bass-reflex enclosure is NOT used.
A34: Driver installation | B34: Both woofers mounted in a custom rigid baffle/lid at the Tesla lower extra trunk storage cavity.
A35: Amplifier installation | B35: Original Pioneer amplifier remote-mounted behind the trunk side / wheel-arch trim, approximately at the OEM Premium amplifier location.
A36: Original Pioneer system rating | B36: 2×30 cm; 1000 W RMS / 3000 W max complete donor system. Original amplifier: 600 W RMS / 1200 W max Class-D.
A37: Pioneer electrical | B37: DC 14.4 V nominal; 10.8–15.1 V allowable; 50 A max current; negative ground. Pioneer wiring example specifies a dedicated 80 A fuse.
A38: Tesla LV compatibility | B38: Tesla publishes 15.5 V low-voltage. Direct Pioneer amp connection is NOT approved until actual SOP9 voltage is measured/verified; use a high-current regulated step-down supply if required.
A39: Signal route | B39: Audison/HELIX DSP dedicated subwoofer line output → RCA → original Pioneer amplifier → two donor woofers.
A40: Acoustic limitation | B40: Do not reuse Pioneer complete-enclosure frequency response/sensitivity as predicted custom-install performance. Final response depends on custom cavity volume, sealing, baffle stiffness, leakage and cabin gain.
A42: FULL HELIX i5 / i7 COMPARISON — 2026-09-06
A43: DSP conclusion | B43: HELIX V EIGHTEEN DSP selected for comparison: 18 amplified / 20 DSP channels, 15 cabin channels used, CH16-18 spare, processed RCA OUT 1/2 to retained Pioneer amplifier.
A44: i5-priority known total | B44: ='HELIX_i5_Setup'!B29
A45: i7-priority known total | B45: ='HELIX_i7_Setup'!B29
A46: Known i7 premium | B46: ='HELIX_Comparison'!C7
A47: Important naming | B47: Neither build can be literally 100% i5 or 100% i7 at all positions. The i5-priority setup uses i7 T20 because Tesla has an official 20mm HELIX adapter but no current Tesla FlexMount25; both use i3 coax center; the i7-priority setup uses i5 M80/M50 because i7 has no 80/50mm drivers.
A48: Purchase status | B48: COMPARISON ONLY — final SOP9 mounts/pigtails, V EIGHTEEN interposer, power/fusing and Pioneer voltage regulation are still open. Known totals are not turnkey installed prices.
A50: FULL HELIX BUDGET UPDATE — 2026-09-06
A51: Best long-term new | B51: V EIGHTEEN + refreshed Ci3/i5 value basket ≈ €3,631.98 known hardware including existing €39.98 adapter reserve. Current lead one-box route. Final 15-channel full-active requires bypass/rewire of the passive L/R crossover supplied in the K200.2TES4 package.
A52: Closest new to €3,500 | B52: NEXT V EIGHT DSP ULTIMATE + AMPLIFY 206 DIRECT ≈ €3,540.98 known hardware with refreshed common basket.
A53: 12-channel staged | B53: V TWELVE alone ≈ €3,331.98; add AMPLIFY 204 DIRECT → ≈ €3,570.98 known hardware with refreshed common basket.
A54: Second DSP later | B54: AMPLIFY 206 DSP (€599) is preferred over DSP MINI (€399) + AMPLIFY 204 (€239): one fewer box and €39 cheaper. Use only if retaining a V TWELVE and later demanding 15 individual cabin amp feeds.
A55: Current used scout | B55: A German private V TWELVE MK2 listing is indexed today at €1,050. Used V TWELVE + 204 route ≈ €3,101.98; used V TWELVE + 206 DSP ≈ €3,461.98. Treat as opportunistic, not a stable price.
A56: Country result | B56: DE has the strongest verified online availability. FR-deliverable prices are generally the same MSRP; ARS24 explicitly ships HELIX/MATCH to France. No lower indexed Belgian checkout was found; HifiMotive Belgium dealer network uses €1,799 V EIGHTEEN / €299 DIRECTOR RRP, so request a bundle quote.
A58: HELIX BUDGET OPTIMIZATION v1.7 — 2026-09-06
A59: Best clean new | B59: V EIGHTEEN route: ≈ €3,631.98 known hardware / ≈ €3,881.98 with the existing illustrative €250 reserve. One DSP/amp and future 15-channel full-active capability.
A60: Best new closest €3,500 | B60: NEXT V EIGHT DSP ULTIMATE + AMPLIFY 206 DIRECT: ≈ €3,540.98 known / ≈ €3,790.98 with illustrative reserve.
A61: Best 12-channel staged | B61: V TWELVE alone: ≈ €3,331.98 known / ≈ €3,581.98 with reserve. Add AMPLIFY 204 DIRECT later → ≈ €3,570.98 known.
A62: Best clearance all-new | B62: Legacy V EIGHT €949 + AMPLIFY 206 DSP: ≈ €3,380.98 known / ≈ €3,630.98 with reserve. Two-DSP complexity remains the trade-off.
A63: Used update | B63: Used V TWELVE €1,200 + 204 DIRECT: ≈ €3,271.98 known / ≈ €3,521.98 with reserve. Used-market availability is not guaranteed.
A64: Full-active decision | B64: Do not build a multi-box full-active system just to save a few euros: legacy V EIGHT + 206 DSP + 204 DIRECT is ≈ €3,619.98 known, essentially the same as the one-box V EIGHTEEN route.
A66: SUPPLIER / SOURCING UPDATE — 2026-09-10
A67: Current clean Full-15 HELIX-DE basket | B67: ='Supplier_Stage_Plan'!C8
A68: Current Core-Music-9 HELIX-DE basket | B68: ='Supplier_Stage_Plan'!C5
A69: Effect / immersion 6 positions later | B69: ='Supplier_Stage_Plan'!C6
A70: Budget-saving staged option | B70: ='Supplier_Stage_Plan'!C10
A71: NL vs DE speaker rule | B71: For i3/i5 and the Highland-specific package, genuine HELIX from Germany is preferred when price is equal/close and stock is available. For i7-class positions, BOXMORE BXS can save materially and deserves selective consideration, but only after exact SKU fit/impedance/accessory verification; do not assume 100% identity from family naming alone.
A72: Supplier state | B72: Schut: BOXMORE/HELIX relationship + connector variability + optional-effect-speaker recommendation. MB Car Audio: no guaranteed 2026 PnP package yet; harness repinning/physical verification advised. Van Hemert: request sent / response pending in captured project data. Bünde: online genuine-HELIX sourcing checked; supplier reply not captured.
A73: Pioneer power/inrush | B73: Previous Tesla field result: direct high-inrush amplifier connection caused VCFRONT / “cannot maintain DC power”; SSR-based switching solved the operational fault. Treat inrush switching and absolute 15.5 V vs Pioneer 15.1 V supply compatibility as two separate engineering gates.
A75: SUBWOOFER AMPLIFIER OPTIONS — v1.9
A76: Current preferred replacement candidate | B76: MATCH UP 1FX — €299 planning price; 10.5–18 V operating range; 1 × 900 W RMS @ 1 Ω; compact; RCA input; DirectDSP capable. Series-driver wiring / load verification REQUIRED.
A77: Critical driver-load evidence | B77: Pioneer Europe lists TS-WX1220AH complete-system impedance as 0.3 Ω; Pioneer Middle East specifies 0.6 Ω × 2. This is consistent with two 0.6 Ω SVC drivers used in parallel in the original active enclosure. Verify each loose driver before rewiring.
A78: No direct replacement at original wiring | B78: UP 1FX, HELIX M ONE and M ONE X are 1 Ω stable, not 0.3 Ω stable. Do not connect them to the original ~0.3 Ω parallel load.
A79: Likely compatible topology after verification | B79: 2 × ~0.6 Ω Pioneer SVC drivers in SERIES → ~1.2 Ω nominal → candidate load for a 1 Ω-stable mono amplifier. Confirm actual drivers / DCR and preferably dealer or manufacturer approval before final connection.
A80: Full-15 + MATCH UP 1FX | B80: ='Supplier_Stage_Plan'!C8+299
A81: Full-15, DIRECTOR deferred + MATCH UP 1FX | B81: ='Supplier_Stage_Plan'!C9+299
A82: Brand-pure HELIX alternative | B82: HELIX M ONE €299 (600 W RMS @1 Ω) or M ONE X €379 (1030 W RMS @1 Ω). Both allow 10.5–16 V, so 15.5 V nominal Tesla is inside range but with less upper-voltage margin than the UP 1FX 18 V ceiling.
A84: V2.0 FINAL SOP9 ASSET INTEGRATION — 2026-09-10
A85: Source capture | B85: Tesla_Model3_SOP9_audio_assets_2026-09-10T11-50-37-616Z.zip; Collector v1.1.6; 241 packaged assets.
A86: Integrity | B86: 241/241 manifest assets match declared byte size and SHA-256. Source ZIP container integrity also passed.
A87: Core evidence | B87: Audio-LHD SVG, Audio-Premium Amp SVG, connector reference export and all three Tesla index CSVs are captured.
A88: Target metadata | B88: 15/15 target speaker endpoint metadata records available.
A89: Target faceviews | B89: 15/15 target endpoints resolved through 3 unique terminal faceview files.
A90: Target location images | B90: 14/15 combined: 12 current collector + X586/X595 prior built-in. X566 location JPG remains unavailable (HTTP 403).
A91: Release decision | B91: Engineering package may move to v2.0. Remaining gaps are physical-vehicle verification and installation decisions, not missing core reference data.
A93: v2.1.0 — MB CAR AUDIO QUOTE / AUDISON ROUTE / EU PRICE UPDATE
A94: Received quote | B94: €4,010.90 hardware only; no cables, damping/materials or labour. DIY installation.
A95: Architecture | B95: AF M8.14 bit = front; AF M4D = rear of front seats; AF M1D = donor-sub amplifier candidate; X569/X579 omit for music.
A96: Tuning | B96: MB field experience: ~3h Audison vs ~8h HELIX. Manufacturer review corrects HELIX “fully manual” claim: DSP PC-Tool 6 contains TuneEQ/TuneToTarget/ATM automation, but not an equivalent fully automatic end-to-end system tune.
A97: Pricing | B97: New EU_Price_Matrix_v2.1 covers every identifiable SKU in the workbook and explicitly flags missing NL/DE/BE/FR local offers rather than inventing prices.

Sheet MB_Channel_Map_v2.1
A1: MB Car Audio architecture — confirmed conversation mapping
A2: This sheet separates installer-confirmed routing from engineering assumptions. No invented per-pin channel assignment is used.
A4: Zone | B4: Primary hardware | C4: Speaker/load group | D4: Status | E4: Installer evidence | F4: DSP/amp implication | G4: SOP9 decision | H4: Open verification | I4: Source type | J4: Notes
A5: Front | B5: Audison AF M8.14 bit | C5: Everything in front / front stage | D5: CONFIRMED | E5: MB: main DSP handles everything at the front | F5: Main DSP + front amplifier | G5: KEEP | H5: Exact Focal-to-SOP9 per-channel map / crossovers | I5: Installer conversation | J5: Center ICC remains a front-stage component.
A6: Rear | B6: Audison AF M4D | C6: Rear woofers + rear midranges | D6: CONFIRMED | E6: MB: M4D intended for everything behind front seats | F6: 4-channel rear companion amp | G6: KEEP | H6: Exact grouping/passive crossover topology | I6: Installer conversation | J6: Optional rear tweeters only if desired.
A7: Rear optional | B7: Audison AF M4D | C7: Additional rear tweeters | D7: OPTIONAL | E7: MB explicitly mentioned as optional | F7: Would share/group rear architecture as engineered | G7: OPTIONAL | H7: Whether used at all; final channel/load map | I7: Installer conversation | J7: Do not consume channels without acoustic reason.
A8: Sub | B8: Audison AF M1D | C8: 2 × Pioneer TS-WX1220AH donor woofers | D8: PROVISIONAL / HIGH CONFIDENCE | E8: Conversation indicates donor woofers are retained and likely driven by one Audison amp | F8: Dedicated mono sub amp | G8: KEEP DONOR DRIVERS | H8: Measure each loose donor driver DCR/impedance and confirm series/parallel load before connection | I8: Installer conversation + engineering inference | J8: Do not reuse earlier assumed Pioneer load without measurement.
A9: Upper/headliner immersive | B9: OMIT | C9: X569 / X579 upper center/headliner music positions | D9: CONFIRMED RECOMMENDATION | E9: MB and previous installer independently advised omission for music | F9: No amplifier channels reserved | G9: OMIT FOR MUSIC | H9: None unless later cinematic/immersive experiment requested | I9: Two installer recommendations | J9: Reported OEM use is minimal for music; mainly immersive/movie context.
A10: Dashboard center | B10: Audison AF M8.14 bit + Focal ICC T3Y 100 | C10: Center stage | D10: KEEP | E10: ICC is included in actual MB hardware quote | F10: Front-stage DSP channel | G10: KEEP | H10: Final level/EQ and exact SOP9 connector | I10: Quote + installer architecture | J10: Not the same as the omitted upper/headliner immersive speakers.
A11: Tesla interface | B11: MATCH PP-TES 1.7B Highland | C11: OEM signal harness basis | D11: CONFIRMED PRODUCT / CUSTOM AUDISON USE | E11: Quoted by MB | F11: Interposer requires Audison-side engineering | G11: KEEP | H11: Pinout/repin and signal mapping | I11: Quote + manufacturer docs | J11: Manufacturer officially specifies UP10DSP use; Audison use is custom.

Sheet DSP_Tuning_Compare
A1: DSP tuning comparison — Audison vs HELIX
A2: Manufacturer capabilities are separated from MB Car Audio field experience. The earlier claim “HELIX is purely manual” is corrected: HELIX has automation, but not an equivalent fully automatic end-to-end workflow.
A4: Aspect | B4: Audison / bit Drive 3.1 + ACCORDO | C4: HELIX / DSP PC-Tool 6 | D4: Assessment | E4: Evidence type | F4: Audison source | G4: HELIX source | H4: Checked | I4: Notes
A5: Measurement microphone | B5: Supported USB measurement microphones / interfaces | C5: Supported measurement workflow | D5: Both support acoustic measurement | E5: Manufacturer | F5: https://audison.com/bit-drive-3-1/ | G5: https://www.audiotec-fischer.de/en/tools/dsp-pc-tool/download-6 | H5: 2026-09-10 | I5: Use a calibrated microphone and correct mic file where applicable.
A6: Automatic output EQ | B6: ACCORDO automatically tunes output EQ | C6: TuneEQ / TuneToTarget provide assisted/automatic EQ functions | D6: Both have EQ automation | E6: Manufacturer | F6: https://audison.zendesk.com/hc/en-gb/articles/35741332904465-bit-Drive-User-manual | G6: https://www.audiotec-fischer.de/en/tools/dsp-pc-tool/download-6 | H6: 2026-09-10 | I6: HELIX is not correctly described as “measurement only”.
A7: Automatic time alignment / delay | B7: ACCORDO calculates/tunes delays as part of automatic tune | C7: DSP PC-Tool 6 includes Automatic Time Measurement / assisted time workflow | D7: Audison more integrated in one workflow | E7: Manufacturer | F7: https://audison.zendesk.com/hc/en-gb/articles/35741332904465-bit-Drive-User-manual | G7: https://www.audiotec-fischer.de/en/tools/dsp-pc-tool/download-6 | H7: 2026-09-10 | I7: Exact final workflow still depends on system topology.
A8: Automatic output levels | B8: ACCORDO tunes output levels and system level calibration | C8: TuneToTarget includes automatic output level adjustment; final calibration still specialist-driven | D8: Both automate levels to a degree; Audison positions ACCORDO as fuller auto-tune | E8: Manufacturer | F8: https://audison.com/bit-drive-3-1/ | G8: https://www.audiotec-fischer.de/en/tools/dsp-pc-tool/download-6 | H8: 2026-09-10 | I8: Avoid “HELIX cannot auto-adjust anything”.
A9: Fully automatic claim | B9: Audison explicitly markets ACCORDO as automatic system tuning | C9: Audiotec Fischer explicitly describes TuneToTarget as partially automated, not a fully automatic tuning system | D9: Meaningful Audison workflow advantage | E9: Manufacturer | F9: https://audison.com/bit-drive-3-1/ | G9: https://www.audiotec-fischer.de/en/tools/dsp-pc-tool/download-6 | H9: 2026-09-10 | I9: HELIX still expects correct crossovers, polarity, time alignment preparation and expert final calibration.
A10: Typical installer tuning time | B10: ~3 hours average | C10: ~8 hours average | D10: ~5 h practical delta in MB experience | E10: MB Car Audio field experience | H10: 2026-09-10 | I10: Not a manufacturer benchmark or guaranteed project duration.
A11: Preset handling | B11: Each setup/preset still needs final validation | C11: Each setup/preset still needs final validation | D11: Do not assume one tune covers every listening target automatically | E11: Engineering | H11: 2026-09-10 | I11: Keep measurement evidence per final preset.

Sheet EU_Price_Matrix_v2.1
A1: EU price matrix v2.1 — NL / DE / BE / FR
A2: Snapshot 2026-09-10. “Average” = average of available lowest observed market prices (one low per country), not a statistical market-wide average. Blank market = no sufficiently reliable current indexed local offer captured. Shipping/checkout/stock remain final-order checks.
A4: Priority | B4: Product | C4: Category | D4: In MB quote | E4: Qty | F4: MB quote €/unit | G4: NL low € | H4: NL seller | I4: NL source | J4: DE low € | K4: DE seller | L4: DE source | M4: BE low € | N4: BE seller | O4: BE source | P4: FR low € | Q4: FR seller | R4: FR source | S4: Cheapest € | T4: Cheapest market | U4: Avg country-low € | V4: Country coverage | W4: Saving vs MB / unit | X4: Saving vs MB total | Y4: Checked | Z4: Confidence | AA4: Price action | AB4: Notes | AC4: Documentation / official source | AD4: Purchase relevance
A5: A | B5: Audison AF LINK | C5: Interconnect | D5: YES | E5: 1 | F5: 18.95 | G5: 18.95 | H5: MB Car Audio quote | I5: Reference_Assets/MB_Car_Audio_Proposal_2026-09-10/MB_Car_Audio_quote_cart_2026-09-10.png | K5: NO CURRENT INDEXED LOCAL OFFER FOUND | N5: NO CURRENT INDEXED LOCAL OFFER FOUND | P5: 29.9 | Q5: Multison | R5: https://multison.fr/products/audison-af-link-cable-cable-de-liaison-pour-amplificateurs-af-bit-et-af-d | S5: =IF(COUNT(G5,J5,M5,P5)=0,"",MIN(G5,J5,M5,P5)) | T5: =IF(S5="","",IF(G5=S5,"NL",IF(J5=S5,"DE",IF(M5=S5,"BE","FR")))) | U5: =IF(COUNT(G5,J5,M5,P5)=0,"",AVERAGE(G5,J5,M5,P5)) | V5: =COUNT(G5,J5,M5,P5) | W5: =IF(OR(F5="",S5=""),"",F5-S5) | X5: =IF(OR(E5="",W5=""),"",E5*W5) | Y5: 2026-09-10 | Z5: MEDIUM | AA5: KEEP MB / CONVENIENCE | AC5: https://audison.com/ | AD5: CURRENT MB QUOTE
A6: A | B6: Audison AF M1D | C6: Sub amplifier | D6: YES | E6: 1 | F6: 599 | G6: 599 | H6: MB Car Audio quote | I6: Reference_Assets/MB_Car_Audio_Proposal_2026-09-10/MB_Car_Audio_quote_cart_2026-09-10.png | J6: 595.9 | K6: Audiomativ | L6: https://www.audiomativ.de/Car-HiFi-Navigation/Endstufen/1-Kanal/ | N6: NO CURRENT INDEXED LOCAL OFFER FOUND | P6: 599 | Q6: Sebasto / Multison | R6: https://multison.fr/ | S6: =IF(COUNT(G6,J6,M6,P6)=0,"",MIN(G6,J6,M6,P6)) | T6: =IF(S6="","",IF(G6=S6,"NL",IF(J6=S6,"DE",IF(M6=S6,"BE","FR")))) | U6: =IF(COUNT(G6,J6,M6,P6)=0,"",AVERAGE(G6,J6,M6,P6)) | V6: =COUNT(G6,J6,M6,P6) | W6: =IF(OR(F6="",S6=""),"",F6-S6) | X6: =IF(OR(E6="",W6=""),"",E6*W6) | Y6: 2026-09-10 | Z6: MEDIUM | AA6: SPLIT-BUY CANDIDATE | AB6: Provisional donor-sub role; driver load verification required. | AC6: https://audison.com/product/af-m1d/ | AD6: CURRENT MB QUOTE
A7: A | B7: Audison AF M4D | C7: Amplifier | D7: YES | E7: 1 | F7: 599 | G7: 599 | H7: MB Car Audio quote | I7: Reference_Assets/MB_Car_Audio_Proposal_2026-09-10/MB_Car_Audio_quote_cart_2026-09-10.png | J7: 462.48 | K7: Audiomativ | L7: https://www.audiomativ.de/Marken-Shop/AUDISON/4-Kanal-Endstufen/ | N7: NO CURRENT INDEXED LOCAL OFFER FOUND | P7: 649 | Q7: Multison | R7: https://multison.fr/ | S7: =IF(COUNT(G7,J7,M7,P7)=0,"",MIN(G7,J7,M7,P7)) | T7: =IF(S7="","",IF(G7=S7,"NL",IF(J7=S7,"DE",IF(M7=S7,"BE","FR")))) | U7: =IF(COUNT(G7,J7,M7,P7)=0,"",AVERAGE(G7,J7,M7,P7)) | V7: =COUNT(G7,J7,M7,P7) | W7: =IF(OR(F7="",S7=""),"",F7-S7) | X7: =IF(OR(E7="",W7=""),"",E7*W7) | Y7: 2026-09-10 | Z7: MEDIUM | AA7: SPLIT-BUY CANDIDATE | AC7: https://audison.com/product/af-m4d/ | AD7: CURRENT MB QUOTE
A8: A | B8: Audison AF M8.14 bit | C8: DSP amplifier | D8: YES | E8: 1 | F8: 1199 | G8: 1199 | H8: AutoSound24 / ACR | I8: https://www.autosound24.nl/producten/AUD-DSPAMP-AF-M8-14BIT | J8: 1049 | K8: Audiomativ / Idealo | L8: https://www.idealo.de/preisvergleich/OffersOfProduct/203732550_-af-m8-14-bit-audison.html | N8: NO CURRENT INDEXED LOCAL OFFER FOUND | P8: 999 | Q8: Sebasto | R8: https://www.sebastoautoradio.net/amplificateur-8-canaux-dsp-hi-res-audison-af-m8-14bit.html | S8: =IF(COUNT(G8,J8,M8,P8)=0,"",MIN(G8,J8,M8,P8)) | T8: =IF(S8="","",IF(G8=S8,"NL",IF(J8=S8,"DE",IF(M8=S8,"BE","FR")))) | U8: =IF(COUNT(G8,J8,M8,P8)=0,"",AVERAGE(G8,J8,M8,P8)) | V8: =COUNT(G8,J8,M8,P8) | W8: =IF(OR(F8="",S8=""),"",F8-S8) | X8: =IF(OR(E8="",W8=""),"",E8*W8) | Y8: 2026-09-10 | Z8: HIGH | AA8: SPLIT-BUY CANDIDATE | AC8: https://audison.com/product/af-m8-14-bit/ | AD8: CURRENT MB QUOTE
A9: A | B9: Audison DRC AC | C9: Controller | D9: YES | E9: 1 | F9: 129 | G9: 129 | H9: MB Car Audio / CarCenterHifi | I9: https://mbcaraudio.nl/bass-controls/audison-drc-ac.html | J9: 129 | K9: Caraudio-Store / justSOUND | L9: https://www.caraudio-store.de/Pegelfernbedienung | N9: NO CURRENT INDEXED LOCAL OFFER FOUND | P9: 129 | Q9: Elettromedia EU store | R9: https://store.elettromedia.com/drc-ac/ | S9: =IF(COUNT(G9,J9,M9,P9)=0,"",MIN(G9,J9,M9,P9)) | T9: =IF(S9="","",IF(G9=S9,"NL",IF(J9=S9,"DE",IF(M9=S9,"BE","FR")))) | U9: =IF(COUNT(G9,J9,M9,P9)=0,"",AVERAGE(G9,J9,M9,P9)) | V9: =COUNT(G9,J9,M9,P9) | W9: =IF(OR(F9="",S9=""),"",F9-S9) | X9: =IF(OR(E9="",W9=""),"",E9*W9) | Y9: 2026-09-10 | Z9: HIGH | AA9: KEEP MB / CONVENIENCE | AC9: https://audison.com/fr/product/drc-ac/ | AD9: CURRENT MB QUOTE
A10: A | B10: Focal IC T3Y 100 | C10: Speaker | D10: YES | E10: 1 | F10: 319 | G10: 319 | H10: MB Car Audio | I10: https://mbcaraudio.nl/autospecifieke-pasklare-speakersets/focal-ic-t3y-100.html | J10: 219 | K10: Idealo | L10: https://www.idealo.de/preisvergleich/OffersOfProduct/204105665_-ic-t3y-100-focal.html | N10: NO CURRENT INDEXED LOCAL OFFER FOUND | P10: 229 | Q10: Sebasto / Multison | R10: https://www.sebastoautoradio.net/haut-parleurs-2-voies-coaxiaux-specifique-tesla-focal-ic-t3y-100.html | S10: =IF(COUNT(G10,J10,M10,P10)=0,"",MIN(G10,J10,M10,P10)) | T10: =IF(S10="","",IF(G10=S10,"NL",IF(J10=S10,"DE",IF(M10=S10,"BE","FR")))) | U10: =IF(COUNT(G10,J10,M10,P10)=0,"",AVERAGE(G10,J10,M10,P10)) | V10: =COUNT(G10,J10,M10,P10) | W10: =IF(OR(F10="",S10=""),"",F10-S10) | X10: =IF(OR(E10="",W10=""),"",E10*W10) | Y10: 2026-09-10 | Z10: MEDIUM | AA10: SPLIT-BUY CANDIDATE | AC10: https://www.focal.com/products/ic-t3y-100 | AD10: CURRENT MB QUOTE
A11: A | B11: Focal ICC T3Y 100 | C11: Speaker | D11: YES | E11: 1 | F11: 179 | G11: 179 | H11: MB Car Audio | I11: https://mbcaraudio.nl/autospecifieke-pasklare-speakersets/focal-icc-t3y-100.html | J11: 149 | K11: Idealo | L11: https://www.idealo.de/preisvergleich/OffersOfProduct/204855027_-inside-icc-t3y-100-focal.html | N11: NO CURRENT INDEXED LOCAL OFFER FOUND | P11: 129 | Q11: Sebasto | R11: https://www.sebastoautoradio.net/voies-centrale-specifique-tesla-focal-icc-t3y-100.html | S11: =IF(COUNT(G11,J11,M11,P11)=0,"",MIN(G11,J11,M11,P11)) | T11: =IF(S11="","",IF(G11=S11,"NL",IF(J11=S11,"DE",IF(M11=S11,"BE","FR")))) | U11: =IF(COUNT(G11,J11,M11,P11)=0,"",AVERAGE(G11,J11,M11,P11)) | V11: =COUNT(G11,J11,M11,P11) | W11: =IF(OR(F11="",S11=""),"",F11-S11) | X11: =IF(OR(E11="",W11=""),"",E11*W11) | Y11: 2026-09-10 | Z11: HIGH | AA11: SPLIT-BUY CANDIDATE | AC11: https://www.focal.com/products/icc-t3y-100 | AD11: CURRENT MB QUOTE
A12: A | B12: Focal IS T3Y 100 | C12: Speaker | D12: YES | E12: 1 | F12: 369 | G12: 369 | H12: MB Car Audio | I12: https://mbcaraudio.nl/autospecifieke-pasklare-speakersets/focal-is-t3y-100.html | J12: 289 | K12: Idealo current T3Y comparison | L12: https://www.idealo.de/preisvergleich/Liste/123511081/focal-t3y.html | N12: NO CURRENT INDEXED LOCAL OFFER FOUND | P12: 299 | Q12: Sebasto / Multison | R12: https://www.sebastoautoradio.net/kit-2-voies-specifique-tesla-focal-is-t3y-100.html | S12: =IF(COUNT(G12,J12,M12,P12)=0,"",MIN(G12,J12,M12,P12)) | T12: =IF(S12="","",IF(G12=S12,"NL",IF(J12=S12,"DE",IF(M12=S12,"BE","FR")))) | U12: =IF(COUNT(G12,J12,M12,P12)=0,"",AVERAGE(G12,J12,M12,P12)) | V12: =COUNT(G12,J12,M12,P12) | W12: =IF(OR(F12="",S12=""),"",F12-S12) | X12: =IF(OR(E12="",W12=""),"",E12*W12) | Y12: 2026-09-10 | Z12: HIGH | AA12: SPLIT-BUY CANDIDATE | AC12: https://www.focal.com/products/is-t3y-100 | AD12: CURRENT MB QUOTE
A13: A | B13: Focal IW T3Y 200 | C13: Speaker | D13: YES | E13: 1 | F13: 459 | G13: 459 | H13: MB Car Audio | I13: https://mbcaraudio.nl/autospecifieke-pasklare-speakersets/focal-iw-t3y-200.html | J13: 314.1 | K13: eBay marketplace / ACR-Hof via Idealo | L13: https://www.idealo.de/preisvergleich/OffersOfProduct/204855028_-iw-t3y-200-focal.html | N13: NO CURRENT INDEXED LOCAL OFFER FOUND | P13: 369 | Q13: Sebasto / Multison | R13: https://www.sebastoautoradio.net/woofer-20-cm-specifique-tesla-focal-iw-t3y-200.html | S13: =IF(COUNT(G13,J13,M13,P13)=0,"",MIN(G13,J13,M13,P13)) | T13: =IF(S13="","",IF(G13=S13,"NL",IF(J13=S13,"DE",IF(M13=S13,"BE","FR")))) | U13: =IF(COUNT(G13,J13,M13,P13)=0,"",AVERAGE(G13,J13,M13,P13)) | V13: =COUNT(G13,J13,M13,P13) | W13: =IF(OR(F13="",S13=""),"",F13-S13) | X13: =IF(OR(E13="",W13=""),"",E13*W13) | Y13: 2026-09-10 | Z13: MEDIUM | AA13: SPLIT-BUY CANDIDATE | AC13: https://www.focal.com/products/iw-t3y-200 | AD13: CURRENT MB QUOTE
A14: A | B14: HELIX Compose Ci3 K200.2TES4 Highland | C14: Speaker kit | D14: NO | H14: NO CURRENT INDEXED LOCAL OFFER FOUND | J14: 729 | K14: CarHifi-Store Bünde | L14: https://www.carhifi-store-buende.de/compose-ci3-k200.2tes4-tesla-model-3-highland | N14: NO CURRENT INDEXED LOCAL OFFER FOUND | Q14: NO CURRENT INDEXED LOCAL OFFER FOUND | S14: =IF(COUNT(G14,J14,M14,P14)=0,"",MIN(G14,J14,M14,P14)) | T14: =IF(S14="","",IF(G14=S14,"NL",IF(J14=S14,"DE",IF(M14=S14,"BE","FR")))) | U14: =IF(COUNT(G14,J14,M14,P14)=0,"",AVERAGE(G14,J14,M14,P14)) | V14: =COUNT(G14,J14,M14,P14) | W14: =IF(OR(F14="",S14=""),"",F14-S14) | X14: =IF(OR(E14="",W14=""),"",E14*W14) | Y14: 2026-09-10 | Z14: HIGH | AA14: COMPARE / VERIFY CHECKOUT | AC14: https://www.audiotec-fischer.de/en/helix/ | AD14: CURRENT COMPARISON
A15: A | B15: HELIX V EIGHTEEN DSP | C15: DSP amplifier | D15: NO | G15: 1799 | H15: ACR / Schut | I15: https://www.acr-helmond.nl/ | J15: 1799 | K15: CarHifi-Store Bünde | L15: https://www.carhifi-store-buende.de/endstufen/ | M15: 1799 | N15: HifiMotive dealer network | O15: https://www.caraudio.nl/artikel/helix/helix-v-eighteen-dsp-18-kanaals-versterker-met-20-kanaals-dsp-heveighteen | P15: 1799 | Q15: FR-deliverable ARS24 / Type-RSound reference | R15: https://www.ars24.com/en/helix-verstaerker-made-in-germany | S15: =IF(COUNT(G15,J15,M15,P15)=0,"",MIN(G15,J15,M15,P15)) | T15: =IF(S15="","",IF(G15=S15,"NL",IF(J15=S15,"DE",IF(M15=S15,"BE","FR")))) | U15: =IF(COUNT(G15,J15,M15,P15)=0,"",AVERAGE(G15,J15,M15,P15)) | V15: =COUNT(G15,J15,M15,P15) | W15: =IF(OR(F15="",S15=""),"",F15-S15) | X15: =IF(OR(E15="",W15=""),"",E15*W15) | Y15: 2026-09-10 | Z15: MEDIUM | AA15: COMPARE / VERIFY CHECKOUT | AB15: Full-active HELIX comparison route. | AC15: https://www.audiotec-fischer.de/en/helix/ | AD15: CURRENT COMPARISON
A16: A | B16: MATCH PP-TES 1.7B Highland | C16: Tesla harness | D16: YES | E16: 1 | F16: 139.95 | G16: 129 | H16: HifiMotive | I16: https://www.caraudio.nl/artikel/match/match-pp-tes-1-7b-highland-kabelset-voor-tesla-model-3-highland-y-juniper-met-base-audio-mapptes17bhl | J16: 129 | K16: Caraudio-Store / Bünde | L16: https://www.caraudio-store.de/Match-PP-TES-17B-Highland | N16: NO CURRENT INDEXED LOCAL OFFER FOUND | Q16: NO CURRENT INDEXED LOCAL OFFER FOUND | S16: =IF(COUNT(G16,J16,M16,P16)=0,"",MIN(G16,J16,M16,P16)) | T16: =IF(S16="","",IF(G16=S16,"NL",IF(J16=S16,"DE",IF(M16=S16,"BE","FR")))) | U16: =IF(COUNT(G16,J16,M16,P16)=0,"",AVERAGE(G16,J16,M16,P16)) | V16: =COUNT(G16,J16,M16,P16) | W16: =IF(OR(F16="",S16=""),"",F16-S16) | X16: =IF(OR(E16="",W16=""),"",E16*W16) | Y16: 2026-09-10 | Z16: HIGH | AA16: SPLIT-BUY CANDIDATE | AB16: Official PnP target is MATCH UP10DSP; Audison use requires custom integration. | AC16: https://www.audiotec-fischer.de/en/match/adaptors-harnesses/pp-tes-1-7b-highland | AD16: CURRENT MB QUOTE
A17: A | B17: Pioneer TS-WX1220AH | C17: Existing donor sub system | D17: NO | H17: NO CURRENT INDEXED LOCAL OFFER FOUND | K17: NO CURRENT INDEXED LOCAL OFFER FOUND | N17: NO CURRENT INDEXED LOCAL OFFER FOUND | Q17: NO CURRENT INDEXED LOCAL OFFER FOUND | S17: =IF(COUNT(G17,J17,M17,P17)=0,"",MIN(G17,J17,M17,P17)) | T17: =IF(S17="","",IF(G17=S17,"NL",IF(J17=S17,"DE",IF(M17=S17,"BE","FR")))) | U17: =IF(COUNT(G17,J17,M17,P17)=0,"",AVERAGE(G17,J17,M17,P17)) | V17: =COUNT(G17,J17,M17,P17) | W17: =IF(OR(F17="",S17=""),"",F17-S17) | X17: =IF(OR(E17="",W17=""),"",E17*W17) | Y17: 2026-09-10 | Z17: NO PRICE | AA17: COMPARE / VERIFY CHECKOUT | AB17: Owned donor hardware: online price is reference only, not purchase requirement. | AC17: https://pioneer-car.eu/nl/nl/ts-wx1220ah/ts-wx1220ah | AD17: CURRENT COMPARISON
A18: B | B18: Audison AF M12.14 bit | C18: DSP amplifier | D18: NO | G18: 1289 | H18: AutoSound24 | I18: https://www.autosound24.nl/producten/AUD-DSPAMP-AF-M12-14BIT | J18: 1205.9 | K18: Idealo / justSOUND | L18: https://www.idealo.de/preisvergleich/OffersOfProduct/203736270_-af-m12-14-bit-audison.html | N18: NO CURRENT INDEXED LOCAL OFFER FOUND | P18: 1290 | Q18: Elettromedia | R18: https://store.elettromedia.com/af-m12-14-bit/ | S18: =IF(COUNT(G18,J18,M18,P18)=0,"",MIN(G18,J18,M18,P18)) | T18: =IF(S18="","",IF(G18=S18,"NL",IF(J18=S18,"DE",IF(M18=S18,"BE","FR")))) | U18: =IF(COUNT(G18,J18,M18,P18)=0,"",AVERAGE(G18,J18,M18,P18)) | V18: =COUNT(G18,J18,M18,P18) | W18: =IF(OR(F18="",S18=""),"",F18-S18) | X18: =IF(OR(E18="",W18=""),"",E18*W18) | Y18: 2026-09-10 | Z18: MEDIUM | AA18: COMPARE / VERIFY CHECKOUT | AB18: Historical/alternative route retained. | AC18: https://audison.com/ | AD18: CURRENT COMPARISON
A19: B | B19: Audison DRC MP CAN | C19: Controller | D19: NO | G19: 179 | H19: MB Car Audio / ACR | I19: https://mbcaraudio.nl/bass-controls/audison-drc-mp-can.html | K19: NO CURRENT INDEXED LOCAL OFFER FOUND | N19: NO CURRENT INDEXED LOCAL OFFER FOUND | Q19: NO CURRENT INDEXED LOCAL OFFER FOUND | S19: =IF(COUNT(G19,J19,M19,P19)=0,"",MIN(G19,J19,M19,P19)) | T19: =IF(S19="","",IF(G19=S19,"NL",IF(J19=S19,"DE",IF(M19=S19,"BE","FR")))) | U19: =IF(COUNT(G19,J19,M19,P19)=0,"",AVERAGE(G19,J19,M19,P19)) | V19: =COUNT(G19,J19,M19,P19) | W19: =IF(OR(F19="",S19=""),"",F19-S19) | X19: =IF(OR(E19="",W19=""),"",E19*W19) | Y19: 2026-09-10 | Z19: HIGH | AA19: COMPARE / VERIFY CHECKOUT | AC19: https://audison.com/ | AD19: CURRENT COMPARISON
A20: B | B20: HELIX AMPLIFY 204 DIRECT | C20: Amplifier | D20: NO | G20: 239 | H20: HifiMotive | I20: https://www.caraudio.nl/assortiment/helix | J20: 239 | K20: DE marketplace / comparison | L20: https://www.idealo.de/ | N20: NO CURRENT INDEXED LOCAL OFFER FOUND | Q20: NO CURRENT INDEXED LOCAL OFFER FOUND | S20: =IF(COUNT(G20,J20,M20,P20)=0,"",MIN(G20,J20,M20,P20)) | T20: =IF(S20="","",IF(G20=S20,"NL",IF(J20=S20,"DE",IF(M20=S20,"BE","FR")))) | U20: =IF(COUNT(G20,J20,M20,P20)=0,"",AVERAGE(G20,J20,M20,P20)) | V20: =COUNT(G20,J20,M20,P20) | W20: =IF(OR(F20="",S20=""),"",F20-S20) | X20: =IF(OR(E20="",W20=""),"",E20*W20) | Y20: 2026-09-10 | Z20: MEDIUM | AA20: COMPARE / VERIFY CHECKOUT | AC20: https://www.audiotec-fischer.de/en/helix/ | AD20: CURRENT COMPARISON
A21: B | B21: HELIX AMPLIFY 206 DIRECT | C21: Amplifier | D21: NO | G21: 358.99 | H21: HifiMotive | I21: https://www.caraudio.nl/assortiment/helix | J21: 359 | K21: ARS24 | L21: https://www.ars24.com/en/6-kanal-verstaerker/auto-endstufen | N21: NO CURRENT INDEXED LOCAL OFFER FOUND | Q21: NO CURRENT INDEXED LOCAL OFFER FOUND | S21: =IF(COUNT(G21,J21,M21,P21)=0,"",MIN(G21,J21,M21,P21)) | T21: =IF(S21="","",IF(G21=S21,"NL",IF(J21=S21,"DE",IF(M21=S21,"BE","FR")))) | U21: =IF(COUNT(G21,J21,M21,P21)=0,"",AVERAGE(G21,J21,M21,P21)) | V21: =COUNT(G21,J21,M21,P21) | W21: =IF(OR(F21="",S21=""),"",F21-S21) | X21: =IF(OR(E21="",W21=""),"",E21*W21) | Y21: 2026-09-10 | Z21: HIGH | AA21: COMPARE / VERIFY CHECKOUT | AC21: https://www.audiotec-fischer.de/en/helix/ | AD21: CURRENT COMPARISON
A22: B | B22: HELIX AMPLIFY 206 DSP | C22: DSP amplifier | D22: NO | H22: NO CURRENT INDEXED LOCAL OFFER FOUND | J22: 599 | K22: ARS24 | L22: https://www.ars24.com/en/helix-amplify-206-dsp | N22: NO CURRENT INDEXED LOCAL OFFER FOUND | P22: 599 | Q22: FR-deliverable reference | R22: https://www.ars24.com/en/helix-amplify-206-dsp | S22: =IF(COUNT(G22,J22,M22,P22)=0,"",MIN(G22,J22,M22,P22)) | T22: =IF(S22="","",IF(G22=S22,"NL",IF(J22=S22,"DE",IF(M22=S22,"BE","FR")))) | U22: =IF(COUNT(G22,J22,M22,P22)=0,"",AVERAGE(G22,J22,M22,P22)) | V22: =COUNT(G22,J22,M22,P22) | W22: =IF(OR(F22="",S22=""),"",F22-S22) | X22: =IF(OR(E22="",W22=""),"",E22*W22) | Y22: 2026-09-10 | Z22: MEDIUM | AA22: COMPARE / VERIFY CHECKOUT | AC22: https://www.audiotec-fischer.de/en/helix/ | AD22: CURRENT COMPARISON
A23: B | B23: HELIX Ci3 M100FM-S3 | C23: Speaker | D23: NO | H23: NO CURRENT INDEXED LOCAL OFFER FOUND | J23: 159 | K23: CarHifi-Store Bünde | L23: https://www.carhifi-store-buende.de/helix-ci3-m100fm-s3 | N23: NO CURRENT INDEXED LOCAL OFFER FOUND | P23: 149 | Q23: Type-RSound FR-facing | R23: https://www.type-rsound.com/en/helix-ci3-m100fm-s3.html | S23: =IF(COUNT(G23,J23,M23,P23)=0,"",MIN(G23,J23,M23,P23)) | T23: =IF(S23="","",IF(G23=S23,"NL",IF(J23=S23,"DE",IF(M23=S23,"BE","FR")))) | U23: =IF(COUNT(G23,J23,M23,P23)=0,"",AVERAGE(G23,J23,M23,P23)) | V23: =COUNT(G23,J23,M23,P23) | W23: =IF(OR(F23="",S23=""),"",F23-S23) | X23: =IF(OR(E23="",W23=""),"",E23*W23) | Y23: 2026-09-10 | Z23: MEDIUM | AA23: COMPARE / VERIFY CHECKOUT | AC23: https://www.audiotec-fischer.de/en/helix/ | AD23: CURRENT COMPARISON
A24: B | B24: HELIX Ci5 M80FM-S3 | C24: Speaker | D24: NO | H24: NO CURRENT INDEXED LOCAL OFFER FOUND | J24: 199 | K24: CarHifi-Store Bünde / ARS24 | L24: https://www.carhifi-store-buende.de/helix-ci5-m80fm-s3 | N24: NO CURRENT INDEXED LOCAL OFFER FOUND | Q24: NO CURRENT INDEXED LOCAL OFFER FOUND | S24: =IF(COUNT(G24,J24,M24,P24)=0,"",MIN(G24,J24,M24,P24)) | T24: =IF(S24="","",IF(G24=S24,"NL",IF(J24=S24,"DE",IF(M24=S24,"BE","FR")))) | U24: =IF(COUNT(G24,J24,M24,P24)=0,"",AVERAGE(G24,J24,M24,P24)) | V24: =COUNT(G24,J24,M24,P24) | W24: =IF(OR(F24="",S24=""),"",F24-S24) | X24: =IF(OR(E24="",W24=""),"",E24*W24) | Y24: 2026-09-10 | Z24: HIGH | AA24: COMPARE / VERIFY CHECKOUT | AC24: https://www.audiotec-fischer.de/en/helix/ | AD24: CURRENT COMPARISON
A25: B | B25: HELIX Ci7 M100FM-S3 | C25: Speaker | D25: NO | H25: NO CURRENT INDEXED LOCAL OFFER FOUND | J25: 399 | K25: CarHifi-Store Bünde | L25: https://www.carhifi-store-buende.de/lautsprecher/helix-compose/helix-compose-i7/ | N25: NO CURRENT INDEXED LOCAL OFFER FOUND | Q25: NO CURRENT INDEXED LOCAL OFFER FOUND | S25: =IF(COUNT(G25,J25,M25,P25)=0,"",MIN(G25,J25,M25,P25)) | T25: =IF(S25="","",IF(G25=S25,"NL",IF(J25=S25,"DE",IF(M25=S25,"BE","FR")))) | U25: =IF(COUNT(G25,J25,M25,P25)=0,"",AVERAGE(G25,J25,M25,P25)) | V25: =COUNT(G25,J25,M25,P25) | W25: =IF(OR(F25="",S25=""),"",F25-S25) | X25: =IF(OR(E25="",W25=""),"",E25*W25) | Y25: 2026-09-10 | Z25: HIGH | AA25: COMPARE / VERIFY CHECKOUT | AC25: https://www.audiotec-fischer.de/en/helix/ | AD25: CURRENT COMPARISON
A26: B | B26: HELIX Ci7 T20FM-SC | C26: Tweeter | D26: NO | H26: NO CURRENT INDEXED LOCAL OFFER FOUND | J26: 399 | K26: CarHifi-Store Bünde | L26: https://www.carhifi-store-buende.de/helix-ci7-t20fm-sc | N26: NO CURRENT INDEXED LOCAL OFFER FOUND | Q26: NO CURRENT INDEXED LOCAL OFFER FOUND | S26: =IF(COUNT(G26,J26,M26,P26)=0,"",MIN(G26,J26,M26,P26)) | T26: =IF(S26="","",IF(G26=S26,"NL",IF(J26=S26,"DE",IF(M26=S26,"BE","FR")))) | U26: =IF(COUNT(G26,J26,M26,P26)=0,"",AVERAGE(G26,J26,M26,P26)) | V26: =COUNT(G26,J26,M26,P26) | W26: =IF(OR(F26="",S26=""),"",F26-S26) | X26: =IF(OR(E26="",W26=""),"",E26*W26) | Y26: 2026-09-10 | Z26: HIGH | AA26: COMPARE / VERIFY CHECKOUT | AC26: https://www.audiotec-fischer.de/en/helix/ | AD26: CURRENT COMPARISON
A27: B | B27: HELIX Ci7 W200FM-S3 | C27: Speaker | D27: NO | H27: NO CURRENT INDEXED LOCAL OFFER FOUND | J27: 509 | K27: CarHifi-Store Bünde no-grille reference | L27: https://www.carhifi-store-buende.de/lautsprecher/helix-compose/helix-compose-i7/ | N27: NO CURRENT INDEXED LOCAL OFFER FOUND | Q27: NO CURRENT INDEXED LOCAL OFFER FOUND | S27: =IF(COUNT(G27,J27,M27,P27)=0,"",MIN(G27,J27,M27,P27)) | T27: =IF(S27="","",IF(G27=S27,"NL",IF(J27=S27,"DE",IF(M27=S27,"BE","FR")))) | U27: =IF(COUNT(G27,J27,M27,P27)=0,"",AVERAGE(G27,J27,M27,P27)) | V27: =COUNT(G27,J27,M27,P27) | W27: =IF(OR(F27="",S27=""),"",F27-S27) | X27: =IF(OR(E27="",W27=""),"",E27*W27) | Y27: 2026-09-10 | Z27: HIGH | AA27: COMPARE / VERIFY CHECKOUT | AC27: https://www.audiotec-fischer.de/en/helix/ | AD27: CURRENT COMPARISON
A28: B | B28: HELIX DIRECTOR for SCP | C28: Controller | D28: NO | G28: 299 | H28: HifiMotive | I28: https://www.caraudio.nl/assortiment/helix | J28: 249 | K28: Caraudio-store / ARS24 | L28: https://www.ars24.com/en/helix-director-for-scp | N28: NO CURRENT INDEXED LOCAL OFFER FOUND | P28: 249 | Q28: ARS24 FR delivery | R28: https://www.ars24.com/en/helix-director-for-scp | S28: =IF(COUNT(G28,J28,M28,P28)=0,"",MIN(G28,J28,M28,P28)) | T28: =IF(S28="","",IF(G28=S28,"NL",IF(J28=S28,"DE",IF(M28=S28,"BE","FR")))) | U28: =IF(COUNT(G28,J28,M28,P28)=0,"",AVERAGE(G28,J28,M28,P28)) | V28: =COUNT(G28,J28,M28,P28) | W28: =IF(OR(F28="",S28=""),"",F28-S28) | X28: =IF(OR(E28="",W28=""),"",E28*W28) | Y28: 2026-09-10 | Z28: HIGH | AA28: COMPARE / VERIFY CHECKOUT | AC28: https://www.audiotec-fischer.de/en/helix/ | AD28: CURRENT COMPARISON
A29: B | B29: HELIX M ONE | C29: Sub amplifier | D29: NO | G29: 299 | H29: NL specialist reference | I29: https://www.caraudio.nl/assortiment/helix | J29: 299 | K29: CarHifi-Store Bünde | L29: https://www.carhifi-store-buende.de/endstufen/helix/ | N29: NO CURRENT INDEXED LOCAL OFFER FOUND | Q29: NO CURRENT INDEXED LOCAL OFFER FOUND | S29: =IF(COUNT(G29,J29,M29,P29)=0,"",MIN(G29,J29,M29,P29)) | T29: =IF(S29="","",IF(G29=S29,"NL",IF(J29=S29,"DE",IF(M29=S29,"BE","FR")))) | U29: =IF(COUNT(G29,J29,M29,P29)=0,"",AVERAGE(G29,J29,M29,P29)) | V29: =COUNT(G29,J29,M29,P29) | W29: =IF(OR(F29="",S29=""),"",F29-S29) | X29: =IF(OR(E29="",W29=""),"",E29*W29) | Y29: 2026-09-10 | Z29: MEDIUM | AA29: COMPARE / VERIFY CHECKOUT | AC29: https://www.audiotec-fischer.de/en/helix/ | AD29: CURRENT COMPARISON
A30: B | B30: HELIX M ONE X | C30: Sub amplifier | D30: NO | G30: 379 | H30: NL specialist reference | I30: https://www.caraudio.nl/assortiment/helix | J30: 349 | K30: DE current comparison | L30: https://www.carhifi-store-buende.de/helix-m-one-x | N30: NO CURRENT INDEXED LOCAL OFFER FOUND | Q30: NO CURRENT INDEXED LOCAL OFFER FOUND | S30: =IF(COUNT(G30,J30,M30,P30)=0,"",MIN(G30,J30,M30,P30)) | T30: =IF(S30="","",IF(G30=S30,"NL",IF(J30=S30,"DE",IF(M30=S30,"BE","FR")))) | U30: =IF(COUNT(G30,J30,M30,P30)=0,"",AVERAGE(G30,J30,M30,P30)) | V30: =COUNT(G30,J30,M30,P30) | W30: =IF(OR(F30="",S30=""),"",F30-S30) | X30: =IF(OR(E30="",W30=""),"",E30*W30) | Y30: 2026-09-10 | Z30: MEDIUM | AA30: COMPARE / VERIFY CHECKOUT | AC30: https://www.audiotec-fischer.de/en/helix/ | AD30: CURRENT COMPARISON
A31: B | B31: HELIX NEXT V EIGHT DSP ULTIMATE | C31: DSP amplifier | D31: NO | G31: 1349 | H31: ACR / Schut | I31: https://www.acr-helmond.nl/ | J31: 1349 | K31: Caraudio-Store / Audiomativ | L31: https://www.caraudio-store.de/DSP-Verstaerker | N31: NO CURRENT INDEXED LOCAL OFFER FOUND | P31: 1349 | Q31: Type-RSound FR-facing | R31: https://www.type-rsound.com/fr/categories/audio-de-voiture/amplificateur/8-canaux.html | S31: =IF(COUNT(G31,J31,M31,P31)=0,"",MIN(G31,J31,M31,P31)) | T31: =IF(S31="","",IF(G31=S31,"NL",IF(J31=S31,"DE",IF(M31=S31,"BE","FR")))) | U31: =IF(COUNT(G31,J31,M31,P31)=0,"",AVERAGE(G31,J31,M31,P31)) | V31: =COUNT(G31,J31,M31,P31) | W31: =IF(OR(F31="",S31=""),"",F31-S31) | X31: =IF(OR(E31="",W31=""),"",E31*W31) | Y31: 2026-09-10 | Z31: MEDIUM | AA31: COMPARE / VERIFY CHECKOUT | AC31: https://www.audiotec-fischer.de/en/helix/ | AD31: CURRENT COMPARISON
A32: B | B32: HELIX V TWELVE DSP MK2 | C32: DSP amplifier | D32: NO | G32: 1499 | H32: ACR Helmond / Schut | I32: https://www.acr-helmond.nl/helix-v-twelve-dsp-mk2.htm | J32: 1499 | K32: Caraudio-Store / ARS24 | L32: https://www.caraudio-store.de/Helix-V-TWELVE-DSP-MK2 | M32: 1499 | N32: HifiMotive dealer network | O32: https://www.caraudio.nl/assortiment/helix | P32: 1499 | Q32: ARS24 FR delivery | R32: https://www.ars24.com/en/helix-v-twelve-dsp-mk2 | S32: =IF(COUNT(G32,J32,M32,P32)=0,"",MIN(G32,J32,M32,P32)) | T32: =IF(S32="","",IF(G32=S32,"NL",IF(J32=S32,"DE",IF(M32=S32,"BE","FR")))) | U32: =IF(COUNT(G32,J32,M32,P32)=0,"",AVERAGE(G32,J32,M32,P32)) | V32: =COUNT(G32,J32,M32,P32) | W32: =IF(OR(F32="",S32=""),"",F32-S32) | X32: =IF(OR(E32="",W32=""),"",E32*W32) | Y32: 2026-09-10 | Z32: MEDIUM | AA32: COMPARE / VERIFY CHECKOUT | AC32: https://www.audiotec-fischer.de/en/helix/ | AD32: CURRENT COMPARISON
A33: B | B33: MATCH UP 10DSP MK2 | C33: DSP amplifier | D33: NO | G33: 1049 | H33: HifiMotive / ACR | I33: https://www.caraudio.nl/artikel/match-up-10dsp-mk2-10-kanaals-dsp-versterker-maup10dspmk2 | J33: 1049 | K33: ARS24 / DE sellers | L33: https://www.ars24.com/en/match-up10dsp-mk2 | N33: NO CURRENT INDEXED LOCAL OFFER FOUND | Q33: NO CURRENT INDEXED LOCAL OFFER FOUND | S33: =IF(COUNT(G33,J33,M33,P33)=0,"",MIN(G33,J33,M33,P33)) | T33: =IF(S33="","",IF(G33=S33,"NL",IF(J33=S33,"DE",IF(M33=S33,"BE","FR")))) | U33: =IF(COUNT(G33,J33,M33,P33)=0,"",AVERAGE(G33,J33,M33,P33)) | V33: =COUNT(G33,J33,M33,P33) | W33: =IF(OR(F33="",S33=""),"",F33-S33) | X33: =IF(OR(E33="",W33=""),"",E33*W33) | Y33: 2026-09-10 | Z33: HIGH | AA33: COMPARE / VERIFY CHECKOUT | AC33: https://www.audiotec-fischer.de/en/match/ | AD33: CURRENT COMPARISON
A34: B | B34: MATCH UP 1FX | C34: Sub amplifier | D34: NO | G34: 299 | H34: HifiMotive | I34: https://www.caraudio.nl/assortiment/match | J34: 299 | K34: ARS24 | L34: https://www.ars24.com/en/match-up1fx | N34: NO CURRENT INDEXED LOCAL OFFER FOUND | P34: 299 | Q34: ARS24 FR delivery | R34: https://www.ars24.com/en/match-up1fx | S34: =IF(COUNT(G34,J34,M34,P34)=0,"",MIN(G34,J34,M34,P34)) | T34: =IF(S34="","",IF(G34=S34,"NL",IF(J34=S34,"DE",IF(M34=S34,"BE","FR")))) | U34: =IF(COUNT(G34,J34,M34,P34)=0,"",AVERAGE(G34,J34,M34,P34)) | V34: =COUNT(G34,J34,M34,P34) | W34: =IF(OR(F34="",S34=""),"",F34-S34) | X34: =IF(OR(E34="",W34=""),"",E34*W34) | Y34: 2026-09-10 | Z34: MEDIUM | AA34: COMPARE / VERIFY CHECKOUT | AC34: https://www.audiotec-fischer.de/en/match/ | AD34: CURRENT COMPARISON
A35: C | B35: Audison AP 2 MV | C35: Speaker | D35: NO | G35: 119 | H35: MB Car Audio / AutoSound24 | I35: https://mbcaraudio.nl/87-cm-/audison-ap-2-mv.html | K35: NO CURRENT INDEXED LOCAL OFFER FOUND | N35: NO CURRENT INDEXED LOCAL OFFER FOUND | Q35: NO CURRENT INDEXED LOCAL OFFER FOUND | S35: =IF(COUNT(G35,J35,M35,P35)=0,"",MIN(G35,J35,M35,P35)) | T35: =IF(S35="","",IF(G35=S35,"NL",IF(J35=S35,"DE",IF(M35=S35,"BE","FR")))) | U35: =IF(COUNT(G35,J35,M35,P35)=0,"",AVERAGE(G35,J35,M35,P35)) | V35: =COUNT(G35,J35,M35,P35) | W35: =IF(OR(F35="",S35=""),"",F35-S35) | X35: =IF(OR(E35="",W35=""),"",E35*W35) | Y35: 2026-09-10 | Z35: HIGH | AA35: COMPARE / VERIFY CHECKOUT | AC35: https://audison.com/ | AD35: ALTERNATIVE / HISTORICAL
A36: C | B36: Audison AP TSL 8 | C36: Woofer | D36: NO | H36: NO CURRENT INDEXED LOCAL OFFER FOUND | K36: NO CURRENT INDEXED LOCAL OFFER FOUND | N36: NO CURRENT INDEXED LOCAL OFFER FOUND | Q36: NO CURRENT INDEXED LOCAL OFFER FOUND | S36: =IF(COUNT(G36,J36,M36,P36)=0,"",MIN(G36,J36,M36,P36)) | T36: =IF(S36="","",IF(G36=S36,"NL",IF(J36=S36,"DE",IF(M36=S36,"BE","FR")))) | U36: =IF(COUNT(G36,J36,M36,P36)=0,"",AVERAGE(G36,J36,M36,P36)) | V36: =COUNT(G36,J36,M36,P36) | W36: =IF(OR(F36="",S36=""),"",F36-S36) | X36: =IF(OR(E36="",W36=""),"",E36*W36) | Y36: 2026-09-10 | Z36: NO PRICE | AA36: COMPARE / VERIFY CHECKOUT | AC36: https://audison.com/ | AD36: ALTERNATIVE / HISTORICAL
A37: C | B37: Audison AP TSL M4M | C37: Speaker | D37: NO | H37: NO CURRENT INDEXED LOCAL OFFER FOUND | K37: NO CURRENT INDEXED LOCAL OFFER FOUND | N37: NO CURRENT INDEXED LOCAL OFFER FOUND | Q37: NO CURRENT INDEXED LOCAL OFFER FOUND | S37: =IF(COUNT(G37,J37,M37,P37)=0,"",MIN(G37,J37,M37,P37)) | T37: =IF(S37="","",IF(G37=S37,"NL",IF(J37=S37,"DE",IF(M37=S37,"BE","FR")))) | U37: =IF(COUNT(G37,J37,M37,P37)=0,"",AVERAGE(G37,J37,M37,P37)) | V37: =COUNT(G37,J37,M37,P37) | W37: =IF(OR(F37="",S37=""),"",F37-S37) | X37: =IF(OR(E37="",W37=""),"",E37*W37) | Y37: 2026-09-10 | Z37: NO PRICE | AA37: COMPARE / VERIFY CHECKOUT | AB37: Current Audison Tesla pack is historical comparison and not treated as Highland-compatible without confirmation. | AC37: https://audison.com/ | AD37: ALTERNATIVE / HISTORICAL
A38: C | B38: Audison AP TSL X4M | C38: Speaker | D38: NO | H38: NO CURRENT INDEXED LOCAL OFFER FOUND | K38: NO CURRENT INDEXED LOCAL OFFER FOUND | N38: NO CURRENT INDEXED LOCAL OFFER FOUND | Q38: NO CURRENT INDEXED LOCAL OFFER FOUND | S38: =IF(COUNT(G38,J38,M38,P38)=0,"",MIN(G38,J38,M38,P38)) | T38: =IF(S38="","",IF(G38=S38,"NL",IF(J38=S38,"DE",IF(M38=S38,"BE","FR")))) | U38: =IF(COUNT(G38,J38,M38,P38)=0,"",AVERAGE(G38,J38,M38,P38)) | V38: =COUNT(G38,J38,M38,P38) | W38: =IF(OR(F38="",S38=""),"",F38-S38) | X38: =IF(OR(E38="",W38=""),"",E38*W38) | Y38: 2026-09-10 | Z38: NO PRICE | AA38: COMPARE / VERIFY CHECKOUT | AC38: https://audison.com/ | AD38: ALTERNATIVE / HISTORICAL
A39: C | B39: BOXMORE BXA M50 S3.1 | C39: Speaker | D39: NO | G39: 149 | H39: HifiMotive | I39: https://www.caraudio.nl/assortiment/boxmore | K39: NO CURRENT INDEXED LOCAL OFFER FOUND | N39: NO CURRENT INDEXED LOCAL OFFER FOUND | Q39: NO CURRENT INDEXED LOCAL OFFER FOUND | S39: =IF(COUNT(G39,J39,M39,P39)=0,"",MIN(G39,J39,M39,P39)) | T39: =IF(S39="","",IF(G39=S39,"NL",IF(J39=S39,"DE",IF(M39=S39,"BE","FR")))) | U39: =IF(COUNT(G39,J39,M39,P39)=0,"",AVERAGE(G39,J39,M39,P39)) | V39: =COUNT(G39,J39,M39,P39) | W39: =IF(OR(F39="",S39=""),"",F39-S39) | X39: =IF(OR(E39="",W39=""),"",E39*W39) | Y39: 2026-09-10 | Z39: HIGH | AA39: COMPARE / VERIFY CHECKOUT | AD39: ALTERNATIVE / HISTORICAL
A40: C | B40: BOXMORE BXA M80 S3.1 | C40: Speaker | D40: NO | G40: 199 | H40: HifiMotive | I40: https://www.caraudio.nl/assortiment/boxmore | K40: NO CURRENT INDEXED LOCAL OFFER FOUND | N40: NO CURRENT INDEXED LOCAL OFFER FOUND | Q40: NO CURRENT INDEXED LOCAL OFFER FOUND | S40: =IF(COUNT(G40,J40,M40,P40)=0,"",MIN(G40,J40,M40,P40)) | T40: =IF(S40="","",IF(G40=S40,"NL",IF(J40=S40,"DE",IF(M40=S40,"BE","FR")))) | U40: =IF(COUNT(G40,J40,M40,P40)=0,"",AVERAGE(G40,J40,M40,P40)) | V40: =COUNT(G40,J40,M40,P40) | W40: =IF(OR(F40="",S40=""),"",F40-S40) | X40: =IF(OR(E40="",W40=""),"",E40*W40) | Y40: 2026-09-10 | Z40: HIGH | AA40: COMPARE / VERIFY CHECKOUT | AD40: ALTERNATIVE / HISTORICAL
A41: C | B41: BOXMORE BXS M100FL S3.1 | C41: Speaker | D41: NO | G41: 269 | H41: HifiMotive | I41: https://www.caraudio.nl/artikel/boxmore-bxs-m100fl-s3-1-100-mm-shallow-midrange-set-bxsm100fls3_1 | K41: NO CURRENT INDEXED LOCAL OFFER FOUND | N41: NO CURRENT INDEXED LOCAL OFFER FOUND | Q41: NO CURRENT INDEXED LOCAL OFFER FOUND | S41: =IF(COUNT(G41,J41,M41,P41)=0,"",MIN(G41,J41,M41,P41)) | T41: =IF(S41="","",IF(G41=S41,"NL",IF(J41=S41,"DE",IF(M41=S41,"BE","FR")))) | U41: =IF(COUNT(G41,J41,M41,P41)=0,"",AVERAGE(G41,J41,M41,P41)) | V41: =COUNT(G41,J41,M41,P41) | W41: =IF(OR(F41="",S41=""),"",F41-S41) | X41: =IF(OR(E41="",W41=""),"",E41*W41) | Y41: 2026-09-10 | Z41: HIGH | AA41: COMPARE / VERIFY CHECKOUT | AD41: ALTERNATIVE / HISTORICAL
A42: C | B42: BOXMORE BXS T20RC.1 | C42: Tweeter | D42: NO | G42: 249 | H42: HifiMotive | I42: https://www.caraudio.nl/artikel/boxmore-bxs-t20rc-1-20-mm-soft-dome-tweeters-set-bxst20rc_1 | K42: NO CURRENT INDEXED LOCAL OFFER FOUND | N42: NO CURRENT INDEXED LOCAL OFFER FOUND | Q42: NO CURRENT INDEXED LOCAL OFFER FOUND | S42: =IF(COUNT(G42,J42,M42,P42)=0,"",MIN(G42,J42,M42,P42)) | T42: =IF(S42="","",IF(G42=S42,"NL",IF(J42=S42,"DE",IF(M42=S42,"BE","FR")))) | U42: =IF(COUNT(G42,J42,M42,P42)=0,"",AVERAGE(G42,J42,M42,P42)) | V42: =COUNT(G42,J42,M42,P42) | W42: =IF(OR(F42="",S42=""),"",F42-S42) | X42: =IF(OR(E42="",W42=""),"",E42*W42) | Y42: 2026-09-10 | Z42: HIGH | AA42: COMPARE / VERIFY CHECKOUT | AD42: ALTERNATIVE / HISTORICAL
A43: C | B43: BOXMORE BXS W200 S3.1 | C43: Speaker | D43: NO | G43: 399 | H43: HifiMotive | I43: https://www.caraudio.nl/artikel/boxmore/boxmore-bxs-w200-s3-1-specialist-200-mm-woofer-set-bxsw200s3_1 | K43: NO CURRENT INDEXED LOCAL OFFER FOUND | N43: NO CURRENT INDEXED LOCAL OFFER FOUND | Q43: NO CURRENT INDEXED LOCAL OFFER FOUND | S43: =IF(COUNT(G43,J43,M43,P43)=0,"",MIN(G43,J43,M43,P43)) | T43: =IF(S43="","",IF(G43=S43,"NL",IF(J43=S43,"DE",IF(M43=S43,"BE","FR")))) | U43: =IF(COUNT(G43,J43,M43,P43)=0,"",AVERAGE(G43,J43,M43,P43)) | V43: =COUNT(G43,J43,M43,P43) | W43: =IF(OR(F43="",S43=""),"",F43-S43) | X43: =IF(OR(E43="",W43=""),"",E43*W43) | Y43: 2026-09-10 | Z43: HIGH | AA43: COMPARE / VERIFY CHECKOUT | AD43: ALTERNATIVE / HISTORICAL
A44: C | B44: DLS Cruise CRPP-TS1.4 | C44: Speaker kit | D44: NO | G44: 299.95 | H44: MB Car Audio | I44: https://mbcaraudio.nl/autospecifieke-producten/tesla-autospecifieke-producten-en-accessoires/automodel-typenummer-en-bouwjaar-selectie-tesla/tesla-model-3-facelift-bouwjaar-2023- | K44: NO CURRENT INDEXED LOCAL OFFER FOUND | N44: NO CURRENT INDEXED LOCAL OFFER FOUND | Q44: NO CURRENT INDEXED LOCAL OFFER FOUND | S44: =IF(COUNT(G44,J44,M44,P44)=0,"",MIN(G44,J44,M44,P44)) | T44: =IF(S44="","",IF(G44=S44,"NL",IF(J44=S44,"DE",IF(M44=S44,"BE","FR")))) | U44: =IF(COUNT(G44,J44,M44,P44)=0,"",AVERAGE(G44,J44,M44,P44)) | V44: =COUNT(G44,J44,M44,P44) | W44: =IF(OR(F44="",S44=""),"",F44-S44) | X44: =IF(OR(E44="",W44=""),"",E44*W44) | Y44: 2026-09-10 | Z44: MEDIUM | AA44: COMPARE / VERIFY CHECKOUT | AC44: https://dls.se/ | AD44: ALTERNATIVE / HISTORICAL
A45: C | B45: DLS Cruise CRPP-TSW.8 | C45: Woofer kit | D45: NO | G45: 299.95 | H45: MB Car Audio | I45: https://mbcaraudio.nl/autospecifieke-producten/tesla-autospecifieke-producten-en-accessoires/automodel-typenummer-en-bouwjaar-selectie-tesla/tesla-model-3-facelift-bouwjaar-2023- | K45: NO CURRENT INDEXED LOCAL OFFER FOUND | N45: NO CURRENT INDEXED LOCAL OFFER FOUND | Q45: NO CURRENT INDEXED LOCAL OFFER FOUND | S45: =IF(COUNT(G45,J45,M45,P45)=0,"",MIN(G45,J45,M45,P45)) | T45: =IF(S45="","",IF(G45=S45,"NL",IF(J45=S45,"DE",IF(M45=S45,"BE","FR")))) | U45: =IF(COUNT(G45,J45,M45,P45)=0,"",AVERAGE(G45,J45,M45,P45)) | V45: =COUNT(G45,J45,M45,P45) | W45: =IF(OR(F45="",S45=""),"",F45-S45) | X45: =IF(OR(E45="",W45=""),"",E45*W45) | Y45: 2026-09-10 | Z45: MEDIUM | AA45: COMPARE / VERIFY CHECKOUT | AC45: https://dls.se/ | AD45: ALTERNATIVE / HISTORICAL
A46: C | B46: ESX QXE8.2W | C46: Woofer | D46: NO | H46: NO CURRENT INDEXED LOCAL OFFER FOUND | J46: 179.1 | K46: Idealo DE | L46: https://www.idealo.de/ | N46: NO CURRENT INDEXED LOCAL OFFER FOUND | Q46: NO CURRENT INDEXED LOCAL OFFER FOUND | S46: =IF(COUNT(G46,J46,M46,P46)=0,"",MIN(G46,J46,M46,P46)) | T46: =IF(S46="","",IF(G46=S46,"NL",IF(J46=S46,"DE",IF(M46=S46,"BE","FR")))) | U46: =IF(COUNT(G46,J46,M46,P46)=0,"",AVERAGE(G46,J46,M46,P46)) | V46: =COUNT(G46,J46,M46,P46) | W46: =IF(OR(F46="",S46=""),"",F46-S46) | X46: =IF(OR(E46="",W46=""),"",E46*W46) | Y46: 2026-09-10 | Z46: MEDIUM | AA46: COMPARE / VERIFY CHECKOUT | AC46: https://www.esxaudio.de/english/ | AD46: ALTERNATIVE / HISTORICAL
A47: C | B47: ESX TES3YSET2 | C47: Tesla speaker kit | D47: NO | H47: NO CURRENT INDEXED LOCAL OFFER FOUND | J47: 1199 | K47: DE current comparison | L47: https://www.esxaudio.de/english/tes3yset2.html | N47: NO CURRENT INDEXED LOCAL OFFER FOUND | Q47: NO CURRENT INDEXED LOCAL OFFER FOUND | S47: =IF(COUNT(G47,J47,M47,P47)=0,"",MIN(G47,J47,M47,P47)) | T47: =IF(S47="","",IF(G47=S47,"NL",IF(J47=S47,"DE",IF(M47=S47,"BE","FR")))) | U47: =IF(COUNT(G47,J47,M47,P47)=0,"",AVERAGE(G47,J47,M47,P47)) | V47: =COUNT(G47,J47,M47,P47) | W47: =IF(OR(F47="",S47=""),"",F47-S47) | X47: =IF(OR(E47="",W47=""),"",E47*W47) | Y47: 2026-09-10 | Z47: MEDIUM | AA47: COMPARE / VERIFY CHECKOUT | AC47: https://www.esxaudio.de/english/ | AD47: ALTERNATIVE / HISTORICAL
A48: C | B48: ESX VXP3M | C48: Speaker | D48: NO | H48: NO CURRENT INDEXED LOCAL OFFER FOUND | J48: 249 | K48: DE current retail benchmark | L48: https://www.esxaudio.de/ | N48: NO CURRENT INDEXED LOCAL OFFER FOUND | Q48: NO CURRENT INDEXED LOCAL OFFER FOUND | S48: =IF(COUNT(G48,J48,M48,P48)=0,"",MIN(G48,J48,M48,P48)) | T48: =IF(S48="","",IF(G48=S48,"NL",IF(J48=S48,"DE",IF(M48=S48,"BE","FR")))) | U48: =IF(COUNT(G48,J48,M48,P48)=0,"",AVERAGE(G48,J48,M48,P48)) | V48: =COUNT(G48,J48,M48,P48) | W48: =IF(OR(F48="",S48=""),"",F48-S48) | X48: =IF(OR(E48="",W48=""),"",E48*W48) | Y48: 2026-09-10 | Z48: MEDIUM | AA48: COMPARE / VERIFY CHECKOUT | AC48: https://www.esxaudio.de/english/ | AD48: ALTERNATIVE / HISTORICAL
A49: C | B49: Focal 3 KM | C49: Speaker | D49: NO | G49: 319 | H49: MB Car Audio | I49: https://mbcaraudio.nl/car-audio-producten/speakers-acc/87-cm- | K49: NO CURRENT INDEXED LOCAL OFFER FOUND | N49: NO CURRENT INDEXED LOCAL OFFER FOUND | Q49: NO CURRENT INDEXED LOCAL OFFER FOUND | S49: =IF(COUNT(G49,J49,M49,P49)=0,"",MIN(G49,J49,M49,P49)) | T49: =IF(S49="","",IF(G49=S49,"NL",IF(J49=S49,"DE",IF(M49=S49,"BE","FR")))) | U49: =IF(COUNT(G49,J49,M49,P49)=0,"",AVERAGE(G49,J49,M49,P49)) | V49: =COUNT(G49,J49,M49,P49) | W49: =IF(OR(F49="",S49=""),"",F49-S49) | X49: =IF(OR(E49="",W49=""),"",E49*W49) | Y49: 2026-09-10 | Z49: HIGH | AA49: COMPARE / VERIFY CHECKOUT | AC49: https://www.focal.com/products/3-km | AD49: ALTERNATIVE / HISTORICAL
A50: C | B50: GLADEN GAMMA GM80 | C50: Speaker | D50: NO | G50: 169 | H50: NL current benchmark | I50: https://mbcaraudio.nl/car-audio-producten/speakers-acc/87-cm- | K50: NO CURRENT INDEXED LOCAL OFFER FOUND | N50: NO CURRENT INDEXED LOCAL OFFER FOUND | Q50: NO CURRENT INDEXED LOCAL OFFER FOUND | S50: =IF(COUNT(G50,J50,M50,P50)=0,"",MIN(G50,J50,M50,P50)) | T50: =IF(S50="","",IF(G50=S50,"NL",IF(J50=S50,"DE",IF(M50=S50,"BE","FR")))) | U50: =IF(COUNT(G50,J50,M50,P50)=0,"",AVERAGE(G50,J50,M50,P50)) | V50: =COUNT(G50,J50,M50,P50) | W50: =IF(OR(F50="",S50=""),"",F50-S50) | X50: =IF(OR(E50="",W50=""),"",E50*W50) | Y50: 2026-09-10 | Z50: MEDIUM | AA50: COMPARE / VERIFY CHECKOUT | AD50: ALTERNATIVE / HISTORICAL
A51: C | B51: Ground Zero GZRM 80SQ | C51: Speaker | D51: NO | H51: NO CURRENT INDEXED LOCAL OFFER FOUND | J51: 179 | K51: MediaMarkt marketplace / ACR Bielefeld | L51: https://www.mediamarkt.de/de/product/_ground-zero-gzrm-80sq-autolautsprecher-151306218.html | N51: NO CURRENT INDEXED LOCAL OFFER FOUND | Q51: NO CURRENT INDEXED LOCAL OFFER FOUND | S51: =IF(COUNT(G51,J51,M51,P51)=0,"",MIN(G51,J51,M51,P51)) | T51: =IF(S51="","",IF(G51=S51,"NL",IF(J51=S51,"DE",IF(M51=S51,"BE","FR")))) | U51: =IF(COUNT(G51,J51,M51,P51)=0,"",AVERAGE(G51,J51,M51,P51)) | V51: =COUNT(G51,J51,M51,P51) | W51: =IF(OR(F51="",S51=""),"",F51-S51) | X51: =IF(OR(E51="",W51=""),"",E51*W51) | Y51: 2026-09-10 | Z51: MEDIUM | AA51: COMPARE / VERIFY CHECKOUT | AD51: ALTERNATIVE / HISTORICAL
A52: C | B52: Ground Zero GZUF 60SQ-A | C52: Speaker | D52: NO | G52: 174.95 | H52: MB Car Audio | I52: https://mbcaraudio.nl/87-cm-/ground-zero-gzuf-60sq-a.html | K52: NO CURRENT INDEXED LOCAL OFFER FOUND | N52: NO CURRENT INDEXED LOCAL OFFER FOUND | Q52: NO CURRENT INDEXED LOCAL OFFER FOUND | S52: =IF(COUNT(G52,J52,M52,P52)=0,"",MIN(G52,J52,M52,P52)) | T52: =IF(S52="","",IF(G52=S52,"NL",IF(J52=S52,"DE",IF(M52=S52,"BE","FR")))) | U52: =IF(COUNT(G52,J52,M52,P52)=0,"",AVERAGE(G52,J52,M52,P52)) | V52: =COUNT(G52,J52,M52,P52) | W52: =IF(OR(F52="",S52=""),"",F52-S52) | X52: =IF(OR(E52="",W52=""),"",E52*W52) | Y52: 2026-09-10 | Z52: HIGH | AA52: COMPARE / VERIFY CHECKOUT | AD52: ALTERNATIVE / HISTORICAL
A53: C | B53: HELIX CFMK80-100 | C53: Adapter | D53: NO | H53: NO CURRENT INDEXED LOCAL OFFER FOUND | K53: NO CURRENT INDEXED LOCAL OFFER FOUND | N53: NO CURRENT INDEXED LOCAL OFFER FOUND | Q53: NO CURRENT INDEXED LOCAL OFFER FOUND | S53: =IF(COUNT(G53,J53,M53,P53)=0,"",MIN(G53,J53,M53,P53)) | T53: =IF(S53="","",IF(G53=S53,"NL",IF(J53=S53,"DE",IF(M53=S53,"BE","FR")))) | U53: =IF(COUNT(G53,J53,M53,P53)=0,"",AVERAGE(G53,J53,M53,P53)) | V53: =COUNT(G53,J53,M53,P53) | W53: =IF(OR(F53="",S53=""),"",F53-S53) | X53: =IF(OR(E53="",W53=""),"",E53*W53) | Y53: 2026-09-10 | Z53: NO PRICE | AA53: COMPARE / VERIFY CHECKOUT | AC53: https://www.audiotec-fischer.de/en/helix/ | AD53: ALTERNATIVE / HISTORICAL
A54: C | B54: HELIX Ci3 C100.2FM-S3 | C54: Center speaker | D54: NO | H54: NO CURRENT INDEXED LOCAL OFFER FOUND | K54: NO CURRENT INDEXED LOCAL OFFER FOUND | N54: NO CURRENT INDEXED LOCAL OFFER FOUND | Q54: NO CURRENT INDEXED LOCAL OFFER FOUND | S54: =IF(COUNT(G54,J54,M54,P54)=0,"",MIN(G54,J54,M54,P54)) | T54: =IF(S54="","",IF(G54=S54,"NL",IF(J54=S54,"DE",IF(M54=S54,"BE","FR")))) | U54: =IF(COUNT(G54,J54,M54,P54)=0,"",AVERAGE(G54,J54,M54,P54)) | V54: =COUNT(G54,J54,M54,P54) | W54: =IF(OR(F54="",S54=""),"",F54-S54) | X54: =IF(OR(E54="",W54=""),"",E54*W54) | Y54: 2026-09-10 | Z54: NO PRICE | AA54: COMPARE / VERIFY CHECKOUT | AC54: https://www.audiotec-fischer.de/en/helix/ | AD54: ALTERNATIVE / HISTORICAL
A55: C | B55: HELIX Ci3 W200FM-S3 | C55: Speaker | D55: NO | H55: NO CURRENT INDEXED LOCAL OFFER FOUND | K55: NO CURRENT INDEXED LOCAL OFFER FOUND | N55: NO CURRENT INDEXED LOCAL OFFER FOUND | Q55: NO CURRENT INDEXED LOCAL OFFER FOUND | S55: =IF(COUNT(G55,J55,M55,P55)=0,"",MIN(G55,J55,M55,P55)) | T55: =IF(S55="","",IF(G55=S55,"NL",IF(J55=S55,"DE",IF(M55=S55,"BE","FR")))) | U55: =IF(COUNT(G55,J55,M55,P55)=0,"",AVERAGE(G55,J55,M55,P55)) | V55: =COUNT(G55,J55,M55,P55) | W55: =IF(OR(F55="",S55=""),"",F55-S55) | X55: =IF(OR(E55="",W55=""),"",E55*W55) | Y55: 2026-09-10 | Z55: NO PRICE | AA55: COMPARE / VERIFY CHECKOUT | AC55: https://www.audiotec-fischer.de/en/helix/ | AD55: ALTERNATIVE / HISTORICAL
A56: C | B56: HELIX Ci5 M50FM-S3 | C56: Speaker | D56: NO | H56: NO CURRENT INDEXED LOCAL OFFER FOUND | J56: 169 | K56: CarHifi-Store Bünde / ARS24 | L56: https://www.carhifi-store-buende.de/helix-ci5-m50fm-s3 | N56: NO CURRENT INDEXED LOCAL OFFER FOUND | Q56: NO CURRENT INDEXED LOCAL OFFER FOUND | S56: =IF(COUNT(G56,J56,M56,P56)=0,"",MIN(G56,J56,M56,P56)) | T56: =IF(S56="","",IF(G56=S56,"NL",IF(J56=S56,"DE",IF(M56=S56,"BE","FR")))) | U56: =IF(COUNT(G56,J56,M56,P56)=0,"",AVERAGE(G56,J56,M56,P56)) | V56: =COUNT(G56,J56,M56,P56) | W56: =IF(OR(F56="",S56=""),"",F56-S56) | X56: =IF(OR(E56="",W56=""),"",E56*W56) | Y56: 2026-09-10 | Z56: HIGH | AA56: COMPARE / VERIFY CHECKOUT | AB56: Headliner product retained as comparison, but current installer recommendation is to omit X569/X579 for music. | AC56: https://www.audiotec-fischer.de/en/helix/ | AD56: ALTERNATIVE / HISTORICAL
A57: C | B57: HELIX DSP MINI MK2 | C57: DSP processor | D57: NO | H57: NO CURRENT INDEXED LOCAL OFFER FOUND | J57: 399 | K57: Caraudio-store / ARS24 | L57: https://www.caraudio-store.de/Helix_s3 | N57: NO CURRENT INDEXED LOCAL OFFER FOUND | Q57: NO CURRENT INDEXED LOCAL OFFER FOUND | S57: =IF(COUNT(G57,J57,M57,P57)=0,"",MIN(G57,J57,M57,P57)) | T57: =IF(S57="","",IF(G57=S57,"NL",IF(J57=S57,"DE",IF(M57=S57,"BE","FR")))) | U57: =IF(COUNT(G57,J57,M57,P57)=0,"",AVERAGE(G57,J57,M57,P57)) | V57: =COUNT(G57,J57,M57,P57) | W57: =IF(OR(F57="",S57=""),"",F57-S57) | X57: =IF(OR(E57="",W57=""),"",E57*W57) | Y57: 2026-09-10 | Z57: HIGH | AA57: COMPARE / VERIFY CHECKOUT | AC57: https://www.audiotec-fischer.de/en/helix/ | AD57: ALTERNATIVE / HISTORICAL
A58: C | B58: HELIX T20FM-TI | C58: Tweeter | D58: NO | H58: NO CURRENT INDEXED LOCAL OFFER FOUND | K58: NO CURRENT INDEXED LOCAL OFFER FOUND | N58: NO CURRENT INDEXED LOCAL OFFER FOUND | Q58: NO CURRENT INDEXED LOCAL OFFER FOUND | S58: =IF(COUNT(G58,J58,M58,P58)=0,"",MIN(G58,J58,M58,P58)) | T58: =IF(S58="","",IF(G58=S58,"NL",IF(J58=S58,"DE",IF(M58=S58,"BE","FR")))) | U58: =IF(COUNT(G58,J58,M58,P58)=0,"",AVERAGE(G58,J58,M58,P58)) | V58: =COUNT(G58,J58,M58,P58) | W58: =IF(OR(F58="",S58=""),"",F58-S58) | X58: =IF(OR(E58="",W58=""),"",E58*W58) | Y58: 2026-09-10 | Z58: NO PRICE | AA58: COMPARE / VERIFY CHECKOUT | AC58: https://www.audiotec-fischer.de/en/helix/ | AD58: ALTERNATIVE / HISTORICAL
A59: C | B59: HELIX V EIGHT DSP (legacy) | C59: DSP amplifier | D59: NO | H59: NO CURRENT INDEXED LOCAL OFFER FOUND | J59: 949 | K59: ARS24 clearance | L59: https://www.ars24.com/en/helix-v-eight-dsp | N59: NO CURRENT INDEXED LOCAL OFFER FOUND | Q59: NO CURRENT INDEXED LOCAL OFFER FOUND | S59: =IF(COUNT(G59,J59,M59,P59)=0,"",MIN(G59,J59,M59,P59)) | T59: =IF(S59="","",IF(G59=S59,"NL",IF(J59=S59,"DE",IF(M59=S59,"BE","FR")))) | U59: =IF(COUNT(G59,J59,M59,P59)=0,"",AVERAGE(G59,J59,M59,P59)) | V59: =COUNT(G59,J59,M59,P59) | W59: =IF(OR(F59="",S59=""),"",F59-S59) | X59: =IF(OR(E59="",W59=""),"",E59*W59) | Y59: 2026-09-10 | Z59: MEDIUM | AA59: COMPARE / VERIFY CHECKOUT | AB59: Legacy/new-old-stock route. | AC59: https://www.audiotec-fischer.de/en/helix/ | AD59: ALTERNATIVE / HISTORICAL
A60: C | B60: MUSWAY MAE6.2W | C60: Woofer | D60: NO | G60: 119 | H60: MB Car Audio | I60: https://mbcaraudio.nl/ | J60: 129 | K60: Musway MSRP / DE benchmark | L60: https://musway.de/ | N60: NO CURRENT INDEXED LOCAL OFFER FOUND | Q60: NO CURRENT INDEXED LOCAL OFFER FOUND | S60: =IF(COUNT(G60,J60,M60,P60)=0,"",MIN(G60,J60,M60,P60)) | T60: =IF(S60="","",IF(G60=S60,"NL",IF(J60=S60,"DE",IF(M60=S60,"BE","FR")))) | U60: =IF(COUNT(G60,J60,M60,P60)=0,"",AVERAGE(G60,J60,M60,P60)) | V60: =COUNT(G60,J60,M60,P60) | W60: =IF(OR(F60="",S60=""),"",F60-S60) | X60: =IF(OR(E60="",W60=""),"",E60*W60) | Y60: 2026-09-10 | Z60: MEDIUM | AA60: COMPARE / VERIFY CHECKOUT | AC60: https://musway.de/english/ | AD60: ALTERNATIVE / HISTORICAL
A61: C | B61: MUSWAY ML3M | C61: Speaker | D61: NO | H61: NO CURRENT INDEXED LOCAL OFFER FOUND | K61: NO CURRENT INDEXED LOCAL OFFER FOUND | N61: NO CURRENT INDEXED LOCAL OFFER FOUND | Q61: NO CURRENT INDEXED LOCAL OFFER FOUND | S61: =IF(COUNT(G61,J61,M61,P61)=0,"",MIN(G61,J61,M61,P61)) | T61: =IF(S61="","",IF(G61=S61,"NL",IF(J61=S61,"DE",IF(M61=S61,"BE","FR")))) | U61: =IF(COUNT(G61,J61,M61,P61)=0,"",AVERAGE(G61,J61,M61,P61)) | V61: =COUNT(G61,J61,M61,P61) | W61: =IF(OR(F61="",S61=""),"",F61-S61) | X61: =IF(OR(E61="",W61=""),"",E61*W61) | Y61: 2026-09-10 | Z61: NO PRICE | AA61: COMPARE / VERIFY CHECKOUT | AC61: https://musway.de/english/ | AD61: ALTERNATIVE / HISTORICAL
A62: C | B62: MUSWAY TES3YSET1 | C62: Tesla speaker kit | D62: NO | H62: NO CURRENT INDEXED LOCAL OFFER FOUND | J62: 799 | K62: Musway / DE retail benchmark | L62: https://musway.de/english/tes3yset1.html | N62: NO CURRENT INDEXED LOCAL OFFER FOUND | Q62: NO CURRENT INDEXED LOCAL OFFER FOUND | S62: =IF(COUNT(G62,J62,M62,P62)=0,"",MIN(G62,J62,M62,P62)) | T62: =IF(S62="","",IF(G62=S62,"NL",IF(J62=S62,"DE",IF(M62=S62,"BE","FR")))) | U62: =IF(COUNT(G62,J62,M62,P62)=0,"",AVERAGE(G62,J62,M62,P62)) | V62: =COUNT(G62,J62,M62,P62) | W62: =IF(OR(F62="",S62=""),"",F62-S62) | X62: =IF(OR(E62="",W62=""),"",E62*W62) | Y62: 2026-09-10 | Z62: MEDIUM | AA62: COMPARE / VERIFY CHECKOUT | AC62: https://musway.de/english/ | AD62: ALTERNATIVE / HISTORICAL
A63: C | B63: PowerBass OE40CN-T3Y | C63: Tesla speaker | D63: NO | H63: NO CURRENT INDEXED LOCAL OFFER FOUND | K63: NO CURRENT INDEXED LOCAL OFFER FOUND | N63: NO CURRENT INDEXED LOCAL OFFER FOUND | Q63: NO CURRENT INDEXED LOCAL OFFER FOUND | S63: =IF(COUNT(G63,J63,M63,P63)=0,"",MIN(G63,J63,M63,P63)) | T63: =IF(S63="","",IF(G63=S63,"NL",IF(J63=S63,"DE",IF(M63=S63,"BE","FR")))) | U63: =IF(COUNT(G63,J63,M63,P63)=0,"",AVERAGE(G63,J63,M63,P63)) | V63: =COUNT(G63,J63,M63,P63) | W63: =IF(OR(F63="",S63=""),"",F63-S63) | X63: =IF(OR(E63="",W63=""),"",E63*W63) | Y63: 2026-09-10 | Z63: NO PRICE | AA63: COMPARE / VERIFY CHECKOUT | AB63: No current indexed NL/DE/BE/FR local offer found; Greek benchmark deliberately excluded from West-EU low price. | AD63: ALTERNATIVE / HISTORICAL
A66: MB quote split-buy summary
A67: MB quote total | B67: =SUMPRODUCT(E5:E63,F5:F63,--(D5:D63="YES"))
A68: Split-buy low total | B68: =SUMPRODUCT(E5:E63,S5:S63,--(D5:D63="YES"))
A69: Gross saving | B69: =B67-B68
A70: Gross saving % | B70: =B69/B67
A71: Caution | B71: Shipping, stock, seller reliability, warranty handling and checkout price can erase part of the gross saving. Marketplace lows are marked MEDIUM confidence.

Sheet MB_Quote_2026-09-10
A1: MB Car Audio — received quote evidence 2026-09-10
A2: Transcribed from the supplied cart screenshot. Hardware only; no cables, damping, mounting/consumables or labour. Installation will be performed by the owner.
A4: Line | B4: Product | C4: Qty | D4: Quoted unit € | E4: Quoted line € | F4: Role / note | G4: Evidence | H4: Quote scope | I4: Status
A5: 1 | B5: Focal IW T3Y 200 | C5: 1 | D5: 459 | E5: =C5*D5 | F5: Front woofer-set | G5: MB_Car_Audio_quote_cart_2026-09-10.png | H5: Hardware only | I5: RECEIVED
A6: 2 | B6: Focal ICC T3Y 100 | C6: 1 | D6: 179 | E6: =C6*D6 | F6: Dashboard center | G6: MB_Car_Audio_quote_cart_2026-09-10.png | H6: Hardware only | I6: RECEIVED
A7: 3 | B7: Focal IC T3Y 100 | C7: 1 | D7: 319 | E7: =C7*D7 | F7: Rear / coaxial set | G7: MB_Car_Audio_quote_cart_2026-09-10.png | H7: Hardware only | I7: RECEIVED
A8: 4 | B8: Focal IS T3Y 100 | C8: 1 | D8: 369 | E8: =C8*D8 | F8: Front mids + tweeters | G8: MB_Car_Audio_quote_cart_2026-09-10.png | H8: Hardware only | I8: RECEIVED
A9: 5 | B9: MATCH PP-TES 1.7B Highland | C9: 1 | D9: 139.95 | E9: =C9*D9 | F9: Tesla signal interposer / harness basis | G9: MB_Car_Audio_quote_cart_2026-09-10.png | H9: Hardware only | I9: RECEIVED
A10: 6 | B10: Audison AF M8.14 bit | C10: 1 | D10: 1199 | E10: =C10*D10 | F10: Alles vóór de voorstoelen / front stage DSP + amplification | G10: MB_Car_Audio_quote_cart_2026-09-10.png | H10: Hardware only | I10: RECEIVED
A11: 7 | B11: Audison AF M4D | C11: 1 | D11: 599 | E11: =C11*D11 | F11: Alles achter de voorstoelen: rear woofers, rear mids, optionele rear tweeters | G11: MB_Car_Audio_quote_cart_2026-09-10.png | H11: Hardware only | I11: RECEIVED
A12: 8 | B12: Audison AF M1D | C12: 1 | D12: 599 | E12: =C12*D12 | F12: Pioneer donor subwoofers | G12: MB_Car_Audio_quote_cart_2026-09-10.png | H12: Hardware only | I12: RECEIVED
A13: 9 | B13: Audison AF LINK | C13: 1 | D13: 18.95 | E13: =C13*D13 | F13: AF bit DSP OUT → AF D PRE IN | G13: MB_Car_Audio_quote_cart_2026-09-10.png | H13: Hardware only | I13: RECEIVED
A14: 10 | B14: Audison DRC AC | C14: 1 | D14: 129 | E14: =C14*D14 | F14: Master/sub/source/preset control | G14: MB_Car_Audio_quote_cart_2026-09-10.png | H14: Hardware only | I14: RECEIVED
C15: TOTAL | D15: =SUM(E5:E14)
A17: Scope confirmation | B17: EUR 4,010.90 is hardware only. Cabling, fusing/distribution, damping, mounting/consumable material and labour are excluded. DIY installation.

Sheet BOM_Recommended
A1: Aanbevolen BOM – 15 cabin speakers
A2: Recommended cabin baseline retained. Existing Pioneer TS-WX1220AH donor subsystem is now explicitly documented outside the cabin-speaker count; original enclosure is not used. Pioneer LV compatibility remains an open power-design gate.
A4: ID | B4: Categorie | C4: Aantal sets | D4: Speakers in set | E4: Tesla locatie / functie | F4: Merk / model | G4: Impedantie | H4: RMS / spec | I4: Fitment / adapter | J4: Aansturing | K4: Regio koopadvies | L4: Eenheidsprijs EUR | M4: Prijsstatus | N4: Regeltotaal EUR | O4: Bron / URL | P4: Opmerking
A5: DSP-01 | B5: DSP/versterker | C5: 1 | D5: 0 | E5: Cabin amplification / processing | F5: Audison Forza AF M12.14 bit | G5: 2–4 Ω | H5: 12×60 W @4Ω; 12×90 W @2Ω; 14ch DSP | I5: Universeel; custom Tesla T-harness | J5: 11 cabin amp-kanalen + DSP OUT naar Pioneer | K5: DE/NL | L5: 1290 | M5: Verified current | N5: =C5*L5 | O5: 12 versterkte kanalen; 6 DSP OUT kanalen; 1 kanaal reserve in voorgestelde map.
A6: CTRL-01 | B6: Displaycontroller | C6: 1 | D6: 0 | E6: Bestuurdersbediening | F6: Audison DRC MP CAN | G6: n.v.t. | H6: OLED; 6 DSP memories; master/sub volume | I6: DRCC aansluiting op Forza | J6: DSP control | K6: NL | L6: 179 | M6: Verified current | N6: =C6*L6 | O6: Officieel geschikt voor AF M12.14 bit.
A7: HAR-01 | B7: Tesla T-harness | C7: 1 | D7: 0 | E7: OEM 16-pin Tesla interposer | F7: MATCH PP-TES 1.7B Highland | G7: n.v.t. | H7: Tesla 16-pin plug/socket + Molex breakout | I7: Direct passend aan Tesla; Audison-zijde repinnen | J7: Signal in/out interposer | K7: DE/NL | L7: 129 | M7: Verified current | N7: =C7*L7 | O7: Fabrikant bedoelt hem voor MATCH UP10; in deze BOM alleen donor/no-cut interposer. Niet direct PnP naar Audison.
A8: SPK-01 | B8: Front speakerkit | C8: 1 | D8: 7 | E8: Front doors + dash L/C/R | F8: HELIX Compose Ci3 K200.2TES4 Highland | G8: 3 Ω | H8: 2×W200 + 2×M100 + 2×T20 + 1×C100 | I8: Highland FlexMount + connector kits inbegrepen | J8: 5 amp-kanalen door passieve L/R mid+tweeter XO | K8: DE | L8: 729 | M8: Verified current | N8: =C8*L8 | O8: Exact Highland kit; geïntegreerde 6 dB crossover voor HT/MT.
A9: SPK-02 | B9: Premium front mids | C9: 1 | D9: 2 | E9: Front doors 80 mm L/R | F9: HELIX Ci5 M80FM-S3 | G9: 3 Ω | H9: 80 mm; advanced midrange | I9: Custom/FlexMount80 Tesla adapter vereist | J9: 2 Audison kanalen L/R | K9: DE/FR | L9: 199 | M9: Verified current | N9: =C9*L9 | O9: Fysieke Highland 80mm adapter nog verifiëren.
A10: SPK-03 | B10: Headliner | C10: 1 | D10: 2 | E10: Headliner L/R | F10: HELIX Ci5 M50FM-S3 | G10: 3 Ω | H10: 50 mm full-range | I10: Custom 60→50 mm adapter/pigtail | J10: AUX 2ch amplifier via Audison DSP OUT | K10: DE/FR | L10: 169 | M10: Verified current | N10: =C10*L10 | O10: Bewust op OEM-kanalen om nieuw DSP-kanaalbudget vrij te houden. | P10: SOP9 correction retained: X569/X579 are PAUDIO-only. Use AUX 2ch from DSP OUT unless PAUDIO output/wiring is proven.
A11: SPK-04 | B11: Rear doors | C11: 1 | D11: 2 | E11: Rear doors L/R | F11: HELIX Ci3 M100FM-S3 | G11: 3 Ω | H11: 100 mm; 80 W RMS | I11: Tesla adapter/pigtail vereist | J11: 2 Audison kanalen L/R | K11: DE/EU | L11: 149 | M11: Verified current | N11: =C11*L11 | O11: Pair price.
A12: SPK-05 | B12: Parcel shelf | C12: 1 | D12: 2 | E12: Parcel shelf L/R (Premium posities) | F12: HELIX Ci3 M100FM-S3 | G12: 3 Ω | H12: 100 mm; 80 W RMS | I12: Custom Tesla mount/pigtail vereist | J12: 2 Audison kanalen L/R | K12: DE/EU | L12: 149 | M12: Verified current | N12: =C12*L12 | O12: Pair price; Premium-posities moeten mogelijk fysiek worden voorbereid.
A13: PWR-01 | B13: Voeding | C13: 1 | D13: 0 | E13: DSP amp power | F13: 16 mm² OFC + MIDI fuse 60 A + terminals | G13: n.v.t. | H13: Budget allowance | I13: Dedicated fused feed | J13: Power | K13: EU | L13: 160 | M13: Budget allowance | N13: =C13*L13 | O13: Definitieve lengte/fusepositie na installatieroute bepalen; bestaande Pioneer voeding apart laten.
A14: ADP-01 | B14: Adapters/pigtails | C14: 1 | D14: 0 | E14: 80mm/headliner/rear/parcel | F14: FlexMount/custom 3D adapters + OEM pigtails | G14: n.v.t. | H14: Budget allowance | I14: No-cut vehicle side | J14: Mechanical / wiring | K14: EU | L14: 180 | M14: Budget allowance | N14: =C14*L14 | O14: Reserve voor 80mm, 60→50mm, rear/parcel mounts en connectoren.
A15: CAB-01 | B15: Bekabeling | C15: 1 | D15: 0 | E15: Speaker/DSP/remote finishing | F15: OFC speaker cable + ferrules + braid + heatshrink | G15: n.v.t. | H15: Budget allowance | I15: Install material | J15: Signal / speaker | K15: EU | L15: 60 | M15: Budget allowance | N15: =C15*L15 | O15: Geen subwooferkabel/amp inbegrepen; bestaande Pioneer module hergebruiken.
A16: AUX-01 | B16: Auxiliary amplifier | C16: 1 | D16: 0 | E16: Headliner L/R amplification | F16: 2-channel compact amplifier - MODEL TBD | G16: TBD | H16: Suitable for 2x headliner full-range | I16: Universal; powered/fused install | J16: 2 channels from Audison DSP OUT | K16: NL/DE/BE/FR first | M16: REQUIRED - UNPRICED | O16: TBD after EU research | P16: Required by SOP9 evidence; excluded from numeric total until model/price is researched.
A17: SUB-01 | B17: Existing subwoofer donor subsystem | C17: 1 | D17: 0 | E17: Tesla lower extra trunk storage / custom baffle | F17: Pioneer TS-WX1220AH donor: 2× original 30 cm woofers | G17: Donor hardware | H17: Original system: 1000 W RMS / 3000 W max | I17: Original Pioneer enclosure NOT used | J17: Driven by retained Pioneer Class-D amp | K17: Existing / reused | L17: 0 | M17: EXISTING - RETAINED | N17: =C17*L17 | O17: https://pioneer-car.eu/ts-wx1220ah/ts-wx1220ah | P17: Two original drivers removed from TS-WX1220AH and installed in custom lower-trunk baffle/lid. Excluded from 15 cabin-speaker count.
A18: SUB-02 | B18: Existing subwoofer amplifier | C18: 1 | D18: 0 | E18: Behind trunk side / wheel-arch trim near OEM Premium amp area | F18: Original TS-WX1220AH Class-D amplifier | G18: 10.8–15.1 V supply | H18: 600 W RMS / 1200 W max; max current 50 A | I18: Remote-mounted; original enclosure NOT used | J18: DSP sub line/RCA → Pioneer amp → two donor woofers | K18: Existing / reused | L18: 0 | M18: EXISTING - RETAINED | N18: =C18*L18 | O18: https://pioneer-car.eu/asset/installation_manuals/UPLOAD_ID_28783/bb886d2a0df764bbfca7a2d7de1562b67e31f364/ | P18: Pioneer specifies negative ground; wiring example uses dedicated 80 A fuse.
A19: PWR-02 | B19: Subwoofer power compatibility gate | C19: 1 | D19: 0 | E19: Tesla LV → Pioneer donor amplifier | F19: High-current regulated DC-DC step-down - MODEL TBD IF REQUIRED | G19: Tesla 15.5 V vs Pioneer max 15.1 V | H19: Must support Pioneer specified max current 50 A; engineering margin TBD | I19: Dedicated fused branch; thermal/grounding design TBD | J19: Voltage verification / regulation | K19: NL/DE/BE/FR first | M19: BLOCKER - UNPRICED | O19: https://www.tesla.com/ownersmanual/model3/nl_nl/GUID-E414862C-CFA1-4A0B-9548-BE21C32CAA58.html | P19: DIRECT CONNECTION NOT APPROVED until actual SOP9 LV is verified. Use regulated step-down if the Pioneer amp can see >15.1 V.
M20: TOTAAL | N20: =SUM(N5:N19)
M21: Budget max | N21: =Overview!B5
M22: Headroom | N22: =N21-N20
M23: Cabin speakers | N23: =SUM(D5:D19)
A25: v2.1 NOTE
A26: Historical/comparison content retained. Current received MB proposal is authoritative in MB_Quote_2026-09-10 / MBC_Shopping_List and MB_Channel_Map_v2.1.

Sheet Price_Comparison
A1: Prijsvergelijking per regio
A2: Webprijzen opnieuw gecontroleerd op 2026-09-02. Bestaande niet-herbevestigde vergelijkprijzen blijven zichtbaar maar moeten bij checkout opnieuw worden geverifieerd.
A4: Product | B4: Market | C4: Seller | D4: Currency | E4: Listed price | F4: Qty/MOQ | G4: VAT in listed? | H4: FX to EUR | I4: EUR ex extra VAT | J4: Indicative NL VAT 21% | K4: Indicative EUR incl. NL VAT | L4: Shipping/duty | M4: Availability / confidence | N4: Source URL | O4: Checked
A5: Audison AF M12.14 bit | B5: NL | C5: MB Car Audio / AutoSound24 | D5: EUR | E5: 1349 | F5: 1 | G5: Yes | H5: 1 | I5: =E5*H5 | J5: =IF(G5="Yes",0,I5*21%) | K5: =I5+J5 | L5: Shipping varies | M5: Reverified 2026-09-02; NL stock shown | N5: https://mbcaraudio.nl/car-audio-producten/versterkers/versterkers-met-dsp | O5: 2026-09-02
A6: Audison AF M12.14 bit | B6: DE | C6: justSOUND | D6: EUR | E6: 1290 | F6: 1 | G6: Yes | H6: 1 | I6: =E6*H6 | J6: =IF(G6="Yes",0,I6*21%) | K6: =I6+J6 | L6: DE shipping stated | M6: Current / in stock | N6: https://just-sound.de/Audison-Forza-AF-M1214-bit-12-Kanal-Verstaerker-mit-DSP-180W | O6: 2026-09-01
A7: Audison AF M12.14 bit | B7: DE | C7: Idealo / just-sound.de | D7: EUR | E7: 1205.9 | F7: 1 | G7: Yes | H7: 1 | I7: =E7*H7 | J7: =IF(G7="Yes",0,I7*21%) | K7: =I7+J7 | L7: DE shipping included per Idealo; NL shipping must be verified | M7: Current comparison price; verify checkout before ordering | N7: https://www.idealo.de/preisvergleich/OffersOfProduct/203736270_-af-m12-14-bit-audison.html | O7: 2026-09-01
A8: Audison AF M12.14 bit | B8: FR/EU | C8: Elettromedia store | D8: EUR | E8: 1290 | F8: 1 | G8: Yes | H8: 1 | I8: =E8*H8 | J8: =IF(G8="Yes",0,I8*21%) | K8: =I8+J8 | L8: EU shipping | M8: Current official store | N8: https://store.elettromedia.com/af-m12-14-bit/ | O8: 2026-09-01
A9: MATCH UP 10DSP MK2 (alternative) | B9: NL | C9: HifiMotive | D9: EUR | E9: 1049 | F9: 1 | G9: Yes | H9: 1 | I9: =E9*H9 | J9: =IF(G9="Yes",0,I9*21%) | K9: =I9+J9 | L9: NL | M9: Reverified 2026-09-02; NL retail/MSRP | N9: https://www.caraudio.nl/artikel/match-up-10dsp-mk2-10-kanaals-dsp-versterker-maup10dspmk2 | O9: 2026-09-02
A10: MATCH UP 10DSP MK2 (alternative) | B10: DE/FR | C10: ARS24 | D10: EUR | E10: 1049 | F10: 1 | G10: Yes | H10: 1 | I10: =E10*H10 | J10: =IF(G10="Yes",0,I10*21%) | K10: =I10+J10 | L10: Ships DE/AT/FR | M10: Current / in stock | N10: https://www.ars24.com/en/match-up10dsp-mk2 | O10: 2026-09-01
A11: MATCH UP 10DSP MK2 (alternative) | B11: USA | C11: Crutchfield | D11: USD | E11: 1450 | F11: 1 | G11: No | H11: 0.860404 | I11: =E11*H11 | J11: =IF(G11="Yes",0,I11*21%) | K11: =I11+J11 | L11: Excl. import/shipping | M11: Current US retail | N11: https://www.crutchfield.com/shopsearch/MATCH_UP_10_DSP.html | O11: 2026-09-01
A12: Audison DRC MP CAN | B12: NL | C12: MB Car Audio | D12: EUR | E12: 179 | F12: 1 | G12: Yes | H12: 1 | I12: =E12*H12 | J12: =IF(G12="Yes",0,I12*21%) | K12: =I12+J12 | L12: Free NL shipping threshold met | M12: Reverified 2026-09-02; MBC route retained | N12: https://mbcaraudio.nl/bass-controls/audison-drc-mp-can.html | O12: 2026-09-02
A13: HELIX DIRECTOR SCP (alternative) | B13: NL | C13: HifiMotive | D13: EUR | E13: 299 | F13: 1 | G13: Yes | H13: 1 | I13: =E13*H13 | J13: =IF(G13="Yes",0,I13*21%) | K13: =I13+J13 | L13: NL | M13: Current | N13: https://www.caraudio.nl/artikel/helix-director-remote-control-met-touchscreen-en-scp-aansluiting-hedirectscp | O13: 2026-09-01
A14: MATCH PP-TES 1.7B Highland | B14: NL | C14: HifiMotive | D14: EUR | E14: 129 | F14: 1 | G14: Yes | H14: 1 | I14: =E14*H14 | J14: =IF(G14="Yes",0,I14*21%) | K14: =I14+J14 | L14: NL | M14: Reverified 2026-09-02 official NL MSRP; MBC lists €139.95 | N14: https://www.caraudio.nl/artikel/match/match-pp-tes-1-7b-highland-kabelset-voor-tesla-model-3-highland-y-juniper-met-base-audio-mapptes17bhl | O14: 2026-09-02
A15: MATCH PP-TES 1.7B Highland | B15: DE | C15: CarHifi-Store Bünde | D15: EUR | E15: 129 | F15: 1 | G15: Yes | H15: 1 | I15: =E15*H15 | J15: =IF(G15="Yes",0,I15*21%) | K15: =I15+J15 | L15: DE/EU shipping | M15: Current / in stock | N15: https://www.carhifi-store-buende.de/endstufen/ | O15: 2026-09-01
A16: HELIX Ci3 K200.2TES4 Highland | B16: DE | C16: CarHifi-Store Bünde | D16: EUR | E16: 729 | F16: 1 | G16: Yes | H16: 1 | I16: =E16*H16 | J16: =IF(G16="Yes",0,I16*21%) | K16: =I16+J16 | L16: EU shipping extra | M16: Reverified 2026-09-02; Highland-specific kit in stock | N16: https://www.carhifi-store-buende.de/compose-ci3-k200.2tes4-tesla-model-3-highland | O16: 2026-09-02
... A30: PowerBass OE40CN-T3Y | B30: GR | C30: iCan Greece | D30: EUR | E30: 121.5 | F30: 1 | G30: Yes | H30: 1 | I30: =E30*H30 | J30: =IF(G30="Yes",0,I30*21%) | K30: =I30+J30 | L30: GR/EU route TBD | M30: Current listing; use only after marketplace/shop check | N30: https://ican.gr/ήχος-και-εικόνα-αυτοκινήτου/ηχεία-αυτοκινήτου/ηχεία-εργοστασιακού-τύπου-oem/powerbass-oe40cn-t3y-διαιρούμενα-ηχεία-αυτοκινήτου-4-oem | O30: 2026-09-02
A32: FULL HELIX 2026-09-06
A33: HELIX i5-priority + V EIGHTEEN | B33: ='HELIX_i5_Setup'!B29 | C33: 15 full-active cabin channels; known hardware only
A34: HELIX i7-priority + V EIGHTEEN | B34: ='HELIX_i7_Setup'!B29 | C34: 15 full-active cabin channels; known hardware only
A35: Known i7 premium vs i5 | B35: ='HELIX_Comparison'!C7 | C35: Does not include TBD install/integration differences
A36: MATCH UP 1FX | B36: NL | C36: HifiMotive / dealer network | D36: EUR | E36: 299 | F36: 1 | G36: Yes | H36: 1 | I36: =E36*H36 | J36: =IF(G36="Yes",0,I36*21%) | K36: =I36+J36 | L36: NL dealer | M36: Current RRP; 10.5–18 V, 1 Ω stable | N36: https://www.caraudio.nl/artikel/helix-src-subwoofer-remote-control-voor-helix-versterkers-hesrc | O36: 2026-09-10
A37: MATCH UP 1FX | B37: DE/FR | C37: ARS24 | D37: EUR | E37: 299 | F37: 1 | G37: Yes | H37: 1 | I37: =E37*H37 | J37: =IF(G37="Yes",0,I37*21%) | K37: =I37+J37 | L37: Free shipping shown; HELIX/MATCH shipping only DE/AT/FR | M37: Ready for dispatch; 1–2 days | N37: https://www.ars24.com/en/match-up1fx | O37: 2026-09-10
A38: HELIX M ONE | B38: DE | C38: CarHifi-Store Bünde | D38: EUR | E38: 299 | F38: 1 | G38: Yes | H38: 1 | I38: =E38*H38 | J38: =IF(G38="Yes",0,I38*21%) | K38: =I38+J38 | L38: DE/EU shipping verify | M38: Available in 4 days listing; 10.5–16 V, 1 Ω stable | N38: https://www.carhifi-store-buende.de/endstufen/helix/ | O38: 2026-09-10
A39: HELIX M ONE X | B39: DE | C39: CarHifi-Store Bünde | D39: EUR | E39: 379 | F39: 1 | G39: Yes | H39: 1 | I39: =E39*H39 | J39: =IF(G39="Yes",0,I39*21%) | K39: =I39+J39 | L39: DE/EU shipping verify | M39: Available in 4 days listing; 10.5–16 V, 1 Ω stable | N39: https://www.carhifi-store-buende.de/helix-m-one-x | O39: 2026-09-10

Sheet Speaker_Map
A1: 15-speaker locatie- en kanaalplan
A2: Provisional channel map. De exacte SOP9 pinout en de Pioneer-submodule worden in v1.1 verwerkt zodra het modelnummer beschikbaar is.
A4: # | B4: Tesla speakerpositie | C4: Driver | D4: Physical speakers | E4: Amplification | F4: Provisional channel | G4: Crossover / DSP note | H4: Fitment status | I4: Risk / action
A5: 1 | B5: Front door woofer L | C5: Ci3 W200FM-S3 | D5: 1 | E5: Audison | F5: CH1 | G5: HP/LP DSP; final XO after measurement | H5: Highland adapter included | I5: Low risk
A6: 2 | B6: Front door woofer R | C6: Ci3 W200FM-S3 | D6: 1 | E6: Audison | F6: CH2 | G6: HP/LP DSP; final XO after measurement | H6: Highland adapter included | I6: Low risk
A7: 3 | B7: Dash mid L + front tweeter L | C7: Ci3 M100FM-S3 + T20FM-TI | D7: 2 | E7: Audison via passive XO | F7: CH3 | G7: Integrated 6 dB crossover in Highland kit | H7: Kit supplied | I7: Verify wiring polarity
A8: 4 | B8: Dash mid R + front tweeter R | C8: Ci3 M100FM-S3 + T20FM-TI | D8: 2 | E8: Audison via passive XO | F8: CH4 | G8: Integrated 6 dB crossover in Highland kit | H8: Kit supplied | I8: Verify wiring polarity
A9: 5 | B9: Dash center | C9: Ci3 C100.2FM-S3 | D9: 1 | E9: Audison | F9: CH5 | G9: Center level / delay / upmix as desired | H9: Kit supplied | I9: Tune conservatively
A10: 6 | B10: Front door 80 mm L | C10: Ci5 M80FM-S3 | D10: 1 | E10: Audison | F10: CH6 | G10: Band-pass DSP | H10: Adapter TBD | I10: Physical adapter check
A11: 7 | B11: Front door 80 mm R | C11: Ci5 M80FM-S3 | D11: 1 | E11: Audison | F11: CH7 | G11: Band-pass DSP | H11: Adapter TBD | I11: Physical adapter check
A12: 8 | B12: Rear door L | C12: Ci3 M100FM-S3 | D12: 1 | E12: Audison | F12: CH8 | G12: Band-pass / full-range depending cabin tune | H12: Adapter TBD | I12: Connector check
A13: 9 | B13: Rear door R | C13: Ci3 M100FM-S3 | D13: 1 | E13: Audison | F13: CH9 | G13: Band-pass / full-range depending cabin tune | H13: Adapter TBD | I13: Connector check
A14: 10 | B14: Parcel shelf L | C14: Ci3 M100FM-S3 | D14: 1 | E14: Audison | F14: CH10 | G14: Surround/rear fill; HP required | H14: Premium position / custom mount | I14: Verify physical opening and trim
A15: 11 | B15: Parcel shelf R | C15: Ci3 M100FM-S3 | D15: 1 | E15: Audison | F15: CH11 | G15: Surround/rear fill; HP required | H15: Premium position / custom mount | I15: Verify physical opening and trim
A16: 12 | B16: Headliner L | C16: Ci5 M50FM-S3 | D16: 1 | E16: Auxiliary 2ch amp via Audison DSP OUT | F16: AUX-L | G16: PAUDIO-only endpoint X569; final HP/EQ in Audison DSP | H16: PAUDIO-only / adapter TBD | I16: Do not assume BAUDIO OEM channel; verify wire path or add new pigtail.
A17: 13 | B17: Headliner R | C17: Ci5 M50FM-S3 | D17: 1 | E17: Auxiliary 2ch amp via Audison DSP OUT | F17: AUX-R | G17: PAUDIO-only endpoint X579; final HP/EQ in Audison DSP | H17: PAUDIO-only / adapter TBD | I17: Do not assume BAUDIO OEM channel; verify wire path or add new pigtail.
A20: Physical speaker count | B20: =SUM(D5:D17)
A21: Audison amp channels used | B21: 11
A22: Audison spare amp channels | B22: =12-B21
A23: Sub amp feed | B23: Audison DSP OUT → existing Pioneer amp
A25: EPC correction | B25: Headliner X569/X579 are PAUDIO option endpoints. Existing BAUDIO 9 cannot be assumed to have active/populated headliner channels.

Sheet HELIX_Budget_BOM
A1: FULL HELIX BUDGET BOM — COMMON SPEAKER / CONTROL BASKET
A2: Price snapshot 2026-09-10. Current Germany-first value basket for 15 physical cabin speakers. Current lead uses V EIGHTEEN separately; this common basket contains speakers/controller/harness basis only. Supplier feedback is treated separately from verified product-page data.
A4: Category | B4: Part / package | C4: Qty | D4: Unit price € | E4: Line total € | F4: Country / seller | G4: Role / positions | H4: Fit / architecture note | I4: Availability / shipping | J4: Source URL | K4: Checked | L4: Confidence
A5: Speaker package | B5: HELIX Compose Ci3 K200.2TES4 Tesla Model 3 Highland | C5: 1 | D5: 729 | E5: =C5*D5 | F5: DE · CarHifi-Store Bünde | G5: 7 physical front/center speakers | H5: 2x woofer + 2x mid + 2x tweeter + center; supplied as passive 2.5-way L/R front system with Highland adapters/connectors. For the final 15-channel full-active map, bypass/rewire the passive L/R crossover and route front mid/tweeter drivers individually. | I5: Sofort verfügbar in current listing; pickup/shipping timing confirm before order | J5: https://www.carhifi-store-buende.de/lautsprecher/nach-fahrzeug/tesla/model-3-highland/ | K5: 2026-09-10 | L5: HIGH
A6: Speaker pair | B6: HELIX Ci5 M80FM-S3 | C6: 1 | D6: 199 | E6: =C6*D6 | F6: DE · CarHifi-Store Bünde | G6: Front door 80 mm L/R X570/X580 | H6: Exact SOP9 physical adapter/pigtail still verify | I6: Sofort verfügbar in current listing | J6: https://www.carhifi-store-buende.de/helix-ci5-m80fm-s3 | K6: 2026-09-10 | L6: HIGH
A7: Speaker pairs | B7: HELIX Ci3 M100FM-S3 | C7: 2 | D7: 159 | E7: =C7*D7 | F7: DE · CarHifi-Store Bünde | G7: Rear doors + parcel shelf (4 drivers) | H7: Rear/parcel SOP9 adapter geometry still verify | I7: Sofort verfügbar in current listing | J7: https://www.carhifi-store-buende.de/helix-ci3-m100fm-s3 | K7: 2026-09-10 | L7: HIGH
A8: Speaker pair | B8: HELIX Ci5 M50FM-S3 | C8: 1 | D8: 169 | E8: =C8*D8 | F8: DE · CarHifi-Store Bünde | G8: Headliner L/R X569/X579 | H8: PAUDIO-only target positions; custom mount/pigtail verify | I8: Sofort verfügbar in current listing | J8: https://www.carhifi-store-buende.de/helix-ci5-m50fm-s3 | K8: 2026-09-10 | L8: HIGH
A9: Adapter reserve | B9: HELIX FlexMount100 Tesla adapter reserve | C9: 2 | D9: 19.99 | E9: =C9*D9 | F9: DE / EU reference | G9: Rear/parcel 100 mm positions | H9: Planning reserve only; exact SOP9 rear/parcel adapter count must be verified | I9: Do not order until physical EPC/fit check | J9: https://www.audiotec-fischer.de/en/tools/flexmount-finder/ | K9: 2026-09-06 | L9: MEDIUM
A10: Tesla interface | B10: MATCH PP-TES 1.7B Highland | C10: 1 | D10: 129 | E10: =C10*D10 | F10: DE · CarHifi-Store Bünde | G10: Tesla-side no-cut donor / interposer | H10: Officially intended for MATCH UP10; HELIX V-series side requires custom repin/interposer | I10: Sofort verfügbar; officially intended for MATCH UP10, so use only as Tesla-side donor/interposer basis | J10: https://www.carhifi-store-buende.de/match-pp-tes-1.7b-highland | K10: 2026-09-10 | L10: HIGH
A11: Controller | B11: HELIX DIRECTOR display remote — connector variant matched to DSP | C11: 1 | D11: 249 | E11: =C11*D11 | F11: DE/FR · ARS24 | G11: Touchscreen DSP / master / sub control | H11: Use DIRECTOR for SCP on V EIGHTEEN / V TWELVE MK2 / NEXT V EIGHT ULTIMATE; legacy V EIGHT MK1/MK2 requires DIRECTOR for Control Input. Price basis remains €249. | I11: 2–3 day listing; ships HELIX only to DE/AT/FR. NL HifiMotive RRP €299. Pickup/logistics may change best source. | J11: https://www.ars24.com/en/helix-director-for-scp | K11: 2026-09-10 | L11: HIGH
A13: COMMON KNOWN HARDWARE TOTAL | E13: =SUM(E5:E11)
A14: Includes | B14: 15 physical cabin speakers, HELIX DIRECTOR and Tesla-side harness donor/interposer. Does NOT include the V EIGHTEEN main DSP/amp.
A15: Excluded / TBD | B15: Power cable, high-current fusing/distribution, damping, custom SOP9 pigtails/mounts, final interposer construction, shipping where not explicit, and Pioneer voltage/inrush hardware remain excluded/TBD.

Sheet HELIX_Budget_Routes
A1: FULL HELIX BUDGET ROUTES — €3,500 TARGET / €4,000 HARD CAP
A2: All routes use the refreshed 2026-09-10 15-speaker HELIX-DE value basket and retained Pioneer donor subsystem. The V EIGHTEEN is the current lead; split/staged routes remain for budget comparison. A €250 planning reserve is illustrative, not a quote. | V2: Planning reserve € | W2: 250
A4: ID | B4: Architecture | C4: Main DSP / amp | D4: Extension | E4: Central DSP ch. | F4: Cabin amp feeds | G4: Front L/R mid+tweeter strategy | H4: 15 physical speakers? | I4: Pioneer sub DSP path | J4: Common basket € | K4: DSP/amp € | L4: Known total € | M4: Δ vs €3,500 | N4: Headroom to €4,000 | O4: Future path | P4: Main benefit | Q4: Trade-off | R4: Status | T4: Route | U4: Known total | V4: Practical total incl. reserve | W4: Δ vs €3,500 incl. reserve | X4: Headroom to €4,000 incl. reserve
A5: R1 | B5: ONE-BOX FUTURE-PROOF | C5: HELIX V EIGHTEEN DSP | D5: None | E5: 20 | F5: 18 available | G5: Passive Ci3 kit initially; can later bypass XO for 15-channel full active | H5: YES | I5: Processed RCA OUT → Pioneer donor amp | J5: ='HELIX_Budget_BOM'!E13 | K5: 1799 | L5: =J5+K5 | M5: =3500-L5 | N5: =4000-L5 | O5: Start passive at 13 feeds; later full-active 15 without changing DSP | P5: Simplest wiring, 18 amp / 20 DSP, 3 spare amp channels after full-active conversion | Q5: ~€112 over €3,500 before shipping/wiring | R5: RECOMMENDED | T5: R1 | U5: 3611.98 | V5: =L5+$W$2 | W5: =3500-V5 | X5: =4000-V5
A6: R2 | B6: BEST NEW ~€3.5K SPLIT | C6: HELIX NEXT V EIGHT DSP ULTIMATE | D6: HELIX AMPLIFY 206 DIRECT | E6: 14 | F6: 8 + 6 available | G6: KEEP Highland kit passive L/R → 13 cabin feeds total | H6: YES | I6: 6th processed RCA → Pioneer donor amp | J6: ='HELIX_Budget_BOM'!E13 | K6: 1708 | L6: =J6+K6 | M6: =3500-L6 | N6: =4000-L6 | O6: 14 DSP outputs exactly cover 13 cabin feeds + sub; no second DSP | P6: Only ~€21 over €3,500; stronger per-channel power; 206 DIRECT designed for HELIX DSP expansion | Q6: Two amplifier boxes; no room for 15 fully-active cabin channels + sub on the 14-channel central DSP | R6: VALUE PICK | T6: R2 | U6: 3520.98 | V6: =L6+$W$2 | W6: =3500-V6 | X6: =4000-V6
A7: R3 | B7: 12CH + SMALL AMP | C7: HELIX V TWELVE DSP MK2 | D7: HELIX AMPLIFY 204 DIRECT | E7: 14 | F7: 12 + up to 4 | G7: KEEP Highland kit passive L/R → 13 cabin feeds total | H7: YES | I7: One V TWELVE RCA → external cabin feed; other RCA → Pioneer donor amp | J7: ='HELIX_Budget_BOM'!E13 | K7: 1738 | L7: =J7+K7 | M7: =3500-L7 | N7: =4000-L7 | O7: Can start V TWELVE only and add 204 later | P7: Simple 12-channel core; staged purchase possible | Q7: Uses only one 204 channel in preferred 13-feed map; nearly same price as R2 with less expansion | R7: GOOD STAGED | T7: R3 | U7: 3550.98 | V7: =L7+$W$2 | W7: =3500-V7 | X7: =4000-V7
A8: R4 | B8: LOWEST NEW HELIX | C8: HELIX V TWELVE DSP MK2 | D8: None | E8: 14 | F8: 12 | G8: Passive front pairs + combine the two headliners on one safe series/mono ambience feed | H8: YES, but 12 feeds | I8: Processed RCA → Pioneer donor amp | J8: ='HELIX_Budget_BOM'!E13 | K8: 1499 | L8: =J8+K8 | M8: =3500-L8 | N8: =4000-L8 | O8: Add AMPLIFY 204 later to split headliners L/R independently | P8: Lowest new route; leaves ~€188 under €3,500 for part of wiring/fusing | Q8: Headliners not independently tuned at first; not full-active | R8: BUDGET COMPROMISE | T8: R4 | U8: 3311.98 | V8: =L8+$W$2 | W8: =3500-V8 | X8: =4000-V8
A9: R5 | B9: 12CH + SECOND DSP NOW/LATER | C9: HELIX V TWELVE DSP MK2 | D9: HELIX AMPLIFY 206 DSP | E9: 14 | F9: 12 + 6 | G9: Can run 15 physical speakers independently across two DSP/amps | H9: YES | I9: V TWELVE stereo RCA reference → 206 DSP; 206 processed RCA → Pioneer | J9: ='HELIX_Budget_BOM'!E13 | K9: 2098 | L9: =J9+K9 | M9: =3500-L9 | N9: =4000-L9 | O9: Buy V TWELVE first; add 206 DSP later when moving to fully separate remaining channels | P9: 15 independent amp feeds possible without replacing V TWELVE; one compact add-on box | Q9: Two DSPs to calibrate; cascaded latency/preset management; only €89 headroom to €4k before wiring | R9: STAGED FULL-ACTIVE | T9: R5 | U9: 3910.98 | V9: =L9+$W$2 | W9: =3500-V9 | X9: =4000-V9
A10: R6 | B10: 12CH + SMALL DSP + AMP LATER | C10: HELIX V TWELVE DSP MK2 | D10: HELIX DSP MINI MK2 + AMPLIFY 204 DIRECT | E10: 14 | F10: 12 + 4 | G10: Can run 15 physical speakers independently after second-stage expansion | H10: YES | I10: V TWELVE stereo RCA → DSP MINI; MINI output → Pioneer | J10: ='HELIX_Budget_BOM'!E13 | K10: 2137 | L10: =J10+K10 | M10: =3500-L10 | N10: =4000-L10 | O10: Explicit small-DSP upgrade path; can defer MINI + 204 until later | P10: Flexible DSP MINI outputs and reusable 204 amplifier | Q10: Two extra boxes, more wiring, and €39 MORE than the 206 DSP route | R10: NOT PREFERRED | T10: R6 | U10: 3949.98 | V10: =L10+$W$2 | W10: =3500-V10 | X10: =4000-V10
A11: R7 | B11: USED 12CH + SMALL AMP | C11: HELIX V TWELVE DSP MK2 USED | D11: HELIX AMPLIFY 204 DIRECT | E11: 14 | F11: 12 + up to 4 | G11: KEEP Highland kit passive L/R → 13 cabin feeds total | H11: YES | I11: One RCA → external feed; one RCA → Pioneer | J11: ='HELIX_Budget_BOM'!E13 | K11: 1439 | L11: =J11+K11 | M11: =3500-L11 | N11: =4000-L11 | O11: Same topology as R3; replace/upgrade only if future full-active desired | P11: Current German private listing at €1,200 keeps the route near €3.25k known hardware and leaves budget for wiring/damping. | Q11: Used/private-market warranty risk; current indexed price is €1,200, not the earlier €1,050 scout. | R11: BEST COST IF USED OK | T11: R7 | U11: 3251.98 | V11: =L11+$W$2 | W11: =3500-V11 | X11: =4000-V11
A12: R8 | B12: USED 12CH + SECOND DSP | C12: HELIX V TWELVE DSP MK2 USED | D12: HELIX AMPLIFY 206 DSP | E12: 14 | F12: 12 + 6 | G12: 15 independent physical cabin feeds across two DSP/amps | H12: YES | I12: V TWELVE stereo RCA → 206 DSP → Pioneer from 206 RCA | J12: ='HELIX_Budget_BOM'!E13 | K12: 1799 | L12: =J12+K12 | M12: =3500-L12 | N12: =4000-L12 | O12: Full 15-channel staged system without replacing used V TWELVE | P12: Current €1,200 used V TWELVE + 206 DSP gives 15 independent cabin feeds for ~€3.61k known hardware. | Q12: Used V TWELVE + two-DSP calibration complexity | R12: USED FULL-ACTIVE VALUE | T12: R8 | U12: 3611.98 | V12: =L12+$W$2 | W12: =3500-V12 | X12: =4000-V12
A13: R9 | B13: CLEARANCE DSP + SECOND DSP | C13: HELIX V EIGHT DSP (legacy / new-old-stock) | D13: HELIX AMPLIFY 206 DSP | E13: 10ch main + 8ch downstream | F13: 8 + 6 available | G13: KEEP Highland kit passive L/R → 13 cabin feeds total | H13: YES | I13: V EIGHT processed stereo RCA → 206 DSP; one 206 RCA → Pioneer donor amp | J13: ='HELIX_Budget_BOM'!E13 | K13: 1548 | L13: =J13+K13 | M13: =3500-L13 | N13: =4000-L13 | O13: Clearance V EIGHT handles 8 cabin feeds; 206 DSP derives the remaining 5 cabin feeds + Pioneer sub from the processed stereo reference | P13: Lowest verified all-new HELIX route with independent L/R headliners: ~€3.36k known hardware | Q13: Legacy 10-channel V EIGHT / only 6 high-level inputs; two DSPs; clearance stock can disappear Legacy V EIGHT also needs DIRECTOR for Control Input, not the SCP connector variant. | R13: BUDGET SLEEPER | T13: R9 | U13: 3360.98 | V13: =L13+$W$2 | W13: =3500-V13 | X13: =4000-V13
A14: R10 | B14: CLEARANCE FULL-ACTIVE / MAX COMPLEXITY | C14: HELIX V EIGHT DSP (legacy / new-old-stock) | D14: HELIX AMPLIFY 206 DSP + AMPLIFY 204 DIRECT | E14: 10ch main + 8ch downstream | F14: 8 + 6 + 4 available | G14: 15 individually amplified cabin speakers | H14: YES | I14: V EIGHT stereo RCA → 206 DSP; 206 RCA1 → 204 DIRECT → 15th cabin feed; RCA2 → Pioneer donor amp | J14: ='HELIX_Budget_BOM'!E13 | K14: 1787 | L14: =J14+K14 | M14: =3500-L14 | N14: =4000-L14 | O14: 15 individual cabin feeds + Pioneer sub without V EIGHTEEN, but through two DSPs and three HELIX amp boxes | P14: Full-active known hardware ~€3.60k | Q14: Only ~€12 cheaper than V EIGHTEEN route while far more complex; useful as architecture proof, not preferred Legacy V EIGHT also needs DIRECTOR for Control Input, not the SCP connector variant. | R14: FULL-ACTIVE BUT COMPLEX | T14: R10 | U14: 3599.98 | V14: =L14+$W$2 | W14: =3500-V14 | X14: =4000-V14
A15: CURRENT INTERPRETATION
A16: Best long-term new | B16: R1 V EIGHTEEN ≈ €3,632 known hardware including the existing €39.98 adapter reserve. Clean one-box end state; current lead.
A17: Best new near €3,500 | B17: R2 NEXT V EIGHT ULTIMATE + AMPLIFY 206 DIRECT ≈ €3,541 known. Slightly cheaper but adds a second cabin amp and caps the central DSP at 14 outputs.
A18: Best staged 12-channel | B18: R3 V TWELVE + AMPLIFY 204 DIRECT ≈ €3,571 known; R4 V TWELVE alone ≈ €3,332. Useful staged route if the V EIGHTEEN cannot be sourced in time.
A19: Best used-price route | B19: R7 used V TWELVE €1,200 + 204 DIRECT ≈ €3,272 known. Used-price route retained; verify serial/invoice/condition.
A20: Smaller DSP later | B20: R5 V TWELVE + AMPLIFY 206 DSP ≈ €3,931 known. Technically expandable, but the V EIGHTEEN is cleaner at similar final spend.
A21: Best strict-budget all-new | B21: R9 legacy V EIGHT + AMPLIFY 206 DSP ≈ €3,381 known. Clearance route only; two-DSP complexity is the trade-off.
A22: Full-active comparison | B22: R10 legacy V EIGHT + 206 DSP + 204 DIRECT ≈ €3,620 known. Saving versus V EIGHTEEN is negligible; do not choose purely for price.

Sheet HELIX_EU_Prices
A1: HELIX PRICE CHECK — DE / BE / FR
A2: Historical rows preserved. Fresh 2026-09-10 rows appended for Germany HELIX, Netherlands BOXMORE and controller comparison.
A4: Priority | B4: Market | C4: Product | D4: Seller / channel | E4: Price € | F4: Shipping / availability | G4: Price role | H4: Source URL | I4: Current finding | J4: Use in routes | K4: Checked | L4: Confidence | M4: Notes
A5: A | B5: DE | C5: HELIX V EIGHTEEN DSP | D5: Caraudio-store / Bünde / ARS24 | E5: 1799 | F5: Available; multiple DE sellers | G5: Best verified new DE | H5: https://www.caraudio-store.de/DSP-Verstaerker | I5: Same €1,799 across DE and FR-facing listings | J5: R1 | K5: 2026-09-06 | L5: HIGH | M5: No meaningful DE/FR discount found.
A6: B | B6: BE dealer network | C6: HELIX V EIGHTEEN DSP | D6: HifiMotive dealer locator | E6: 1799 | F6: Belgian specialists via dealer locator | G6: Recommended retail | H6: https://www.caraudio.nl/artikel/helix/helix-v-eighteen-dsp-18-kanaals-versterker-met-20-kanaals-dsp-heveighteen | I6: €1,799 RRP; no lower indexed BE checkout found | J6: Reference | K6: 2026-09-06 | L6: MEDIUM | M6: Use dealer quote to try to beat DE price.
A7: B | B7: FR delivery | C7: HELIX V EIGHTEEN DSP | D7: ARS24 / French-language Type-RSound storefront | E7: 1799 | F7: ARS24 states HELIX shipping to France | G7: FR-deliverable reference | H7: https://www.ars24.com/en/helix-verstaerker-made-in-germany | I7: €1,799; no lower indexed FR-local offer found | J7: Reference | K7: 2026-09-06 | L7: HIGH | M7: Type-RSound French storefront also shows €1,799.
A8: A | B8: DE | C8: HELIX NEXT V EIGHT DSP ULTIMATE | D8: Caraudio-store / Audiomativ | E8: 1349 | F8: Available; Audiomativ free DE shipping | G8: Best verified new | H8: https://www.caraudio-store.de/DSP-Verstaerker | I8: €1,349 | J8: R2 | K8: 2026-09-06 | L8: HIGH | M8: 8 speaker outs + 6 processed RCA / 14 DSP.
A9: A | B9: FR-facing | C9: HELIX NEXT V EIGHT DSP ULTIMATE | D9: Type-RSound French storefront | E9: 1349 | F9: French-language checkout storefront | G9: FR-facing price | H9: https://www.type-rsound.com/fr/categories/audio-de-voiture/amplificateur/8-canaux.html | I9: €1,349 | J9: R2 reference | K9: 2026-09-06 | L9: MEDIUM | M9: Store is not necessarily France-based; verify delivered VAT/shipping.
A10: A | B10: DE | C10: HELIX V TWELVE DSP MK2 | D10: Caraudio-store / ARS24 / Bünde | E10: 1499 | F10: DE available; ARS24 ships to France | G10: Best verified new | H10: https://www.caraudio-store.de/Helix-V-TWELVE-DSP-MK2 | I10: €1,499 | J10: R3-R6 | K10: 2026-09-06 | L10: HIGH | M10: 12 amp / 14 DSP / 2 RCA outputs.
A11: B | B11: BE dealer network | C11: HELIX V TWELVE DSP MK2 | D11: HifiMotive / Belgium specialists | E11: 1499 | F11: Dealer quote required | G11: Recommended retail | H11: https://www.caraudio.nl/artikel/helix/helix-v-eighteen-dsp-18-kanaals-versterker-met-20-kanaals-dsp-heveighteen | I11: V TWELVE accessory/dealer RRP €1,499; no lower BE indexed offer found | J11: Reference | K11: 2026-09-06 | L11: MEDIUM | M11: Ask BE dealer for bundle discount rather than list price.
A12: A | B12: FR delivery | C12: HELIX V TWELVE DSP MK2 | D12: ARS24 | E12: 1499 | F12: Free shipping shown; only DE/AT/FR | G12: FR-deliverable reference | H12: https://www.ars24.com/en/helix-v-twelve-dsp-mk2 | I12: €1,499 | J12: R3-R6 | K12: 2026-09-06 | L12: HIGH | M12: Useful for France, not NL/BE.
A13: A | B13: DE | C13: HELIX AMPLIFY 206 DIRECT | D13: ARS24 | E13: 359 | F13: DE/AT/FR shipping; listed 2–3 days | G13: Best verified new | H13: https://www.ars24.com/en/6-kanal-verstaerker/auto-endstufen | I13: €359 | J13: R2 | K13: 2026-09-06 | L13: HIGH | M13: 6x100W@4Ω / 6x190W@2Ω.
A14: A | B14: DE | C14: HELIX AMPLIFY 204 DIRECT | D14: Kaufland marketplace via Idealo | E14: 239 | F14: Free DE shipping in indexed offer | G14: Best verified new | H14: https://www.idealo.de/preisvergleich/Liste/123962287/amp-4000-dab-hifi-stereo-verstaerker.html | I14: €239 | J14: R3/R6/R7 | K14: 2026-09-06 | L14: MEDIUM | M14: Marketplace listing; verify exact 12V 204 DIRECT, not 24V X-OVER.
A15: A | B15: DE/FR | C15: HELIX AMPLIFY 206 DSP | D15: ARS24 / Type-RSound | E15: 599 | F15: ARS24 DE/AT/FR; Type-RSound lists €599 | G15: Best verified new | H15: https://www.ars24.com/en/6-kanal-verstaerker/auto-endstufen | I15: €599 | J15: R5/R8 | K15: 2026-09-06 | L15: HIGH | M15: 6 amp + 8 DSP; 2 processed RCA outputs.
A16: A | B16: DE | C16: HELIX DSP MINI MK2 | D16: Caraudio-store / ARS24 | E16: 399 | F16: Available | G16: Best verified new | H16: https://www.caraudio-store.de/Helix_s3 | I16: €399 | J16: R6 | K16: 2026-09-06 | L16: HIGH | M16: Useful later, but MINI + 204 costs more and adds another box versus 206 DSP.
... A44: A | B44: DE | C44: HELIX Ci7 T20FM-SC | D44: CarHifi-Store Bünde | E44: 399 | F44: Sofort verfügbar / some listings show 4-day replenishment | G44: i7 genuine HELIX reference | H44: https://www.carhifi-store-buende.de/helix-ci7-t20fm-sc | I44: 20 mm silk dome pair | J44: i7 compare | K44: 2026-09-10 | L44: HIGH | M44: Use exact stock confirmation at time of purchase.
A45: A | B45: NL | C45: MATCH UP 1FX | D45: HifiMotive dealer network | E45: 299 | F45: NL RRP | G45: Preferred replacement candidate | H45: https://www.audiotec-fischer.de/en/match/amplifiers/up-1fx | I45: 10.5–18 V; 1 Ω stable; driver series-wiring verification required | J45: Sub amp S3 | K45: 2026-09-10 | L45: HIGH
A46: A | B46: DE/FR | C46: MATCH UP 1FX | D46: ARS24 | E46: 299 | F46: Ready for dispatch 1–2 days; ships DE/AT/FR | G46: Current DE price | H46: https://www.ars24.com/en/match-up1fx | I46: Same €299 price; physical NL pickup not offered by ARS24 | J46: Sub amp S3 | K46: 2026-09-10 | L46: HIGH
A47: B | B47: DE | C47: HELIX M ONE | D47: CarHifi-Store Bünde | E47: 299 | F47: Available in 4 days listing | G47: Full-HELIX alternative | H47: https://www.carhifi-store-buende.de/endstufen/helix/ | I47: 10.5–16 V; 600 W @1 Ω; less voltage headroom than UP 1FX | J47: Sub amp S4 | K47: 2026-09-10 | L47: HIGH
A48: B | B48: DE | C48: HELIX M ONE X | D48: CarHifi-Store Bünde | E48: 379 | F48: Available in 4 days listing | G48: High-power full-HELIX alternative | H48: https://www.carhifi-store-buende.de/helix-m-one-x | I48: 10.5–16 V; 1030 W @1 Ω; likely more power than donor drivers need | J48: Sub amp S5 | K48: 2026-09-10 | L48: HIGH

Sheet HELIX_Budget_Channel_Map
A1: HELIX BUDGET ROUTES — CHANNEL / EXPANSION MAP
A2: These maps show the budget logic. The Highland Ci3 kit keeps the front L/R mid+tweeter pairs passive in most budget routes, so 15 physical speakers require 13 cabin amplifier feeds. v1.7 adds the €949 legacy V EIGHT + 206 DSP clearance path and demonstrates why a three-box full-active variant is not attractive versus V EIGHTEEN.
A4: Route | B4: Stage | C4: Main device / output | D4: External device / output | E4: Cabin feed / function | F4: Physical speakers represented | G4: DSP ownership | H4: Sub path | I4: Upgrade note | J4: Risk / verify
A5: R1 | B5: Now | C5: V EIGHTEEN CH1–13 | D5: — | E5: 13 cabin feeds | F5: 15 physical speakers; front L/R mid+tweeter passive pairs | G5: Single V EIGHTEEN 20ch DSP | H5: V EIGHTEEN processed RCA → Pioneer | I5: Later bypass L/R passive XO and expand to 15 individual V EIGHTEEN channels | J5: Need dedicated wiring to make kit drivers fully active later.
A6: R1 | B6: Later full-active | C6: V EIGHTEEN CH1–15 | D6: — | E6: 15 individual cabin feeds | F6: 15 physical speakers | G6: Single V EIGHTEEN 20ch DSP | H6: Processed RCA → Pioneer | I6: CH16–18 remain spare | J6: Best clean end-state.
A7: R2 | B7: Final | C7: NEXT V EIGHT CH1–8 | D7: 206 DIRECT CH1–5 from V EIGHT RCA OUT1–5 | E7: 13 cabin feeds | F7: 15 physical speakers; passive L/R mid+tweeter pairs | G7: Single V EIGHT 14ch DSP | H7: V EIGHT RCA OUT6 → Pioneer | I7: No second DSP; all 14 DSP channels consumed | J7: Cannot later reach 15 individual cabin channels + sub without another DSP / changing main DSP.
A8: R3 | B8: Stage 1 | C8: V TWELVE CH1–12 | D8: — | E8: 12 cabin feeds | F8: 15 physical; passive front pairs + headliners combined/series as ambience pair | G8: Single V TWELVE 14ch DSP | H8: RCA → Pioneer | I8: Add 204 DIRECT later | J8: Headliner L/R not independently tuned at stage 1; verify 6Ω series wiring and desired mono ambience.
A9: R3 | B9: Stage 2 | C9: V TWELVE CH1–12 | D9: 204 DIRECT CH1 from V TWELVE RCA OUT1 | E9: 13 cabin feeds | F9: 15 physical; passive front pairs, independent headliners | G9: Single V TWELVE 14ch DSP | H9: V TWELVE RCA OUT2 → Pioneer | I9: Final efficient 13-feed solution | J9: 204 is underused but cheapest HELIX extension found.
A10: R5 | B10: Final / staged | C10: V TWELVE CH1–12 | D10: AMPLIFY 206 DSP CH1–3 | E10: 15 individual cabin feeds | F10: 15 physical speakers | G10: Cascaded: V TWELVE + 206 DSP | H10: 206 DSP processed RCA → Pioneer | I10: V TWELVE RCA L/R configured as full-range stereo reference into 206 DSP | J10: Two DSPs; latency/time alignment and preset workflow must be measured/tuned together.
A11: R6 | B11: Later | C11: V TWELVE CH1–12 | D11: DSP MINI → AMPLIFY 204 CH1–3 | E11: 15 individual cabin feeds | F11: 15 physical speakers | G11: Cascaded: V TWELVE + DSP MINI | H11: DSP MINI output → Pioneer | I11: Two DSP MINI outputs remain available | J11: More boxes and €39 higher than 206 DSP extension.
A12: R7/R8 | B12: Used variants | C12: Same as R3 or R5 | D12: Same extensions | E12: Same feed counts | F12: Same 15 physical speakers | G12: Same DSP topology | H12: Same Pioneer path | I12: Only the V TWELVE purchase state changes | J12: Private-sale condition/warranty risk.
A13: R9 | B13: Final budget | C13: V EIGHT DSP CH1–8 | D13: AMPLIFY 206 DSP CH1–5 | E13: 13 cabin feeds | F13: 15 physical; passive front pairs, independent headliners | G13: Cascaded: legacy V EIGHT + 206 DSP | H13: 206 DSP processed RCA → Pioneer | I13: V EIGHT processed RCA L/R configured as stereo reference into 206 DSP | J13: Two DSPs; legacy V EIGHT has only 6 high-level inputs and clearance stock.
A14: R10 | B14: Full-active proof | C14: V EIGHT DSP CH1–8 | D14: 206 DSP CH1–6 + 204 DIRECT CH1 from 206 RCA1 | E14: 15 individual cabin feeds | F14: 15 physical speakers | G14: Cascaded: V EIGHT + 206 DSP | H14: 206 RCA2 → Pioneer | I14: Uses all required downstream outputs; 204 supplies the 15th cabin amplifier channel | J14: Three HELIX boxes. Only ~€12 cheaper than one-box V EIGHTEEN, therefore not recommended new.

Sheet HELIX_Upgrade_Path
A1: HELIX STAGED PURCHASE / UPGRADE PATH
A2: A staged approach avoids buying a second DSP now unless you genuinely need 15 independently amplified cabin drivers. v1.7 includes a €250 configurable practical reserve concept and a current €949 legacy V EIGHT clearance option. Known totals below exclude the reserve unless explicitly stated.
A4: Path | B4: Stage | C4: Purchase now | D4: Stage total € | E4: What works immediately | F4: Later addition | G4: Final known total € | H4: Why choose it | I4: Why not
A5: A — cleanest | B5: 1 | C5: V EIGHTEEN + full budget speaker basket + Director + PP-TES | D5: 3611.98 | E5: All 15 physical speakers; can run 13-feed passive-front initially | F5: Later: only bypass front passive XO / upgrade i5/i7 speakers; no DSP replacement | G5: 3611.98 | H5: One DSP/amp, future full active already supported | I5: ~€112 above €3,500 before wiring.
A6: B — closest new €3.5k | B6: 1 | C6: NEXT V EIGHT ULTIMATE + 206 DIRECT + budget basket | D6: 3520.98 | E6: 15 physical / 13 feeds + processed Pioneer sub | F6: Later second DSP only if moving to 15 independent cabin channels | G6: 3520.98 | H6: Very close to budget and high channel power | I6: Two amp boxes; 14 central DSP channels fully consumed.
A7: C — staged 12ch | B7: 1 | C7: V TWELVE only + budget basket | D7: 3311.98 | E7: 15 physical / 12 feeds; passive front pairs; headliners temporarily combined | F7: Add AMPLIFY 204 DIRECT (€239) when independent headliner L/R tuning is wanted | G7: 3550.98 | H7: Lets you spend on wiring/damping first and add one small amp later | I7: Stage 1 headliner compromise; final still passive front pairs.
A8: D — staged full 15 | B8: 1 | C8: V TWELVE only + budget basket | D8: 3311.98 | E8: Same 12-feed stage as C | F8: Add AMPLIFY 206 DSP (€599); route V TWELVE stereo line reference into second DSP | G8: 3910.98 | H8: 15 independently amplified cabin speakers later without replacing V TWELVE | I8: Two DSP tuning stacks and only ~€89 to €4k before wiring.
A9: E — small DSP later | B9: 1 | C9: V TWELVE only + budget basket | D9: 3311.98 | E9: Same 12-feed stage | F9: Add DSP MINI MK2 (€399) + AMPLIFY 204 DIRECT (€239) | G9: 3949.98 | H9: Explicit small-DSP expansion path | I9: More boxes and higher cost than 206 DSP; not recommended unless MINI is already owned.
A10: F — used value | B10: 1 | C10: Used V TWELVE €1,200 + budget basket | D10: 3012.98 | E10: Same 12-feed stage | F10: Add 204 DIRECT → €3,251.98 OR add 206 DSP → €3,611.98 | G10: 3611.98 | H10: Current used price still leaves more budget than new V TWELVE, but the old €1,050 scout is no longer current. | I10: Used listing is transient/private and two-DSP option remains complex.
A11: G — clearance sleeper | B11: 1 | C11: Legacy V EIGHT DSP €949 + AMPLIFY 206 DSP €599 + budget basket | D11: 3360.98 | E11: 15 physical / 13 feeds; passive front pairs; independent headliners | F11: Optional 204 DIRECT later only if true 15-channel full active becomes mandatory | G11: 3599.98 | H11: Best all-new known-hardware total under €3.5k while keeping touchscreen and independent headliners | I11: Two DSPs and discontinued/clearance main DSP; stock risk.
A12: H — clearance full-active | B12: 2 | C12: Add AMPLIFY 204 DIRECT to path G | D12: 3599.98 | E12: 15 independently amplified cabin speakers + Pioneer DSP feed | F12: No further DSP needed | G12: 3599.98 | H12: Proves full-active can fit ~€3.6k known hardware | I12: Three boxes and only ~€12 cheaper than V EIGHTEEN; choose V EIGHTEEN instead for a new clean build.

Sheet HELIX_Comparison
A1: HELIX FULL-CABIN COMPARISON — i5-PRIORITY vs i7-PRIORITY
A2: Current price snapshot updated 2026-09-06. Existing i5/i7-priority scenarios are preserved. New budget sheets show that the most cost-effective all-HELIX path is a Ci3 Highland/i5 small-driver basket with either V EIGHTEEN (~€3.61k) or NEXT V EIGHT + AMPLIFY 206 DIRECT (~€3.52k).
A4: Metric / decision | B4: i5-priority | C4: i7-priority | D4: Interpretation
A5: Known component total | B5: ='HELIX_i5_Setup'!B29 | C5: ='HELIX_i7_Setup'!B29 | D5: Known retail hardware only; see each setup for exclusions.
A6: Delta vs old €3,500 budget | B6: ='HELIX_i5_Setup'!B31 | C6: ='HELIX_i7_Setup'!B31 | D6: Both exceed the old target before custom integration costs.
A7: i7 premium vs i5 | B7: 0 | C7: =C5-B5 | D7: Additional known retail cost for i7-priority.
A8: Cabin speakers | B8: 15 | C8: 15 | D8: Both complete the 15-speaker target.
A9: Amplified cabin channels | B9: 15 / 18 | C9: 15 / 18 | D9: Three V EIGHTEEN amplified channels remain spare.
A10: DSP channels | B10: 20 | C10: 20 | D10: Two processed RCA outputs feed the retained Pioneer amplifier.
A11: Front woofer | B11: Ci5 S200FM-S2 — 2Ω / 200W RMS / 25–500Hz / 47mm / ±7.8mm | C11: Ci7 W200FM-S3 — 3Ω / 150W RMS / 35–2500Hz / 65.8mm / UHD paper | D11: i5 prioritizes shallow high-excursion low-end; i7 prioritizes broader midbass range, texture and resolution.
A12: Woofer channel constraint | B12: MUST use CH13–18 because 2Ω is only rated there | C12: 3Ω; CH13/14 recommended but not a strict 2Ω constraint | D12: Important wiring difference.
A13: Main midrange strategy | B13: Ci5 M80FM-S3 — 8 units; 80→100 adapters for six 100mm-class positions | C13: Ci7 M100FM-S3 — 6 units directly on FlexMount100 + Ci5 M80 for front 80mm | D13: i7 is physically simpler in 100mm locations; i5 uses more adapter layers.
A14: Center | B14: Ci3 C100.2FM-S3 MK2 coax | C14: Ci3 C100.2FM-S3 MK2 coax | D14: Full-range center chosen intentionally; one speaker from the purchased pair remains spare.
A15: Tweeters | B15: Ci7 T20FM-SC + CFMK20 TES.1 | C15: Ci7 T20FM-SC + CFMK20 TES.1 | D15: Current Tesla FlexMount20 support makes this the fit-first choice in both scenarios.
A16: Headliners | B16: Ci5 M50FM-S3 | C16: Ci5 M50FM-S3 | D16: i7 has no 50mm driver; custom SOP9 headliner fit still requires physical verification.
A17: Front-door 80mm | B17: Ci5 M80FM-S3 | C17: Ci5 M80FM-S3 | D17: i7 has no 80mm driver.
A18: Tesla fit evidence | B18: Official CFMK200 Tesla compatibility includes Ci5 S200; current retailer bundle explicitly lists Model 3 Highland 09/2023-today | C18: Official CFMK200/100/20 Tesla family + current Highland i7 install examples | D18: Strong evidence for core front fit. Rear/parcel/headliner are still SOP9 position-specific verification items.
A19: Sound priority | B19: Best value / dynamics / shallow packaging | C19: Highest resolution / tonal refinement / high-end i7 construction | D19: i7 is the no-compromise sound choice.
... A23: TBD / excluded | B23: Power cable/fusing, final interposer, custom pigtails/adapters, damping, shipping, Pioneer regulation | C23: Same | D23: These can materially increase final installed cost.
A25: CURRENT INTERPRETATION
A26: V EIGHTEEN is the correct HELIX DSP/amplifier for the 15-speaker target. i5-priority is the rational price/performance configuration; i7-priority buys higher-end i7 woofer/midrange construction and simpler native 100mm mounting, but costs about €750 more in currently priced hardware. Neither scenario is purchase-ready until the SOP9 added-position mounts/pigtails and power architecture are physically verified.
A28: NEW BUDGET FINDING — DE / BE / FR SEARCH
A29: V EIGHTEEN + Ci3 Highland budget basket | B29: ≈ €3,611.98 | C29: Best long-term new route | D29: Only ~€91 more than split V EIGHT + 206 DIRECT; true 18/20-channel future-proof core.
A30: NEXT V EIGHT ULTIMATE + 206 DIRECT | B30: ≈ €3,520.98 | C30: Best new route closest to €3,500 | D30: 14 DSP channels exactly match 13 passive-front cabin feeds + Pioneer sub.
A31: V TWELVE + 204 DIRECT | B31: ≈ €3,550.98 | C31: Best 12-channel + small-amp route | D31: Can buy V TWELVE first at ≈€3,311.98 and add 204 later.
A32: Used V TWELVE €1,050 + 204 DIRECT | B32: ≈ €3,101.98 | C32: Best current cost route if used is accepted | D32: Leaves budget for install materials; transient private listing.
A33: V TWELVE + 206 DSP | B33: ≈ €3,910.98 | C33: Best second-DSP staged route | D33: 15 independent cabin amp feeds possible, but two DSPs are more complex than V EIGHTEEN.
A35: v1.8 supplier / sourcing update — 2026-09-10
A37: Route / decision | B37: Known € | C37: Benefit | D37: Trade-off | E37: Current recommendation
A38: V EIGHTEEN + value Full-15 | B38: ='Supplier_Stage_Plan'!C8 | C38: 18 amp / 20 DSP; one-box 15-channel end state | D38: Higher upfront amp cost | E38: CURRENT LEAD
A39: V EIGHTEEN Core-Music-9 now | B39: ='Supplier_Stage_Plan'!C5 | C39: Spend first on positions Schut considers musically relevant | D39: 6 effect/immersion positions deferred | E39: BEST STAGED START
A40: NEXT V EIGHT + 206 DIRECT | B40: ='HELIX_Budget_Routes'!L6 | C40: Near budget, modern split architecture | D40: Second amp; 14 central DSP outputs | E40: ALTERNATIVE
A41: V TWELVE + 204 DIRECT | B41: ='HELIX_Budget_Routes'!L7 | C41: Staged 12-channel path | D41: More boxes for similar final spend | E41: ALTERNATIVE
A42: BOXMORE BXS high-end subset | B42: ='Speaker_Sourcing_NL_DE'!F15 | C42: Potential high-end speaker saving in NL/BE | D42: Not proven identical to exact HELIX i7 SKUs / Tesla adapters | E42: VERIFY PER SKU

Sheet HELIX_i5_Setup
A1: FULL HELIX CABIN — COMPOSE i5-PRIORITY / V EIGHTEEN DSP
A2: 15 individually amplified cabin speakers + retained Pioneer TS-WX1220AH donor sub subsystem. i5-priority means i5 wherever HELIX offers the needed size; i7 T20 is retained for Tesla-specific 20mm tweeter fit, and i3 coax is used for a full-range center.
A4: Category | B4: Item / part | C4: Series | D4: Qty packs | E4: Units / pack | F4: Units used | G4: Size / type | H4: Impedance | I4: RMS / frequency | J4: Suggested channel / role | K4: Adapter / fitment | L4: Unit price | M4: Line total | N4: Preferred shop | O4: Benefit / trade-off | P4: Fitment confidence | Q4: Source URL
A5: DSP / control | B5: HELIX V EIGHTEEN DSP | C5: HELIX | D5: 1 | E5: 1 | F5: 1 | G5: 18ch amp / 20ch DSP | H5: — | I5: CH1-12: 70W@4Ω / up to 100W@3Ω; CH13-18: 75W@4Ω / 120W@2Ω | J5: All 15 cabin channels + RCA OUT 1/2 | K5: Custom SOP9 interposer on Tesla side | L5: 1799 | M5: =IF(ISNUMBER(L5),D5*L5,"") | N5: CarHifi-Store Bünde (DE) · 4-day listing | O5: Only current HELIX all-in-one amplifier with enough amplified channels for 15 individual cabin speakers; 3 amplified channels remain spare. | P5: HIGH - official channel capacity | Q5: https://mbcaraudio.nl/versterkers-met-dsp/helix-v-eighteen-dsp.html
A6: DSP / control | B6: HELIX DIRECTOR for SCP | C6: HELIX | D6: 1 | E6: 1 | F6: 1 | G6: Touchscreen remote | H6: — | I6: DSP control / presets / master / sub level | J6: SCP | K6: SCP cable supplied | L6: 249 | M6: =IF(ISNUMBER(L6),D6*L6,"") | N6: ARS24 (DE/FR) · 2–3 days; NL RRP €299 | O6: Requested display/controller; direct SCP integration. | P6: HIGH | Q6: https://schutcarsystems.nl/product/helix-director/
A7: Integration | B7: MATCH PP-TES 1.7B Highland | C7: MATCH / Audiotec Fischer | D7: 1 | E7: 1 | F7: 1 | G7: Tesla no-cut harness donor | H7: — | I7: Highland standard audio / Ryzen | J7: Tesla BAUDIO → custom V EIGHTEEN interposer | K7: NOT direct V EIGHTEEN PnP; repin/adapt purchased harness only | L7: 129 | M7: =IF(ISNUMBER(L7),D7*L7,"") | N7: CarHifi-Store Bünde (DE) · immediate listing | O7: Uses original Tesla connectors; vehicle loom remains untouched. | P7: HIGH as Tesla-side donor; VERIFY V18 repin | Q7: https://www.caraudio.nl/artikel/match/match-pp-tes-1-7b-highland-kabelset-voor-tesla-model-3-highland-y-juniper-met-base-audio-mapptes17bhl
A8: Speaker | B8: Ci5 S200FM-S2 | C8: i5 | D8: 1 | E8: 2 | F8: 2 | G8: 200 mm hybrid woofer | H8: 2 Ω | I8: 200W RMS / 400W max; 25–500 Hz; 47 mm depth; ±7.8 mm | J8: CH13 / CH14 REQUIRED | K8: CFMK200 TES.1 | L8: 299 | M8: =IF(ISNUMBER(L8),D8*L8,"") | N8: HFB Audio (DE) | O8: Very shallow, high excursion and strong low-frequency authority; excellent value. V EIGHTEEN 2Ω rating exists only on CH13-18. | P8: HIGH driver + official Tesla 200mm adapter; SOP9 connector verify | Q8: https://shop.hfb.audio/produkte-fuers-auto/lautsprecher/824/helix-ci5-s200fm-s2-20cm-tiefton-lautsprecher-mit-geringer-einbautiefe
A9: Speaker | B9: Ci7 T20FM-SC | C9: i7 shared | D9: 1 | E9: 2 | F9: 2 | G9: 20 mm silk dome tweeter | H9: 4 Ω | I9: 1.5–30 kHz; HP ≥2.5kHz @24dB/oct | J9: CH1 / CH2 | K9: CFMK20 TES.1 | L9: 399 | M9: =IF(ISNUMBER(L9),D9*L9,"") | N9: CarHifi-Store Bünde (DE) · stock confirm | O9: Used in i5-priority setup because HELIX currently offers a Tesla FlexMount20 adapter but no Tesla FlexMount25 for Ci5 T25. | P9: HIGH - official Tesla adapter | Q9: https://shop.hfb.audio/produkte-fuers-auto/lautsprecher/816/helix-ci7-t20fm-sc-high-end-hochtoener
A10: Speaker | B10: Ci5 M80FM-S3 | C10: i5 | D10: 4 | E10: 2 | F10: 8 | G10: 80 mm midrange | H10: 3 Ω | I10: 90W RMS / 135W max; 200–6000 Hz | J10: CH3, CH5-CH11 | K10: Direct at X570/X580; CFMK80-100 + CFMK100 TES.1 planned for 100mm-class positions | L10: 199 | M10: =IF(ISNUMBER(L10),D10*L10,"") | N10: CarHifi-Store Bünde (DE) · immediate listing | O10: Compact, efficient and much cheaper than i7 M100. Requires more adapter layers in the 100mm positions. | P10: VERIFY rear/parcel/dashboard physical mounts on SOP9 | Q10: https://shop.hfb.audio/produkte-fuers-auto/lautsprecher/1098/helix-ci5-m80fm-s3-8cm-mitteltoener
A11: Speaker | B11: Ci3 C100.2FM-S3 MK2 | C11: i3 center | D11: 1 | E11: 2 | F11: 1 | G11: 100 mm 2-way coax center | H11: 3 Ω | I11: 80W RMS / 120W max; 100–25kHz | J11: CH4 center | K11: CFMK100 TES.1; one spare speaker remains | L11: 199 | M11: =IF(ISNUMBER(L11),D11*L11,"") | N11: HFB Audio (DE) | O11: Full-range coax center is more appropriate than forcing an i7 M100 mid-only driver into the center. Mirrors the philosophy of the current Highland soundXTREME i7 front + i3 center package. | P11: HIGH driver/adapter family; position verify | Q11: https://shop.hfb.audio/produkte-fuers-auto/lautsprecher/1063/helix-ci3-c100.2fm-s3-mk2
A12: Speaker | B12: Ci5 M50FM-S3 | C12: i5 | D12: 1 | E12: 2 | F12: 2 | G12: 50 mm wideband | H12: 3 Ω | I12: 70W RMS / 100W max; 300–20kHz | J12: CH12 / CH15 headliners | K12: FlexMount50 universal included; SOP9 custom mount/pigtail TBD | L12: 169 | M12: =IF(ISNUMBER(L12),D12*L12,"") | N12: CarHifi-Store Bünde (DE) · immediate listing | O12: Compact true wideband solution for PAUDIO-only headliner positions. | P12: VERIFY custom SOP9 headliner fit/pigtail | Q12: https://shop.hfb.audio/produkte-fuers-auto/lautsprecher/1097/helix-ci5-m50fm-s3-5cm-breitbaender-bzw.-mitteltoener
A13: Adapter | B13: CFMK200 TES.1 (FDM) | C13: FlexMount | D13: 1 | E13: 2 | F13: 2 | G13: 200 mm Tesla Model 3 pair | H13: — | I13: Official compatible with Ci5 S200FM-S2 / Ci7 W200FM-S3 | J13: Front woofer mounts | K13: Tesla Model 3 original woofer position | L13: 99 | M13: =IF(ISNUMBER(L13),D13*L13,"") | N13: Caraudio-Store.de (DE) | O13: Official vehicle-specific 200mm adapter family. | P13: HIGH family fit; confirm Highland connector/pigtail | Q13: https://www.caraudio-store.de/Helix_s11
A14: Adapter | B14: CFMK20 TES.1 | C14: FlexMount | D14: 1 | E14: 2 | F14: 2 | G14: 20 mm Tesla tweeter pair | H14: — | I14: Compatible with Ci7 T20FM-SC | J14: Front tweeters | K14: Tesla factory tweeter mount | L14: 15.7 | M14: =IF(ISNUMBER(L14),D14*L14,"") | N14: CarFeature (DE) | O14: Avoids custom tweeter fabrication. | P14: HIGH - official Tesla adapter | Q14: https://www.carfeature.de/de/hifi-navigation/zubehoer/lautsprecherringe/fuer-einbau/25934/helix-cfmk20-tes.1-adapterringe-fuer-tesla
A15: Adapter | B15: CFMK100 TES.1 | C15: FlexMount | D15: 4 | E15: 2 | F15: 7 | G15: 100 mm Tesla adapter pair | H15: — | I15: Tesla FlexConnect inlay B included | J15: Dash L/R + center + rear L/R + parcel L/R | K15: One adapter remains spare | L15: 19.99 | M15: =IF(ISNUMBER(L15),D15*L15,"") | N15: CarHifi-Store Bünde (DE) | O15: Tesla-specific 100mm interface. In i5 setup most locations also need CFMK80-100. | P15: VERIFY exact SOP9 rear/parcel mount geometry | Q15: https://www.carhifi-store-buende.de/helix-flexmount-cfmk100-tes.1
A16: Adapter | B16: CFMK80-100 | C16: FlexMount | D16: 3 | E16: 2 | F16: 6 | G16: 80→100 mm adapter pair | H16: — | I16: Ci5 M80FM-S3 → FlexMount100 | J16: Dash L/R + rear L/R + parcel L/R | K16: Used together with CFMK100 TES.1 | L16: 19.99 | M16: =IF(ISNUMBER(L16),D16*L16,"") | N16: Just-Sound (DE) | O16: Enables i5 M80 value route in 100mm positions. | P16: HIGH adapter compatibility; vehicle position verify | Q16: https://just-sound.de/HELIX-CFMK80-100-FlexMount80-100-Adapterringe
A17: Existing hardware | B17: Pioneer TS-WX1220AH donor subsystem | C17: Pioneer retained | D17: 1 | E17: 1 | F17: 1 | G17: 2×12in donor drivers + original amp | H17: — | I17: Existing hardware; custom lower-trunk baffle | J17: V EIGHTEEN processed RCA OUT 1/2 → Pioneer amp | K17: Pioneer LV compatibility gate remains | L17: 0 | M17: =IF(ISNUMBER(L17),D17*L17,"") | N17: Already owned | O17: Retains existing sub hardware; no new sub purchase. | P17: BLOCKER - verify/regulate Pioneer 15.1V max supply | Q17: https://pioneer-car.eu/ts-wx1220ah/ts-wx1220ah
A18: TBD integration | B18: Front-door 80 mm SOP9 mount / pigtail verification | C18: Custom | D18: 1 | E18: 1 | F18: 1 | G18: Mount / pigtail | H18: — | I18: TBD | J18: X570 / X580 | K18: Physical proof required before order | M18: =IF(ISNUMBER(L18),D18*L18,"") | N18: TBD NL/DE | O18: Not included in known total. | P18: VERIFY
A19: TBD integration | B19: Headliner 50 mm SOP9 mount / pigtail | C19: Custom | D19: 1 | E19: 1 | F19: 1 | G19: Mount / pigtail | H19: — | I19: TBD | J19: X569 / X579 | K19: PAUDIO-only added positions | M19: =IF(ISNUMBER(L19),D19*L19,"") | N19: TBD NL/DE | O19: Not included in known total. | P19: VERIFY
A20: TBD integration | B20: V EIGHTEEN power / fuse / OFC / distribution | C20: Install material | D20: 1 | E20: 1 | F20: 1 | G20: Power integration | H20: — | I20: V EIGHTEEN: 10.5–18V, 108A max rating, 3×30A internal fuses | J20: Tesla LV → V EIGHTEEN | K20: Engineer final cable/fuse topology | M20: =IF(ISNUMBER(L20),D20*L20,"") | N20: TBD NL/DE | O20: Not included in known total. | P20: VERIFY | Q20: https://www.audiotec-fischer.de/en/helix/amplifiers/v-eighteen-dsp
A21: TBD integration | B21: Pioneer voltage compatibility / regulation | C21: Power gate | D21: 1 | E21: 1 | F21: 1 | G21: High-current DC-DC if required | H21: — | I21: Pioneer max 15.1V vs Tesla published 15.5V | J21: Tesla LV → Pioneer amp | K21: Do not connect directly until verified | M21: =IF(ISNUMBER(L21),D21*L21,"") | N21: TBD | O21: Existing blocker preserved from v1.4. | P21: BLOCKER | Q21: https://pioneer-car.eu/ts-wx1220ah/ts-wx1220ah
A23: OPTIONAL / NOT INCLUDED IN KNOWN TOTAL
A24: Option | B24: Part | C24: Price delta / price | G24: Reason | Q24: Source
A25: Pure i5 tweeter option | B25: Ci5 T25FM-CA | C25: €149/pair instead of €399 | G25: Cheaper and truly i5, but the current HELIX Tesla FlexMount list does not show a Tesla FlexMount25 adapter. Main i5-priority BOM therefore uses i7 T20FM-SC + CFMK20 TES.1 for fit-first integration. | Q25: https://www.audiotec-fischer.de/en/helix/speakers/compose/
A27: SUMMARY
A28: Physical cabin speakers used | B28: =SUMIF(A5:A21,"Speaker",F5:F21) | C28: Must equal 15
A29: Known hardware total | B29: =SUM(M5:M21) | C29: Excludes every row with TBD/blank pricing
A30: Old workbook budget maximum | B30: =Overview!B5 | C30: Legacy €3,500 target
A31: Known delta vs old budget | B31: =B29-B30 | C31: Positive = above old budget
A32: Amplified cabin channels used | B32: 15 | C32: V EIGHTEEN has 18
A33: Spare amplified channels | B33: 3 | C33: CH16-18
A34: DSP channels | B34: 20 | C34: 18 amplified + 2 processed RCA outputs
A35: Pioneer sub signal | B35: V EIGHTEEN processed RCA OUT 1/2 → retained Pioneer TS-WX1220AH donor amplifier | C35: Existing Pioneer drivers/amp remain €0 purchase hardware
A37: KNOWN TOTAL excludes: SOP9-specific custom 80mm/headliner pigtails or mounts, final no-cut V EIGHTEEN interposer work, power/fuse/OFC materials, damping, shipping and any Pioneer DC-DC regulation. Do not treat the known total as an installed turnkey price.

Sheet HELIX_i7_Setup
A1: FULL HELIX CABIN — COMPOSE i7-PRIORITY / V EIGHTEEN DSP
A2: High-end i7 wherever the required 200/100/20mm size exists; i5 M80/M50 fill the 80mm and headliner positions, while Ci3 C100.2FM-S3 MK2 is the recommended full-range center. 15 individual V EIGHTEEN cabin channels + retained Pioneer subsystem.
A4: Category | B4: Item / part | C4: Series | D4: Qty packs | E4: Units / pack | F4: Units used | G4: Size / type | H4: Impedance | I4: RMS / frequency | J4: Suggested channel / role | K4: Adapter / fitment | L4: Unit price | M4: Line total | N4: Preferred shop | O4: Benefit / trade-off | P4: Fitment confidence | Q4: Source URL
A5: DSP / control | B5: HELIX V EIGHTEEN DSP | C5: HELIX | D5: 1 | E5: 1 | F5: 1 | G5: 18ch amp / 20ch DSP | H5: — | I5: CH1-12: 70W@4Ω / up to 100W@3Ω; CH13-18: 75W@4Ω / 120W@2Ω | J5: All 15 cabin channels + RCA OUT 1/2 | K5: Custom SOP9 interposer on Tesla side | L5: 1799 | M5: =IF(ISNUMBER(L5),D5*L5,"") | N5: CarHifi-Store Bünde (DE) · 4-day listing | O5: Only current HELIX all-in-one amplifier with enough amplified channels for 15 individual cabin speakers; 3 amplified channels remain spare. | P5: HIGH - official channel capacity | Q5: https://mbcaraudio.nl/versterkers-met-dsp/helix-v-eighteen-dsp.html
A6: DSP / control | B6: HELIX DIRECTOR for SCP | C6: HELIX | D6: 1 | E6: 1 | F6: 1 | G6: Touchscreen remote | H6: — | I6: DSP control / presets / master / sub level | J6: SCP | K6: SCP cable supplied | L6: 249 | M6: =IF(ISNUMBER(L6),D6*L6,"") | N6: ARS24 (DE/FR) · 2–3 days; NL RRP €299 | O6: Requested display/controller; direct SCP integration. | P6: HIGH | Q6: https://schutcarsystems.nl/product/helix-director/
A7: Integration | B7: MATCH PP-TES 1.7B Highland | C7: MATCH / Audiotec Fischer | D7: 1 | E7: 1 | F7: 1 | G7: Tesla no-cut harness donor | H7: — | I7: Highland standard audio / Ryzen | J7: Tesla BAUDIO → custom V EIGHTEEN interposer | K7: NOT direct V EIGHTEEN PnP; repin/adapt purchased harness only | L7: 129 | M7: =IF(ISNUMBER(L7),D7*L7,"") | N7: CarHifi-Store Bünde (DE) · immediate listing | O7: Uses original Tesla connectors; vehicle loom remains untouched. | P7: HIGH as Tesla-side donor; VERIFY V18 repin | Q7: https://www.caraudio.nl/artikel/match/match-pp-tes-1-7b-highland-kabelset-voor-tesla-model-3-highland-y-juniper-met-base-audio-mapptes17bhl
A8: Speaker | B8: Ci7 W200FM-S3 | C8: i7 | D8: 1 | E8: 2 | F8: 2 | G8: 200 mm high-end woofer | H8: 3 Ω | I8: 150W RMS / 225W max; 35–2500 Hz; 65.8 mm depth | J8: CH13 / CH14 suggested | K8: CFMK200 TES.1 | L8: 509 | M8: =IF(ISNUMBER(L8),D8*L8,"") | N8: CarHifi-Store Bünde (DE) · no-grille listing €509; standard set €539 | O8: Made in Germany i7 front woofer; broader upper range and UHD paper cone for cleaner midbass/transition. Less shallow and lower excursion than i5 S200. | P8: HIGH driver + Highland evidence; SOP9 connector verify | Q8: https://shop.hfb.audio/produkte-fuers-auto/lautsprecher/817/helix-ci7-w200fm-s3-20cm-highend-mittel/tiefton-lautsprecher
A9: Speaker | B9: Ci7 T20FM-SC | C9: i7 | D9: 1 | E9: 2 | F9: 2 | G9: 20 mm high-end silk dome | H9: 4 Ω | I9: 1.5–30 kHz; HP ≥2.5kHz @24dB/oct | J9: CH1 / CH2 | K9: CFMK20 TES.1 | L9: 399 | M9: =IF(ISNUMBER(L9),D9*L9,"") | N9: CarHifi-Store Bünde (DE) · stock confirm | O9: Made in Germany high-end tweeter with official Tesla adapter support. | P9: HIGH - official Tesla adapter | Q9: https://shop.hfb.audio/produkte-fuers-auto/lautsprecher/816/helix-ci7-t20fm-sc-high-end-hochtoener
A10: Speaker | B10: Ci7 M100FM-S3 | C10: i7 | D10: 3 | E10: 2 | F10: 6 | G10: 100 mm high-end midrange | H10: 3 Ω | I10: 100W RMS / 150W max; 110–7000 Hz | J10: CH3, CH5, CH8-CH11 | K10: CFMK100 TES.1 | L10: 399 | M10: =IF(ISNUMBER(L10),D10*L10,"") | N10: CarHifi-Store Bünde (DE) · 4-day listing | O10: Made in Germany; best resolution/tonal detail and direct 100mm FlexMount path for six positions. | P10: VERIFY rear/parcel exact SOP9 fit; Highland front-door evidence exists | Q10: https://shop.hfb.audio/produkte-fuers-auto/lautsprecher/819/helix-ci7-m100fm-s3-10cm-highend-mittelton-lautsprecher
A11: Speaker | B11: Ci3 C100.2FM-S3 MK2 | C11: i3 center | D11: 1 | E11: 2 | F11: 1 | G11: 100 mm 2-way coax center | H11: 3 Ω | I11: 80W RMS / 120W max; 100–25kHz | J11: CH4 center | K11: CFMK100 TES.1; one spare speaker remains | L11: 199 | M11: =IF(ISNUMBER(L11),D11*L11,"") | N11: HFB Audio (DE) | O11: Recommended center: full-range coax; current Highland soundXTREME likewise combines i7 front components with i3 center. | P11: HIGH driver/adapter family; position verify | Q11: https://shop.hfb.audio/produkte-fuers-auto/lautsprecher/1063/helix-ci3-c100.2fm-s3-mk2
A12: Speaker | B12: Ci5 M80FM-S3 | C12: i5 shared | D12: 1 | E12: 2 | F12: 2 | G12: 80 mm advanced midrange | H12: 3 Ω | I12: 90W RMS / 135W max; 200–6000 Hz | J12: CH6 / CH7 | K12: Front-door 80mm mount/pigtail verify | L12: 199 | M12: =IF(ISNUMBER(L12),D12*L12,"") | N12: CarHifi-Store Bünde (DE) · immediate listing | O12: i7 line has no 80mm driver; Ci5 M80 is the logical HELIX Compose fit. | P12: VERIFY SOP9 front-door 80mm mounting details | Q12: https://shop.hfb.audio/produkte-fuers-auto/lautsprecher/1098/helix-ci5-m80fm-s3-8cm-mitteltoener
A13: Speaker | B13: Ci5 M50FM-S3 | C13: i5 shared | D13: 1 | E13: 2 | F13: 2 | G13: 50 mm advanced wideband | H13: 3 Ω | I13: 70W RMS / 100W max; 300–20kHz | J13: CH12 / CH15 | K13: FlexMount50 universal included; SOP9 custom mount/pigtail TBD | L13: 169 | M13: =IF(ISNUMBER(L13),D13*L13,"") | N13: CarHifi-Store Bünde (DE) · immediate listing | O13: i7 line has no 50mm driver; Ci5 M50 gives full-range headliner coverage. | P13: VERIFY custom SOP9 headliner fit/pigtail | Q13: https://shop.hfb.audio/produkte-fuers-auto/lautsprecher/1097/helix-ci5-m50fm-s3-5cm-breitbaender-bzw.-mitteltoener
A14: Adapter | B14: CFMK200 TES.1 (FDM) | C14: FlexMount | D14: 1 | E14: 2 | F14: 2 | G14: 200 mm Tesla Model 3 pair | H14: — | I14: Official compatible with Ci7 W200FM-S3 and Ci5 S200FM-S2 | J14: Front woofer mounts | K14: Tesla Model 3 original woofer position | L14: 99 | M14: =IF(ISNUMBER(L14),D14*L14,"") | N14: Caraudio-Store.de (DE) | O14: Official vehicle-specific 200mm adapter family. | P14: HIGH family fit; confirm Highland connector/pigtail | Q14: https://www.caraudio-store.de/Helix_s11
A15: Adapter | B15: CFMK20 TES.1 | C15: FlexMount | D15: 1 | E15: 2 | F15: 2 | G15: 20 mm Tesla tweeter pair | H15: — | I15: Compatible with Ci7 T20FM-SC | J15: Front tweeters | K15: Tesla factory tweeter mount | L15: 15.7 | M15: =IF(ISNUMBER(L15),D15*L15,"") | N15: CarFeature (DE) | O15: Direct Tesla-specific tweeter adapter. | P15: HIGH - official Tesla adapter | Q15: https://www.carfeature.de/de/hifi-navigation/zubehoer/lautsprecherringe/fuer-einbau/25934/helix-cfmk20-tes.1-adapterringe-fuer-tesla
A16: Adapter | B16: CFMK100 TES.1 | C16: FlexMount | D16: 4 | E16: 2 | F16: 7 | G16: 100 mm Tesla adapter pair | H16: — | I16: Tesla FlexConnect inlay B included | J16: Dash L/R + center + rear L/R + parcel L/R | K16: One adapter remains spare | L16: 19.99 | M16: =IF(ISNUMBER(L16),D16*L16,"") | N16: CarHifi-Store Bünde (DE) | O16: Simpler than i5 route because Ci7 M100 natively uses FlexMount100; only center uses same adapter. | P16: VERIFY exact SOP9 rear/parcel mount geometry | Q16: https://www.carhifi-store-buende.de/helix-flexmount-cfmk100-tes.1
A17: Existing hardware | B17: Pioneer TS-WX1220AH donor subsystem | C17: Pioneer retained | D17: 1 | E17: 1 | F17: 1 | G17: 2×12in donor drivers + original amp | H17: — | I17: Existing hardware; custom lower-trunk baffle | J17: V EIGHTEEN processed RCA OUT 1/2 → Pioneer amp | K17: Pioneer LV compatibility gate remains | L17: 0 | M17: =IF(ISNUMBER(L17),D17*L17,"") | N17: Already owned | O17: Retains existing sub hardware; no new sub purchase. | P17: BLOCKER - verify/regulate Pioneer 15.1V max supply | Q17: https://pioneer-car.eu/ts-wx1220ah/ts-wx1220ah
A18: TBD integration | B18: Front-door 80 mm SOP9 mount / pigtail verification | C18: Custom | D18: 1 | E18: 1 | F18: 1 | G18: Mount / pigtail | H18: — | I18: TBD | J18: X570 / X580 | K18: Physical proof required before order | M18: =IF(ISNUMBER(L18),D18*L18,"") | N18: TBD NL/DE | O18: Not included in known total. | P18: VERIFY
A19: TBD integration | B19: Headliner 50 mm SOP9 mount / pigtail | C19: Custom | D19: 1 | E19: 1 | F19: 1 | G19: Mount / pigtail | H19: — | I19: TBD | J19: X569 / X579 | K19: PAUDIO-only added positions | M19: =IF(ISNUMBER(L19),D19*L19,"") | N19: TBD NL/DE | O19: Not included in known total. | P19: VERIFY
A20: TBD integration | B20: V EIGHTEEN power / fuse / OFC / distribution | C20: Install material | D20: 1 | E20: 1 | F20: 1 | G20: Power integration | H20: — | I20: V EIGHTEEN: 10.5–18V, 108A max rating, 3×30A internal fuses | J20: Tesla LV → V EIGHTEEN | K20: Engineer final cable/fuse topology | M20: =IF(ISNUMBER(L20),D20*L20,"") | N20: TBD NL/DE | O20: Not included in known total. | P20: VERIFY | Q20: https://www.audiotec-fischer.de/en/helix/amplifiers/v-eighteen-dsp
A21: TBD integration | B21: Pioneer voltage compatibility / regulation | C21: Power gate | D21: 1 | E21: 1 | F21: 1 | G21: High-current DC-DC if required | H21: — | I21: Pioneer max 15.1V vs Tesla published 15.5V | J21: Tesla LV → Pioneer amp | K21: Do not connect directly until verified | M21: =IF(ISNUMBER(L21),D21*L21,"") | N21: TBD | O21: Existing blocker preserved from v1.4. | P21: BLOCKER | Q21: https://pioneer-car.eu/ts-wx1220ah/ts-wx1220ah
A23: OPTIONAL / NOT INCLUDED IN KNOWN TOTAL
A24: Option | B24: Part | C24: Price delta / price | G24: Reason | Q24: Source
A25: Maximum i7 center option | B25: 4th pair Ci7 M100FM-S3 replacing Ci3 center pair | C25: +€200 known hardware | G25: More i7 content, but M100 is a midrange with 110–7000 Hz response. The recommended Ci3 C100.2FM-S3 MK2 is a 100–25kHz coax and is a more complete center; CarHifi-Store Bünde also uses i3 center with i7 front in its Highland soundXTREME. | Q25: https://www.carhifi-store-buende.de/tesla-model-3-sr-highland-soundxtreme
A27: SUMMARY
A28: Physical cabin speakers used | B28: =SUMIF(A5:A21,"Speaker",F5:F21) | C28: Must equal 15
A29: Known hardware total | B29: =SUM(M5:M21) | C29: Excludes every row with TBD/blank pricing
A30: Old workbook budget maximum | B30: =Overview!B5 | C30: Legacy €3,500 target
A31: Known delta vs old budget | B31: =B29-B30 | C31: Positive = above old budget
A32: Amplified cabin channels used | B32: 15 | C32: V EIGHTEEN has 18
A33: Spare amplified channels | B33: 3 | C33: CH16-18
A34: DSP channels | B34: 20 | C34: 18 amplified + 2 processed RCA outputs
A35: Pioneer sub signal | B35: V EIGHTEEN processed RCA OUT 1/2 → retained Pioneer TS-WX1220AH donor amplifier | C35: Existing Pioneer drivers/amp remain €0 purchase hardware
A37: KNOWN TOTAL excludes: SOP9-specific custom 80mm/headliner pigtails or mounts, final no-cut V EIGHTEEN interposer work, power/fuse/OFC materials, damping, shipping and any Pioneer DC-DC regulation. i7 is the premium/no-compromise cabin route, not a budget route.
A39: v1.8 sourcing note | B39: For the i7-class subset, BOXMORE BXS is a lower-cost NL/BE candidate, but published current specs are not universally identical to HELIX i7. See Speaker_Sourcing_NL_DE before mixing brands.

Sheet HELIX_Channel_Map
A1: HELIX V EIGHTEEN — PROPOSED 15-CHANNEL SOP9 MAP
A2: Same logical map for both scenarios. i5 S200 woofers must be on CH13/14 (2Ω-capable bank). CH16–18 remain spare; processed RCA DSP outputs feed the existing Pioneer donor amplifier.
A4: V EIGHTEEN out | B4: Physical # | C4: Location | D4: Tesla endpoint | E4: i5-priority driver | F4: i7-priority driver | G4: Nominal load | H4: Why this channel | I4: Adapter / mount | J4: Fitment status | K4: DSP starting role | L4: Source / note
A5: CH1 | B5: 3 | C5: Front left tweeter | D5: X565 | E5: Ci7 T20FM-SC | F5: Ci7 T20FM-SC | G5: 4Ω | H5: CH1-12 suitable; dedicated active tweeter | I5: CFMK20 TES.1 | J5: HIGH | K5: HP ≥2.5kHz @24dB/oct; final tune in car | L5: HELIX tweeter official data
A6: CH2 | B6: 4 | C6: Front right tweeter | D6: X575 | E6: Ci7 T20FM-SC | F6: Ci7 T20FM-SC | G6: 4Ω | H6: CH1-12 suitable; dedicated active tweeter | I6: CFMK20 TES.1 | J6: HIGH | K6: HP ≥2.5kHz @24dB/oct; final tune in car | L6: HELIX tweeter official data
A7: CH3 | B7: 5 | C7: Instrument panel left | D7: X566 | E7: Ci5 M80FM-S3 | F7: Ci7 M100FM-S3 | G7: 3Ω | H7: Up to 100W@3Ω typical on CH1-12 | I7: i5: CFMK80-100 + CFMK100 TES.1; i7: CFMK100 TES.1 | J7: VERIFY SOP9 position | K7: Band-pass / time-align | L7: Physical mount verify
A8: CH4 | B8: 6 | C8: Instrument panel center | D8: X595 | E8: Ci3 C100.2FM-S3 MK2 | F8: Ci3 C100.2FM-S3 MK2 | G8: 3Ω | H8: Dedicated RealCenter-capable channel | I8: CFMK100 TES.1 | J8: VERIFY SOP9 center fit | K8: Center / RealCenter; HP tuned after measurement | L8: Full-range coax center
A9: CH5 | B9: 7 | C9: Instrument panel right | D9: X576 | E9: Ci5 M80FM-S3 | F9: Ci7 M100FM-S3 | G9: 3Ω | H9: Up to 100W@3Ω typical on CH1-12 | I9: i5: CFMK80-100 + CFMK100 TES.1; i7: CFMK100 TES.1 | J9: VERIFY SOP9 position | K9: Band-pass / time-align | L9: Physical mount verify
A10: CH6 | B10: 8 | C10: Front left door 80mm | D10: X570 | E10: Ci5 M80FM-S3 | F10: Ci5 M80FM-S3 | G10: 3Ω | H10: Dedicated added PAUDIO position | I10: SOP9 mount/pigtail TBD | J10: VERIFY | K10: Band-pass / time-align | L10: Added PAUDIO-only position
A11: CH7 | B11: 9 | C11: Front right door 80mm | D11: X580 | E11: Ci5 M80FM-S3 | F11: Ci5 M80FM-S3 | G11: 3Ω | H11: Dedicated added PAUDIO position | I11: SOP9 mount/pigtail TBD | J11: VERIFY | K11: Band-pass / time-align | L11: Added PAUDIO-only position
A12: CH8 | B12: 10 | C12: Rear left door | D12: X586 | E12: Ci5 M80FM-S3 | F12: Ci7 M100FM-S3 | G12: 3Ω | H12: Dedicated rear channel | I12: i5: 80→100 + Tesla 100; i7: Tesla 100 | J12: VERIFY | K12: Rear fill; lower level / delay | L12: Exact rear mount verify
A13: CH9 | B13: 11 | C13: Rear right door | D13: X591 | E13: Ci5 M80FM-S3 | F13: Ci7 M100FM-S3 | G13: 3Ω | H13: Dedicated rear channel | I13: i5: 80→100 + Tesla 100; i7: Tesla 100 | J13: VERIFY | K13: Rear fill; lower level / delay | L13: Exact rear mount verify
A14: CH10 | B14: 12 | C14: Parcel shelf left | D14: X588 | E14: Ci5 M80FM-S3 | F14: Ci7 M100FM-S3 | G14: 3Ω | H14: Dedicated PAUDIO parcel channel | I14: i5: 80→100 + Tesla 100; i7: Tesla 100 | J14: VERIFY | K14: Rear ambience / band-pass | L14: Added PAUDIO-only position
A15: CH11 | B15: 13 | C15: Parcel shelf right | D15: X593 | E15: Ci5 M80FM-S3 | F15: Ci7 M100FM-S3 | G15: 3Ω | H15: Dedicated PAUDIO parcel channel | I15: i5: 80→100 + Tesla 100; i7: Tesla 100 | J15: VERIFY | K15: Rear ambience / band-pass | L15: Added PAUDIO-only position
A16: CH12 | B16: 14 | C16: Headliner left | D16: X569 | E16: Ci5 M50FM-S3 | F16: Ci5 M50FM-S3 | G16: 3Ω | H16: Dedicated headliner channel | I16: Custom SOP9 FlexMount50/pigtail TBD | J16: VERIFY | K16: Wideband ambience; aggressive HP protection | L16: PAUDIO-only endpoint
... A19: CH15 | B19: 15 | C19: Headliner right | D19: X579 | E19: Ci5 M50FM-S3 | F19: Ci5 M50FM-S3 | G19: 3Ω | H19: CH1-12 already allocated; CH15 available | I19: Custom SOP9 FlexMount50/pigtail TBD | J19: VERIFY | K19: Wideband ambience; aggressive HP protection | L19: PAUDIO-only endpoint
A20: CH16 | C20: SPARE | D20: — | E20: — | F20: — | G20: — | H20: Reserved | I20: — | J20: SPARE | K20: Future | L20: 3 spare amplified channels total
A21: CH17 | C21: SPARE | D21: — | E21: — | F21: — | G21: — | H21: Reserved | I21: — | J21: SPARE | K21: Future | L21: 3 spare amplified channels total
A22: CH18 | C22: SPARE | D22: — | E22: — | F22: — | G22: — | H22: Reserved | I22: — | J22: SPARE | K22: Future | L22: 3 spare amplified channels total
A23: RCA OUT 1/2 | B23: S1/S2 | C23: Retained Pioneer sub subsystem | D23: — | E23: Pioneer TS-WX1220AH donor amp | F23: Pioneer TS-WX1220AH donor amp | G23: Low-level RCA | H23: Processed DSP outputs 19/20 remain available | I23: RCA to remote Pioneer amp | J23: POWER BLOCKER | K23: Sub LPF / phase / delay set in V EIGHTEEN | L23: Pioneer supply still requires 15.1V compatibility decision

Sheet Alternatives
A1: Architectuurvergelijking
A2: Waarom v1.0 Audison aanbeveelt, plus PnP en high-channel alternatieven.
A4: Option | B4: DSP/Amp | C4: Display | D4: Amp channels | E4: DSP channels | F4: Tesla harness | G4: Estimated system total | H4: Strength | I4: Trade-off | J4: Recommendation
A5: A – Recommended | B5: Audison AF M12.14 bit €1,290 | C5: DRC MP CAN OLED €179 | D5: 12 | E5: 14 | F5: PP-TES donor/interposer; Audison-side custom | G5: =BOM_Recommended!N16 | H5: Best channel count / budget; 6 DSP outputs for Pioneer | I5: Not direct plug-and-play to Audison | J5: BEST FIT | SOP9 v1.3: PAUDIO-only headliners remove the prior assumption of free OEM headliner channels; AUX/grouping may be required.
A6: B – Maximum PnP | B6: MATCH UP 10DSP MK2 €1,049 | C6: HELIX DIRECTOR touchscreen €299 | D6: 10 | E6: 11 | F6: PP-TES 1.7B direct PnP | G6: =BOM_Recommended!N16-1290-179+1049+299 | H6: Factory harness compatibility; easiest DIY | I6: Only 10 amp channels; more OEM/passive grouping needed | J6: SECOND | SOP9 v1.3: PAUDIO-only headliners remove the prior assumption of free OEM headliner channels; AUX/grouping may be required.
A7: C – High channel new | B7: HELIX V TWELVE DSP MK2 €1,499 | C7: HELIX DIRECTOR €299 | D7: 12 | E7: 14 | F7: Custom / adapted Tesla interposer | G7: =BOM_Recommended!N16-1290-179+1499+299 | H7: Excellent DSP + 12 channels | I7: Typically exceeds €3,500 after wiring/adapters | J7: OVER BUDGET | SOP9 v1.3: PAUDIO-only headliners remove the prior assumption of free OEM headliner channels; AUX/grouping may be required.
A8: D – Used high channel | B8: HELIX V TWELVE DSP MK2 used €1,200–1,250 | C8: HELIX DIRECTOR €299 | D8: 12 | E8: 14 | F8: Custom / adapted Tesla interposer | G8: =BOM_Recommended!N16-1290-179+1225+299 | H8: High-end within budget if good used unit found | I8: Used hardware / warranty risk | J8: OPTIONAL | SOP9 v1.3: PAUDIO-only headliners remove the prior assumption of free OEM headliner channels; AUX/grouping may be required.
A9: E – Full-active high channel | B9: HELIX V EIGHTEEN DSP €1,799 | C9: HELIX DIRECTOR €299 | D9: 18 | E9: 20 | F9: Custom / adapted Tesla interposer | G9: =BOM_Recommended!N16-1290-179+1799+299 | H9: All 15 cabin positions can be individually amplified/DSP-routed with channel reserve | I9: About €522 above current €3,500 cap before any speaker/shop savings | J9: PREMIUM / OVER BUDGET
A10: F – PowerBass price route (exploratory) | B10: PowerBass T3Y core + existing DSP choice | C10: Depends on DSP architecture | F10: SOP9 connector/layout verification required | H10: Potentially lower speaker spend; explicit Highland fitment exists for T3Y family | I10: Exact 15-position completion and West-EU retail availability not yet proven | J10: RESEARCH ONLY
A11: G – Full HELIX i5-priority | B11: HELIX V EIGHTEEN DSP €1,799 | C11: HELIX DIRECTOR €299 | D11: 18 | E11: 20 | F11: PP-TES donor → custom V EIGHTEEN interposer | G11: ='HELIX_i5_Setup'!B29 | H11: Best full-HELIX price/performance; i5 shallow/high-excursion woofer, 15 dedicated channels | I11: More 80→100 adapter layers; not literally all i5 because Tesla-compatible tweeter/center sizing | J11: NEW STRONG CANDIDATE — VALUE FULL HELIX
A12: H – Full HELIX i7-priority | B12: HELIX V EIGHTEEN DSP €1,799 | C12: HELIX DIRECTOR €299 | D12: 18 | E12: 20 | F12: PP-TES donor → custom V EIGHTEEN interposer | G12: ='HELIX_i7_Setup'!B29 | H12: Premium full-HELIX route; i7 W200/M100/T20 where available, 15 dedicated channels | I12: About €750 above i5-priority before custom install; i5 M80/M50 still required where i7 has no matching size | J12: NEW PREMIUM CANDIDATE — MAX CABIN QUALITY
A15: Evidence / notes
A16: MATCH PP-TES 1.7B Highland is officially for Ryzen + standard audio Model 3 Highland from MY 10/2023 and MATCH UP10; using it with Audison requires repinning only the purchased harness, not the Tesla vehicle wiring.
A17: Audison official Tesla Sound Pack is currently NOT Highland-compatible; this BOM therefore does not claim the Audison Tesla kit/harness is compatible. It uses the universal AF M12.14 bit with a custom interposer.
A18: China: a verified one-off retail SOP9 15-speaker + DSP/display package was not found. Made-in-China results are wholesale/OEM and not suitable as a direct retail substitute.
A19: 2026-09-02 correction: V EIGHTEEN and PowerBass are comparison routes only; they do not replace the Audison BEST FIT recommendation without a new decision.
A21: v2.1 NOTE
A22: Historical/comparison content retained. Current received MB proposal is authoritative in MB_Quote_2026-09-10 / MBC_Shopping_List and MB_Channel_Map_v2.1.

Sheet Subwoofer_System
A1: Pioneer TS-WX1220AH donor subsystem — custom Tesla lower-trunk installation + replacement-amplifier options
A2: This sheet documents the existing hardware actually reused. It intentionally does not treat the original Pioneer enclosure performance as the performance of the new Tesla installation.
A4: Item | B4: Installed / retained configuration | C4: Official donor specification | D4: Current status | E4: Design implication | F4: Source URL
A5: Donor model | B5: Pioneer TS-WX1220AH | C5: Active Class-D bass-reflex system with 2 × 30 cm drivers | D5: RETAINED AS DONOR HARDWARE | E5: Use donor components only; do not depict original enclosure | F5: https://pioneer-car.eu/ts-wx1220ah/ts-wx1220ah
A6: Woofer drivers | B6: 2 × original 30 cm / 12-inch drivers | C6: 1000 W RMS / 3000 W max donor-system rating | D6: INSTALLED / RETAINED | E6: Mounted in custom rigid baffle/lid at lower extra trunk storage | F6: https://pioneer-car.eu/asset/installation_manuals/UPLOAD_ID_28783/bb886d2a0df764bbfca7a2d7de1562b67e31f364/
A7: Original enclosure | B7: Not used | C7: Bass-reflex enclosure was part of published product performance | D7: DISCARDED / NOT USED | E7: Published complete-system frequency response and sensitivity are not transferable | F7: https://pioneer-car.eu/ts-wx1220ah/ts-wx1220ah
A8: Class-D amplifier | B8: Original Pioneer amplifier removed from enclosure; remote-mounted behind trunk wheel-arch side trim near OEM Premium amp area | C8: 600 W RMS / 1200 W max | D8: RETAINED / REMOTE-MOUNTED | E8: Feed from DSP low-level/RCA output | F8: https://pioneer-car.eu/asset/installation_manuals/UPLOAD_ID_28783/bb886d2a0df764bbfca7a2d7de1562b67e31f364/
A9: Amplifier supply | B9: Tesla high-current LV source → dedicated fuse → field-proven SSR/inrush switching path → separate voltage compatibility/regulation gate → Pioneer amp | C9: 14.4 V nominal; 10.8–15.1 V allowable | D9: TWO SEPARATE GATES | E9: Previous Tesla: SSR-based switching solved VCFRONT / “cannot maintain DC power” behavior. Separately verify whether the Pioneer amp may be exposed above its 15.1 V limit. | F9: https://pioneer-car.eu/asset/installation_manuals/UPLOAD_ID_28783/bb886d2a0df764bbfca7a2d7de1562b67e31f364/
A10: Maximum current | B10: Dedicated subwoofer power branch | C10: 50 A max current | D10: VERIFIED DONOR SPEC | E10: Power conversion/fuse/cable solution must be engineered for current and thermal load | F10: https://pioneer-car.eu/asset/installation_manuals/UPLOAD_ID_28783/bb886d2a0df764bbfca7a2d7de1562b67e31f364/
A11: Fuse reference | B11: Dedicated Pioneer branch | C11: Pioneer installation example specifies 80 A fuse | D11: VERIFIED DONOR SPEC | E11: Follow final converter/amplifier manufacturer rules; do not share undersized cabin-DSP branch | F11: https://pioneer-car.eu/asset/installation_manuals/UPLOAD_ID_28783/bb886d2a0df764bbfca7a2d7de1562b67e31f364/
A12: Ground | B12: Short chassis ground near remote amplifier | C12: Negative ground | D12: VERIFIED DONOR SPEC | E12: Use appropriate structural ground and matching cable gauge | F12: https://pioneer-car.eu/asset/installation_manuals/UPLOAD_ID_28783/bb886d2a0df764bbfca7a2d7de1562b67e31f364/
A13: RCA input | B13: DSP subwoofer line output → RCA → Pioneer amp | C13: 100 mV + 100 mV / 22 kΩ at max gain | D13: PREFERRED SIGNAL ROUTE | E13: Avoid speaker-level integration when a dedicated DSP pre-out is available | F13: https://pioneer-car.eu/asset/installation_manuals/UPLOAD_ID_28783/bb886d2a0df764bbfca7a2d7de1562b67e31f364/
A14: Speaker-level input | B14: Available but not preferred in proposed architecture | C14: 2 V + 2 V / 5 kΩ | D14: REFERENCE ONLY | E14: Keep as fallback/reference | F14: https://pioneer-car.eu/asset/installation_manuals/UPLOAD_ID_28783/bb886d2a0df764bbfca7a2d7de1562b67e31f364/
A15: Tesla low-voltage system | B15: Vehicle source side | C15: 15.5 V published | D15: VERIFIED VEHICLE SPEC | E15: Potentially above Pioneer 15.1 V max; requires measurement/compatibility decision | F15: https://www.tesla.com/ownersmanual/model3/nl_nl/GUID-E414862C-CFA1-4A0B-9548-BE21C32CAA58.html
A16: Acoustic behavior | B16: Custom lower-trunk cavity / baffle | C16: Original published 20 Hz–2.9 kHz and sensitivity belong to original complete enclosure/system | D16: RE-TUNE REQUIRED | E16: Tune DSP only after installed cavity volume, sealing, rigidity and cabin response are measured | F16: https://pioneer-car.eu/ts-wx1220ah/ts-wx1220ah
A18: POWER DECISION GATE
A19: Known | B19: Tesla owner manual lists 15.5 V LV; Pioneer permits 10.8–15.1 V and 50 A max current.
A20: Unknown | B20: Actual SOP9 voltage at the intended amplifier feed point across operating/charging states.
A21: Required | B21: Measure/verify source range before connecting Pioneer amp. If >15.1 V is possible at amp input, specify a regulated high-current step-down stage with adequate continuous/transient/thermal margin.
A22: Do not assume | B22: A converter model, fuse topology downstream of a converter, wire gauge, efficiency or thermal solution until the final power architecture is engineered.
A24: FIELD-PROVEN INRUSH / SWITCHING NOTE
A25: Previous Tesla behavior | B25: Direct amplifier feed triggered VCFRONT / “cannot maintain DC power”; SSR-based switching made the installation operate correctly. | C25: User field experience | D25: REUSE CONCEPT | E25: Keep SSR/inrush function in SOP9 design, but exact relay model, trigger logic and any precharge/current-limiting values must be recovered/verified. | F25: User-provided installation history
A26: Voltage remains separate | B26: SSR is a switching/inrush-management component in the proven architecture; it is not treated as a voltage regulator. | C26: Tesla ≈15.5 V vs Pioneer 15.1 V max | D26: OPEN | E26: If actual amplifier input can exceed 15.1 V, specify a suitable high-current regulated solution or alternative sub amplifier. | F26: Engineering decision
A28: REPLACEMENT AMPLIFIER DECISION — v1.9
A29: Driver impedance evidence | B29: Pioneer Europe lists 0.3 Ω for the TS-WX1220AH complete system; Pioneer Middle East lists 0.6 Ω × 2. | C29: 0.3 Ω total / 0.6 Ω ×2 regional official data | D29: VERIFY LOOSE DRIVERS | E29: Consistent with two 0.6 Ω SVC drivers originally paralleled. Do not assume until measured/identified. | F29: https://pioneer-mea.com/en/products/ts-wx1220ah/
A30: MATCH UP 1FX replacement | B30: Remove original Pioneer amp; V EIGHTEEN line out → UP 1FX RCA → Pioneer drivers | C30: 10.5–18 V; 350 W@4 Ω / 600 W@2 Ω / 900 W@1 Ω; 1 Ω stable | D30: PREFERRED CANDIDATE / CONDITIONAL | E30: If each driver is ~0.6 Ω nominal, wire the two in series (~1.2 Ω nominal candidate). Never use original ~0.3 Ω parallel load. | F30: https://www.audiotec-fischer.de/en/match/amplifiers/up-1fx
A31: HELIX M ONE replacement | B31: Same signal topology as above | C31: 10.5–16 V; 240/410/600 W RMS @4/2/1 Ω | D31: FULL-HELIX OPTION / CONDITIONAL | E31: Same series-load requirement; less supply-voltage headroom than UP 1FX. | F31: https://www.audiotec-fischer.de/en/helix/amplifiers/m-one
A32: HELIX M ONE X replacement | B32: Same signal topology as above | C32: 10.5–16 V; 400/700/1030 W RMS @4/2/1 Ω | D32: HIGH-POWER HELIX OPTION / CONDITIONAL | E32: Same series-load requirement; extra output likely unnecessary unless carefully gain-limited. | F32: https://www.audiotec-fischer.de/en/helix/amplifiers/m-one-x
A33: Wake/inrush remains separate | B33: Tesla high-current source → dedicated fuse → verified controlled switching/wake strategy → replacement amp | C33: Replacement amp voltage tolerance does not prove e-fuse/inrush compatibility | D33: RE-ENGINEER | E33: Use previous SSR success as field evidence; size switching/fusing for the selected new amplifier. | F33: Engineering decision

Sheet Sub_Amp_Options
A1: SUBWOOFER AMPLIFIER OPTIONS — PIONEER TS-WX1220AH DONOR DRIVERS
A2: The two original Pioneer 30 cm drivers are retained; only the amplifier/power architecture changes. Pioneer Europe publishes 0.3 Ω for the complete system while another official Pioneer regional specification states 0.6 Ω × 2. Treat this as strong evidence for two very-low-impedance SVC drivers originally paralleled, but VERIFY the loose drivers before connecting a replacement amplifier. All proposed replacement monoblocks are 1 Ω stable, not 0.3 Ω stable.
A4: Route | B4: Amplifier / power solution | C4: New amp € | D4: Supply range | E4: Published output | F4: Minimum published load | G4: Pioneer driver wiring | H4: Compatibility status | I4: Full-15 total incl DIRECTOR + reserve | J4: Full-15 total DIRECTOR deferred | K4: Benefits | L4: Risks / verification | M4: Source URL
A5: S1 | B5: Retain original Pioneer Class-D + field-proven SSR | C5: 0 | D5: 10.8–15.1 V | E5: 600 W RMS original amp | F5: Original matched load | G5: Keep original driver wiring unless dismantled wiring proves otherwise | H5: BLOCKED pending voltage solution | I5: ='Supplier_Stage_Plan'!C8 | J5: ='Supplier_Stage_Plan'!C9 | K5: No amplifier purchase; proven previous-Tesla SSR/inrush concept | L5: Tesla ~15.5 V is above Pioneer 15.1 V max. SSR addresses switching/inrush behavior, not voltage. DC-DC or measured compliant feed still required. | M5: https://pioneer-car.eu/asset/installation_manuals/UPLOAD_ID_28783/bb886d2a0df764bbfca7a2d7de1562b67e31f364/
A6: S2 | B6: Retain Pioneer + SSR + regulated high-current DC-DC | C6: TBD | D6: Pioneer still 10.8–15.1 V after regulator | E6: 600 W RMS original amp | F6: Original matched load | G6: Keep original driver wiring | H6: TECHNICALLY PLAUSIBLE / converter TBD | I6: TBD | J6: TBD | K6: Keeps known amp/driver electrical match and prior acoustic behavior | L6: Suitable converter, current headroom, efficiency, thermal management and inrush behavior still need design; likely not the simplest route. | M6: https://pioneer-car.eu/asset/installation_manuals/UPLOAD_ID_28783/bb886d2a0df764bbfca7a2d7de1562b67e31f364/
A7: S3 | B7: MATCH UP 1FX | C7: 299 | D7: 10.5–18 V | E7: 350 W @4 Ω; 600 W @2 Ω; 900 W @1 Ω | F7: 1 Ω | G7: VERIFY 0.6 Ω ×2 drivers; wire SERIES → ~1.2 Ω nominal candidate load | H7: PREFERRED REPLACEMENT CANDIDATE / CONDITIONAL | I7: ='Supplier_Stage_Plan'!C8+C7 | J7: ='Supplier_Stage_Plan'!C9+C7 | K7: Best voltage headroom of compared replacements; compact; RCA input; 1 Ω stable; DirectDSP feature; price €299 | L7: NOT compatible with original ~0.3 Ω parallel load. Series rewiring and actual driver verification required. Preserve/verify Tesla high-current wake/inrush strategy. | M7: https://www.audiotec-fischer.de/en/match/amplifiers/up-1fx
A8: S4 | B8: HELIX M ONE | C8: 299 | D8: 10.5–16 V | E8: 240 W @4 Ω; 410 W @2 Ω; 600 W @1 Ω | F8: 1 Ω | G8: VERIFY 0.6 Ω ×2 drivers; wire SERIES → ~1.2 Ω nominal candidate load | H8: FULL-HELIX BRAND OPTION / CONDITIONAL | I8: ='Supplier_Stage_Plan'!C8+C8 | J8: ='Supplier_Stage_Plan'!C9+C8 | K8: HELIX-branded; 600 W @1 Ω mirrors original amplifier RMS figure; €299 current DE reference | L8: Only 16 V upper supply limit gives less margin than UP 1FX; not compatible with original 0.3 Ω parallel load; series wiring verification required. | M8: https://www.audiotec-fischer.de/en/helix/amplifiers/m-one
A9: S5 | B9: HELIX M ONE X | C9: 379 | D9: 10.5–16 V | E9: 400 W @4 Ω; 700 W @2 Ω; 1030 W @1 Ω | F9: 1 Ω | G9: VERIFY 0.6 Ω ×2 drivers; wire SERIES → ~1.2 Ω nominal candidate load | H9: HIGH-POWER FULL-HELIX OPTION / CONDITIONAL | I9: ='Supplier_Stage_Plan'!C8+C9 | J9: ='Supplier_Stage_Plan'!C9+C9 | K9: Full HELIX branding; substantial output reserve; 1 Ω stable | L9: More expensive and potentially excessive for donor drivers; gain/output must be limited. 16 V ceiling; series-driver verification required. | M9: https://www.audiotec-fischer.de/en/helix/amplifiers/m-one-x
A11: CURRENT DECISION
A12: Preferred electrical replacement | B12: MATCH UP 1FX, conditional on confirming each loose Pioneer driver and using a safe series load. 18 V ceiling is a better match to Tesla LV than the 16 V HELIX M ONE/M ONE X ceiling.
A13: Do not do | B13: Do not connect any 1 Ω-stable replacement amplifier to the original ~0.3 Ω parallel load.
A14: Before purchase | B14: Measure/identify each donor driver, confirm ~0.6 Ω nominal class / wiring, inspect original internal wiring, and obtain dealer/manufacturer confirmation that the resulting series load is acceptable.
A15: Inrush / e-fuse | B15: A voltage-compatible replacement does not automatically eliminate Tesla inrush/e-fuse concerns. Reuse the prior SSR/wake strategy as evidence, but re-engineer it for the new amplifier current demand.
A17: S6 | B17: Audison AF M1D — MB proposal | C17: 599 | D17: Verify actual operating supply specification before final design | E17: Dedicated mono amplifier; exact output depends on load | F17: VERIFY official minimum load / driver wiring | G17: MEASURE both donor drivers first; choose safe series/parallel topology | H17: CURRENT MB PROPOSAL / CONDITIONAL | K17: Keeps sub duty off front/rear amplifiers | L17: Do not infer donor-driver impedance from complete TS-WX1220AH system spec; measure loose units and confirm load. | M17: https://audison.com/product/af-m1d/

Sheet Sources
A1: Bronnen en prijspeildatum
A2: Plain-text URLs opgenomen zodat de BOM later handmatig of automatisch kan worden geactualiseerd.
A4: Source | B4: URL | C4: Use / note
A5: Tesla / SOP9 wiring reference | B5: https://service.tesla.com/docs/Model3/ElectricalReference/ | C5: Official Tesla service reference
A6: MATCH PP-TES 1.7B Highland | B6: https://www.audiotec-fischer.de/en/match/adaptors-harnesses/pp-tes-1-7b-highland | C6: Official compatibility and connector detail
A7: Audison AF M12.14 bit | B7: https://audison.com/product/af-m12-14-bit/ | C7: Official 12 amp / 14 DSP spec and DRC MP CAN accessory
A8: Audison DRC MP CAN NL | B8: https://mbcaraudio.nl/bass-controls/audison-drc-mp-can.html | C8: €179; explicit AF M12.14 compatibility
A9: HELIX Highland front kit | B9: https://www.carhifi-store-buende.de/compose-ci3-k200.2tes4-tesla-model-3-highland | C9: €729; exact kit contents and adapters
A10: HELIX Ci5 M80FM-S3 | B10: https://www.ars24.com/en/helix-ci5-m80fm-s3 | C10: €199; DE/FR shipping
A11: HELIX Ci5 M50FM-S3 | B11: https://www.ars24.com/en/helix-ci5-m50fm-s3 | C11: €169; DE/FR shipping
A12: HELIX Ci3 M100FM-S3 | B12: https://shop.hfb.audio/produkte-fuers-auto/lautsprecher/831/helix-ci3-m100fm-s3-10cm-mittelton-lautsprecher | C12: €149 per pair
A13: MATCH UP10 US | B13: https://www.crutchfield.com/shopsearch/MATCH_UP_10_DSP.html | C13: $1,450 US current price
A14: China wholesale benchmark | B14: https://bhyiming.en.made-in-china.com/product/IdetXGaKEOcp/China-Manufacturer-Plug-and-Play-System-Woofer-for-Tesla-Model-3-High-Sound-Quality-8-Inch-Car-Accesssories-Car-Audio-Subwoofers.html | C14: $95 each at MOQ 200; not retail
A15: Audison Tesla pack limitation | B15: https://audison.com/de/tesla/ | C15: Official note: 2024+ Highland currently not compatible with their Tesla pack
... A129: Tesla SOP9 collector capture 2026-09-10 | B129: https://service.tesla.com/docs/Model3/ElectricalReference/prog-333/ | C129: Collector v1.1.6; 241 packaged assets SHA-256 verified; 14 HTTP 403/missing attempts recorded as required=false.

Sheet MBC_Configurator
A1: MBCaraudio-first configurator – SOP9 15-speaker upgrade
A2: Doel: zoveel mogelijk bij MBCaraudio inkopen. Prijzen gecontroleerd op 2026-09-01. De 2 bestaande subwoofers + Pioneer mono-versterker zijn uitgesloten. Focal T3Y dekt 11 van 15 fysieke cabin-speakers; 4 SOP9-posities moeten door MBCaraudio schriftelijk worden gespecificeerd/bevestigd.
A4: Budget / scenario | B4: Waarde | D4: MBC retailcomponent | E4: Prijs | F4: Status | H4: Conclusie | I4: Waarde | J4: Toelichting
A5: Budget minimum | B5: 3000 | D5: Focal T3Y core (11 fysieke speakers) | E5: 1645 | F5: Highland expliciet ondersteund door MBC/Focal | H5: Bekende MBC hardware (zonder 4 ontbrekende + kabels) | I5: =SUM(E5:E8) | J5: Dit is géén volledige 15-speakerprijs.
A6: Budget maximum | B6: 3500 | D6: Audison AF M12.14 bit | E6: 1349 | F6: 12×60 W RMS @4Ω / 14ch DSP | H6: Bekend + kabelreserve | I6: =I5+$B$7 | J6: Nog steeds zonder 4 ontbrekende cabin-speakers.
A7: Reserve bekabeling/zekering/OFC | B7: 200 | D7: Audison DRC MP CAN OLED | E7: 179 | F7: Display + master/sub/presets | H7: Planning full-15 incl. €400 allowance | I7: =I6+$B$8 | J7: Indicatie tot MBC exacte 4 resterende speakers quoteert.
A8: Planning allowance 4 ontbrekende speakers | B8: 400 | D8: MATCH PP-TES-1.7B RYZEN | E8: 129 | F8: Als Tesla-side interposer; Audison-zijde custom | H8: Planning na pakketkorting | I8: =I7*(1-$B$9) | J8: Pakketkorting wordt op gehele planningssom toegepast.
A9: Pakketkorting offerte | B9: 0 | H9: Ruimte t.o.v. budget max | I9: =B6-I8 | J9: Positief = binnen budget; negatief = overschrijding.
A10: Offerteprijs MBC (later invullen) | H10: Benodigde korting om €3.500 te halen | I10: =MAX(0,1-($B$6/I7)) | J10: Alleen planningswaarde; echte korting hangt van offerte af.
A12: Kernadvies
A13: Focal + Audison Forza is de sterkste MBC-first route die nu aantoonbaar Highland-compatibel is voor de primaire 11 speakerposities. Laat MBCaraudio vóór bestellen per VIN/SOP9 schriftelijk bevestigen welke 4 extra cabin-speakers, adapters en bedrading nodig zijn om werkelijk alle 15 posities te vervangen. Audison AP TSL 3Y SPK KIT is als vergelijkingsoptie opgenomen maar is door Audison zelf expliciet uitgesloten voor 2024+ Highland.
A15: MBC candidate update
A16: Als MBC de budgetkandidaat GLADEN GAMMA GM80 + Audison AP 2 MV technisch geschikt verklaart, daalt de vier-speaker reserve van €400 naar €288. Full-system retailplanning wordt dan circa €3.790 incl. €200 installatiemateriaal; circa 7,7% pakketvoordeel is dan voldoende om €3.500 te halen.

Sheet MBC_Focal_Set
A1: MBCaraudio – Focal T3Y Highland speakeroptie
A2: Alle vier Focal T3Y-productfamilies die MBCaraudio op de Model 3 Facelift 2023+ pagina toont. Aantallen zijn fysieke speakers/transducers die in de Highland worden gemonteerd; ICC T3Y 100 wordt bij Highland volgens MBC zonder de meegeleverde tweeter gebruikt.
A4: Positie | B4: Product | C4: Sets | D4: Fysieke speakers | E4: RMS W / speaker | F4: MAX W / speaker | G4: Impedantie Ω | H4: MBC prijs/set | I4: Subtotaal | J4: AF M12.14 @4Ω | K4: Amp/Speaker RMS | L4: Match | M4: Highland/SOP9 status | N4: Bron URL | O4: US review signal | P4: US review/source
A5: Front doors – midbass/woofer L+R | B5: Focal IW T3Y 200 | C5: 1 | D5: 2 | E5: 75 | F5: 150 | G5: 4 | H5: 459 | I5: =C5*H5 | J5: 60 | K5: =IF(E5>0,J5/E5,"") | L5: =IF(K5="","n/a",IF(K5<0.75,"Amp beperkt speakervermogen",IF(K5<=1.25,"Goede RMS-match",IF(K5<=1.75,"Meer amp-headroom – limiter/gain", "Veel amp-headroom – limiter vereist")))) | M5: Expliciet MBC Highland LR/Performance vanaf 2023 | N5: https://mbcaraudio.nl/autospecifieke-pasklare-speakersets/focal-iw-t3y-200.html | O5: 5/5 (3 reviews) | P5: Crutchfield – limited sample; $1,049.99
A6: Front stage – mids L+R + tweeters L+R | B6: Focal IS T3Y 100 | C6: 1 | D6: 4 | E6: 50 | F6: 100 | G6: 4 | H6: 369 | I6: =C6*H6 | J6: 60 | K6: =IF(E6>0,J6/E6,"") | L6: =IF(K6="","n/a",IF(K6<0.75,"Amp beperkt speakervermogen",IF(K6<=1.25,"Goede RMS-match",IF(K6<=1.75,"Meer amp-headroom – limiter/gain", "Veel amp-headroom – limiter vereist")))) | M6: Expliciet MBC Highland LR/Performance vanaf 2023 | N6: https://mbcaraudio.nl/autospecifieke-pasklare-speakersets/focal-is-t3y-100.html | O6: 5/5 (2 reviews) | P6: Crutchfield – limited sample; $719.99
A7: Dashboard center | B7: Focal ICC T3Y 100 | C7: 1 | D7: 1 | E7: 50 | F7: 100 | G7: 4 | H7: 179 | I7: =C7*H7 | J7: 60 | K7: =IF(E7>0,J7/E7,"") | L7: =IF(K7="","n/a",IF(K7<0.75,"Amp beperkt speakervermogen",IF(K7<=1.25,"Goede RMS-match",IF(K7<=1.75,"Meer amp-headroom – limiter/gain", "Veel amp-headroom – limiter vereist")))) | M7: Highland: volgens MBC alleen center gebruiken, zonder meegeleverde tweeter | N7: https://mbcaraudio.nl/autospecifieke-pasklare-speakersets/focal-icc-t3y-100.html | O7: 3/5 (1 review) | P7: Crutchfield – single review; $369.99
A8: Rear doors L+R | B8: Focal IC T3Y 100 | C8: 1 | D8: 2 | E8: 40 | F8: 80 | G8: 4 | H8: 319 | I8: =C8*H8 | J8: 60 | K8: =IF(E8>0,J8/E8,"") | L8: =IF(K8="","n/a",IF(K8<0.75,"Amp beperkt speakervermogen",IF(K8<=1.25,"Goede RMS-match",IF(K8<=1.75,"Meer amp-headroom – limiter/gain", "Veel amp-headroom – limiter vereist")))) | M8: Expliciet MBC Highland LR/Performance rear doors | N8: https://mbcaraudio.nl/autospecifieke-pasklare-speakersets/focal-ic-t3y-100.html | O8: No reviews | P8: Crutchfield $629.99/pair
A9: Parcel shelf L+R | B9: Focal IC T3Y 100 | C9: 1 | D9: 2 | E9: 40 | F9: 80 | G9: 4 | H9: 319 | I9: =C9*H9 | J9: 60 | K9: =IF(E9>0,J9/E9,"") | L9: =IF(K9="","n/a",IF(K9<0.75,"Amp beperkt speakervermogen",IF(K9<=1.25,"Goede RMS-match",IF(K9<=1.75,"Meer amp-headroom – limiter/gain", "Veel amp-headroom – limiter vereist")))) | M9: Expliciet MBC Highland LR/Performance parcel shelf; extra bekabeling mogelijk | N9: https://mbcaraudio.nl/autospecifieke-pasklare-speakersets/focal-ic-t3y-100.html | O9: No reviews | P9: Crutchfield $629.99/pair
A11: SOP9 completion gap | D11: =15-SUM(D5:D9) | E11: TBD door MBCaraudio – waarschijnlijk resterende Premium/immersive-posities; exacte locatie, maat, impedantie en aansluiting eerst bevestigen. | M11: 4 fysieke cabin-speakers zijn nog niet door Focal T3Y op de MBC Highland-pagina afgedekt. Laat MBC per VIN/SOP9 passende producten + adapters schriftelijk bevestigen. Geen universele Focal-driver zonder maat/connectorcontrole bestellen.
A13: Focal T3Y retailtotaal MBC | D13: =SUM(D5:D9) | I13: =SUM(I5:I9)
A15: v2.1 NOTE
A16: Historical/comparison content retained. Current received MB proposal is authoritative in MB_Quote_2026-09-10 / MBC_Shopping_List and MB_Channel_Map_v2.1.

Sheet MBC_Audison_Set
A1: MBCaraudio – Audison Tesla speaker upgrade (vergelijking)
A2: MBCaraudio verkoopt de nieuwe Audison AP TSL 3Y speakerkit, maar Audison vermeldt officieel dat de huidige Tesla Sound Packs NIET compatibel zijn met 2024+ Model 3 Highland. Daarom: alleen vergelijken; niet bestellen voor SOP9 zonder schriftelijke bevestiging van een nieuwe/revised Highland-versie.
A4: Onderdeel/positie | B4: Audison component | C4: Aantal | D4: RMS W / speaker | E4: MAX W / speaker | F4: Impedantie Ω | G4: MBC kitprijs | H4: AF M12.14 kanaal RMS | I4: Amp/Speaker RMS | J4: Match | K4: SOP9 status | L4: Opmerking | M4: MBC/official source | N4: Prijsstatus
A5: Front tweeters | B5: AP TSL T1 | C5: 2 | E5: 100 | F5: 4 | G5: 749 | H5: 60 | I5: =IF(D5>0,H5/D5,"") | J5: =IF(I5="","n/a",IF(I5<0.75,"Amp beperkt speakervermogen",IF(I5<=1.25,"Goede RMS-match",IF(I5<=1.75,"Meer amp-headroom – limiter/gain","Veel amp-headroom – limiter vereist")))) | K5: NIET Highland-compatibel volgens Audison | L5: RMS niet apart gepubliceerd in geraadpleegde kitdata | M5: https://audison.com/tesla/ | N5: MBC kit €749
A6: Front mids | B6: AP TSL M4M | C6: 2 | D6: 50 | E6: 100 | F6: 4 | G6: 0 | H6: 60 | I6: =IF(D6>0,H6/D6,"") | J6: =IF(I6="","n/a",IF(I6<0.75,"Amp beperkt speakervermogen",IF(I6<=1.25,"Goede RMS-match",IF(I6<=1.75,"Meer amp-headroom – limiter/gain","Veel amp-headroom – limiter vereist")))) | K6: NIET Highland-compatibel volgens Audison | L6: Official speaker spec | M6: https://audison.com/tesla/ | N6: MBC kit €749
A7: Front 200mm woofers | B7: AP TSL 8 | C7: 2 | D7: 100 | E7: 300 | F7: 4 | G7: 0 | H7: 60 | I7: =IF(D7>0,H7/D7,"") | J7: =IF(I7="","n/a",IF(I7<0.75,"Amp beperkt speakervermogen",IF(I7<=1.25,"Goede RMS-match",IF(I7<=1.75,"Meer amp-headroom – limiter/gain","Veel amp-headroom – limiter vereist")))) | K7: NIET Highland-compatibel volgens Audison | L7: Official speaker spec | M7: https://audison.com/tesla/ | N7: MBC kit €749
A8: Dashboard center coax | B8: AP TSL X4M | C8: 1 | D8: 40 | E8: 80 | F8: 4 | G8: 0 | H8: 60 | I8: =IF(D8>0,H8/D8,"") | J8: =IF(I8="","n/a",IF(I8<0.75,"Amp beperkt speakervermogen",IF(I8<=1.25,"Goede RMS-match",IF(I8<=1.75,"Meer amp-headroom – limiter/gain","Veel amp-headroom – limiter vereist")))) | K8: NIET Highland-compatibel volgens Audison | L8: Official speaker spec | M8: https://audison.com/tesla/ | N8: MBC kit €749
A10: Kitinhoud | B10: 7 fysieke speakerunits (2 tweeters + 2 mids + 2 woofers + 1 center). Geen 15-speakercomplete set. | G10: 749 | K10: NIET KOPEN voor SOP9 zonder schriftelijke Highland-confirmatie
A12: v2.1 NOTE
A13: Historical/comparison content retained. Current received MB proposal is authoritative in MB_Quote_2026-09-10 / MBC_Shopping_List and MB_Channel_Map_v2.1.

Sheet MBC_Other_Options
A1: MBCaraudio – overige Tesla speakeropties op Facelift 2023+ pagina
A2: Deze sets staan door MBCaraudio in de Model 3 Facelift 2023+ categorie, maar fabrikantpagina’s zijn vaak generiek “Model 3/Model Y” en geven geen expliciete SOP9/2026-confirmatie. Daarom alleen shortlist; eerst VIN/SOP9-fitment laten bevestigen.
A4: Merk/Set | B4: MBC prijs | C4: Inhoud (fysieke speakers, sub niet meegeteld) | D4: RMS relevante driver(s) | E4: MAX | F4: Impedantie | G4: 15-speaker dekking | H4: SOP9 zekerheid | I4: Pluspunt | J4: Minpunt | K4: MBC URL | L4: Fabrikant URL | M4: Advies | N4: Opmerking
A5: DLS Cruise CRPP-TS1.4 + CRPP-TSW.8 | B5: 599.9 | C5: 2× 200mm woofer + 2× 100mm mid + 2× tweeter = 6 | D5: Woofer 120W; component 60W | E5: Woofer 240W; component 120W | F5: 4Ω | G5: 6/15 | H5: MBC category + DLS says Model 3 2022+; SOP9 verify | I5: Sterke woofer RMS; nette prijs | J5: Veel posities ontbreken; geen full set | K5: https://mbcaraudio.nl/autospecifieke-producten/tesla-autospecifieke-producten-en-accessoires/automodel-typenummer-en-bouwjaar-selectie-tesla/tesla-model-3-facelift-bouwjaar-2023- | L5: https://dls.se/product/cruise-crpp-tsw-8/ | M5: Interessante mix-optie | N5: AF M12.14 levert 60W @4Ω: perfect voor componentset, maar benut 120W woofer niet volledig.
A6: MUSWAY TES3YSET1 | B6: 799 | C6: 2× woofer + 2× tweeter + 3× mid = 7 (plus sub, niet nodig) | D6: MAE6.2W 100W; MAE6.2T 100W; ML3M 60W | E6: 200W / 200W / 120W | F6: 3Ω woof/tweet; 4Ω mids | G6: 7/15 | H6: MBC Facelift category; fabrikant generiek Model 3/Y | I6: Complete adapters in kit; goede value | J6: Bevat sub die jij niet nodig hebt; geen full 15; SOP9 niet expliciet | K6: https://mbcaraudio.nl/autospecifieke-producten/tesla-autospecifieke-producten-en-accessoires/automodel-typenummer-en-bouwjaar-selectie-tesla/tesla-model-3-facelift-bouwjaar-2023- | L6: https://musway.de/english/tes3yset1.html | M6: Alleen na fitmentbevestiging | N6: Interessant als MBC korting geeft en sub uit pakket kan laten vervallen/crediteren.
A7: ESX TES3YSET2 | B7: 1199 | C7: 2× woofer + 2× tweeter + 3× mid = 7 (plus sub, niet nodig) | D7: QXE8.2W 125W; VXP3M 60W; tweeter set spec verifiëren | E7: 250W / 120W | F7: QXE woofer 3Ω; VXP mid 4Ω | G7: 7/15 | H7: MBC Facelift category; fabrikant generiek Model 3/Y | I7: Hoog vermogen / premium componenten | J7: Duur; sub overbodig; geen full 15; SOP9 niet expliciet | K7: https://mbcaraudio.nl/autospecifieke-producten/tesla-autospecifieke-producten-en-accessoires/automodel-typenummer-en-bouwjaar-selectie-tesla/tesla-model-3-facelift-bouwjaar-2023- | L7: https://www.esxaudio.de/english/tes3yset2.html | M7: Alleen bij forse bundelkorting | N7: AF M12.14 is voor de woofer relatief licht, maar DSP/gain blijft veilig; 3Ω output ligt tussen 4Ω/2Ω specificaties.

Sheet Power_Match
A1: RMS / MAX vermogensmatch – speakers versus DSP-versterkers
A2: Nominal RMS comparison. Retained Pioneer TS-WX1220AH donor hardware remains separate. v1.8 records the previous Tesla SSR switching solution as field-proven for the VCFRONT/inrush symptom while keeping absolute supply-voltage compatibility as a separate open engineering gate.
A4: Speaker / set | B4: Speaker Ω | C4: Speaker RMS W | D4: Speaker MAX W | E4: AF M12.14 RMS/ch | F4: AF ratio | G4: AF oordeel | H4: HELIX V Twelve RMS/ch | I4: HELIX ratio | J4: HELIX oordeel | K4: MATCH UP10 RMS/ch | L4: MATCH ratio | M4: Opmerking
A5: Focal IW T3Y 200 | B5: 4 | C5: 75 | D5: 150 | E5: 60 | F5: =IF(C5>0,E5/C5,"") | G5: =IF(F5<0.75,"Amp beperkt speakervermogen",IF(F5<=1.25,"Goede RMS-match",IF(F5<=1.75,"Meer headroom – limiter/gain","Veel headroom – limiter vereist"))) | H5: 75 | I5: =IF(C5>0,H5/C5,"") | J5: =IF(I5<0.75,"Amp beperkt speakervermogen",IF(I5<=1.25,"Goede RMS-match",IF(I5<=1.75,"Meer headroom – limiter/gain","Veel headroom – limiter vereist"))) | K5: 65 | L5: =IF(C5>0,K5/C5,"") | M5: Front 200mm woofer
A6: Focal IS T3Y 100 (mid+tweeter via crossover) | B6: 4 | C6: 50 | D6: 100 | E6: 60 | F6: =IF(C6>0,E6/C6,"") | G6: =IF(F6<0.75,"Amp beperkt speakervermogen",IF(F6<=1.25,"Goede RMS-match",IF(F6<=1.75,"Meer headroom – limiter/gain","Veel headroom – limiter vereist"))) | H6: 75 | I6: =IF(C6>0,H6/C6,"") | J6: =IF(I6<0.75,"Amp beperkt speakervermogen",IF(I6<=1.25,"Goede RMS-match",IF(I6<=1.75,"Meer headroom – limiter/gain","Veel headroom – limiter vereist"))) | K6: 65 | L6: =IF(C6>0,K6/C6,"") | M6: Component set rating
A7: Focal ICC T3Y 100 | B7: 4 | C7: 50 | D7: 100 | E7: 60 | F7: =IF(C7>0,E7/C7,"") | G7: =IF(F7<0.75,"Amp beperkt speakervermogen",IF(F7<=1.25,"Goede RMS-match",IF(F7<=1.75,"Meer headroom – limiter/gain","Veel headroom – limiter vereist"))) | H7: 75 | I7: =IF(C7>0,H7/C7,"") | J7: =IF(I7<0.75,"Amp beperkt speakervermogen",IF(I7<=1.25,"Goede RMS-match",IF(I7<=1.75,"Meer headroom – limiter/gain","Veel headroom – limiter vereist"))) | K7: 65 | L7: =IF(C7>0,K7/C7,"") | M7: Highland: center only
A8: Focal IC T3Y 100 | B8: 4 | C8: 40 | D8: 80 | E8: 60 | F8: =IF(C8>0,E8/C8,"") | G8: =IF(F8<0.75,"Amp beperkt speakervermogen",IF(F8<=1.25,"Goede RMS-match",IF(F8<=1.75,"Meer headroom – limiter/gain","Veel headroom – limiter vereist"))) | H8: 75 | I8: =IF(C8>0,H8/C8,"") | J8: =IF(I8<0.75,"Amp beperkt speakervermogen",IF(I8<=1.25,"Goede RMS-match",IF(I8<=1.75,"Meer headroom – limiter/gain","Veel headroom – limiter vereist"))) | K8: 65 | L8: =IF(C8>0,K8/C8,"") | M8: Rear/parcel coax
A9: DLS CRPP-TS1.4 | B9: 4 | C9: 60 | D9: 120 | E9: 60 | F9: =IF(C9>0,E9/C9,"") | G9: =IF(F9<0.75,"Amp beperkt speakervermogen",IF(F9<=1.25,"Goede RMS-match",IF(F9<=1.75,"Meer headroom – limiter/gain","Veel headroom – limiter vereist"))) | H9: 75 | I9: =IF(C9>0,H9/C9,"") | J9: =IF(I9<0.75,"Amp beperkt speakervermogen",IF(I9<=1.25,"Goede RMS-match",IF(I9<=1.75,"Meer headroom – limiter/gain","Veel headroom – limiter vereist"))) | K9: 65 | L9: =IF(C9>0,K9/C9,"") | M9: Component set
A10: DLS CRPP-TSW.8 | B10: 4 | C10: 120 | D10: 240 | E10: 60 | F10: =IF(C10>0,E10/C10,"") | G10: =IF(F10<0.75,"Amp beperkt speakervermogen",IF(F10<=1.25,"Goede RMS-match",IF(F10<=1.75,"Meer headroom – limiter/gain","Veel headroom – limiter vereist"))) | H10: 75 | I10: =IF(C10>0,H10/C10,"") | J10: =IF(I10<0.75,"Amp beperkt speakervermogen",IF(I10<=1.25,"Goede RMS-match",IF(I10<=1.75,"Meer headroom – limiter/gain","Veel headroom – limiter vereist"))) | K10: 65 | L10: =IF(C10>0,K10/C10,"") | M10: Front woofer
A11: Audison AP TSL M4M | B11: 4 | C11: 50 | D11: 100 | E11: 60 | F11: =IF(C11>0,E11/C11,"") | G11: =IF(F11<0.75,"Amp beperkt speakervermogen",IF(F11<=1.25,"Goede RMS-match",IF(F11<=1.75,"Meer headroom – limiter/gain","Veel headroom – limiter vereist"))) | H11: 75 | I11: =IF(C11>0,H11/C11,"") | J11: =IF(I11<0.75,"Amp beperkt speakervermogen",IF(I11<=1.25,"Goede RMS-match",IF(I11<=1.75,"Meer headroom – limiter/gain","Veel headroom – limiter vereist"))) | K11: 65 | L11: =IF(C11>0,K11/C11,"") | M11: Audison Tesla kit; not Highland currently
A12: Audison AP TSL X4M | B12: 4 | C12: 40 | D12: 80 | E12: 60 | F12: =IF(C12>0,E12/C12,"") | G12: =IF(F12<0.75,"Amp beperkt speakervermogen",IF(F12<=1.25,"Goede RMS-match",IF(F12<=1.75,"Meer headroom – limiter/gain","Veel headroom – limiter vereist"))) | H12: 75 | I12: =IF(C12>0,H12/C12,"") | J12: =IF(I12<0.75,"Amp beperkt speakervermogen",IF(I12<=1.25,"Goede RMS-match",IF(I12<=1.75,"Meer headroom – limiter/gain","Veel headroom – limiter vereist"))) | K12: 65 | L12: =IF(C12>0,K12/C12,"") | M12: Audison Tesla kit; not Highland currently
A13: Audison AP TSL 8 | B13: 4 | C13: 100 | D13: 300 | E13: 60 | F13: =IF(C13>0,E13/C13,"") | G13: =IF(F13<0.75,"Amp beperkt speakervermogen",IF(F13<=1.25,"Goede RMS-match",IF(F13<=1.75,"Meer headroom – limiter/gain","Veel headroom – limiter vereist"))) | H13: 75 | I13: =IF(C13>0,H13/C13,"") | J13: =IF(I13<0.75,"Amp beperkt speakervermogen",IF(I13<=1.25,"Goede RMS-match",IF(I13<=1.75,"Meer headroom – limiter/gain","Veel headroom – limiter vereist"))) | K13: 65 | L13: =IF(C13>0,K13/C13,"") | M13: Audison Tesla kit; not Highland currently
A14: MUSWAY ML3M | B14: 4 | C14: 60 | D14: 120 | E14: 60 | F14: =IF(C14>0,E14/C14,"") | G14: =IF(F14<0.75,"Amp beperkt speakervermogen",IF(F14<=1.25,"Goede RMS-match",IF(F14<=1.75,"Meer headroom – limiter/gain","Veel headroom – limiter vereist"))) | H14: 75 | I14: =IF(C14>0,H14/C14,"") | J14: =IF(I14<0.75,"Amp beperkt speakervermogen",IF(I14<=1.25,"Goede RMS-match",IF(I14<=1.75,"Meer headroom – limiter/gain","Veel headroom – limiter vereist"))) | K14: 65 | L14: =IF(C14>0,K14/C14,"") | M14: TES3YSET1 mid
A15: MUSWAY MAE6.2W | B15: 3 | C15: 100 | D15: 200 | E15: 60 | F15: =IF(C15>0,E15/C15,"") | G15: =IF(F15<0.75,"Amp beperkt speakervermogen",IF(F15<=1.25,"Goede RMS-match",IF(F15<=1.75,"Meer headroom – limiter/gain","Veel headroom – limiter vereist"))) | H15: 75 | I15: =IF(C15>0,H15/C15,"") | J15: =IF(I15<0.75,"Amp beperkt speakervermogen",IF(I15<=1.25,"Goede RMS-match",IF(I15<=1.75,"Meer headroom – limiter/gain","Veel headroom – limiter vereist"))) | K15: 65 | L15: =IF(C15>0,K15/C15,"") | M15: TES3YSET1 woofer; exact 3Ω AF power not specified
A16: ESX VXP3M | B16: 4 | C16: 60 | D16: 120 | E16: 60 | F16: =IF(C16>0,E16/C16,"") | G16: =IF(F16<0.75,"Amp beperkt speakervermogen",IF(F16<=1.25,"Goede RMS-match",IF(F16<=1.75,"Meer headroom – limiter/gain","Veel headroom – limiter vereist"))) | H16: 75 | I16: =IF(C16>0,H16/C16,"") | J16: =IF(I16<0.75,"Amp beperkt speakervermogen",IF(I16<=1.25,"Goede RMS-match",IF(I16<=1.75,"Meer headroom – limiter/gain","Veel headroom – limiter vereist"))) | K16: 65 | L16: =IF(C16>0,K16/C16,"") | M16: TES3YSET2 mid
A17: ESX QXE8.2W | B17: 3 | C17: 125 | D17: 250 | E17: 60 | F17: =IF(C17>0,E17/C17,"") | G17: =IF(F17<0.75,"Amp beperkt speakervermogen",IF(F17<=1.25,"Goede RMS-match",IF(F17<=1.75,"Meer headroom – limiter/gain","Veel headroom – limiter vereist"))) | H17: 75 | I17: =IF(C17>0,H17/C17,"") | J17: =IF(I17<0.75,"Amp beperkt speakervermogen",IF(I17<=1.25,"Goede RMS-match",IF(I17<=1.75,"Meer headroom – limiter/gain","Veel headroom – limiter vereist"))) | K17: 65 | L17: =IF(C17>0,K17/C17,"") | M17: TES3YSET2 woofer; exact 3Ω AF power not specified
A19: Amplifier referentie
A20: Audison AF M12.14 bit | B20: 12×60W @4Ω = 720W; 12×90W @2Ω = 1080W; 6×180W bridged @4Ω = 1080W; official Total Power RMS 1080W | C20: €1.349 MBC | D20: 12 amp / 14 DSP; aanbevolen MBC-first
A21: HELIX V TWELVE DSP MK2 | B21: 12×75W @4Ω = 900W; 12×120W @2Ω = 1440W | C21: €1.499 MBC | D21: Meer speakerpower, maar controller/harness opnieuw begroten
A22: MATCH UP 10DSP 24V (MBC page) | B22: 8×65W + 2×90W @4Ω = 700W (MBC page is 24V model; verify vehicle-voltage suitability) | C22: €1.049 MBC | D22: MBC-link is 24V uitvoering; niet automatisch geschikt voor jouw voertuigvoeding – verify exact 12/16V model
A24: Retained Pioneer TS-WX1220AH donor subsystem
A25: 2 × Pioneer 30 cm donor woofers | B25: Original donor system rating | C25: 1000 W RMS | D25: 3000 W max | M25: Custom lower-trunk baffle; original Pioneer enclosure not used
A26: Original Pioneer Class-D amp | B26: Supply | C26: 10.8–15.1 V | D26: 600 W RMS / 1200 W max | M26: 50 A max current; negative ground; Pioneer example dedicated 80 A fuse
A27: Tesla LV compatibility | B27: Tesla published LV | C27: 15.5 V | D27: > Pioneer 15.1 V max | M27: Direct connection not approved; verify actual SOP9 voltage / regulate if required
A29: PIONEER / TESLA POWER NOTE v1.8
A30: Prior vehicle result | B30: Without SSR: VCFRONT / cannot maintain DC power errors. With SSR-based switching: stable operation.
A31: SOP9 rule | B31: Reuse the proven switching concept, but independently resolve 15.5 V vehicle LV vs Pioneer 15.1 V maximum and final high-current feed/fusing.

Sheet MBC_Shopping_List
A1: MB Car Audio — ontvangen hardwareprijsopgaaf 2026-09-10
A2: Werkelijke ontvangen prijsopgaaf. €4.010,90 is uitsluitend hardware: geen bekabeling, demping, montage-/verbruiksmateriaal en geen arbeid. Montage en afregeling worden door eigenaar uitgevoerd.
A4: Select | B4: Categorie | C4: Product | D4: Qty | E4: MB prijs / unit | F4: MB totaal | G4: Functie / zone | H4: Bekend uit gesprek | I4: Online laagste | J4: Potentiële besparing | K4: Prijsstatus | L4: Bron / referentie | M4: SOP9 status | N4: Notitie
A5: JA | B5: Speaker | C5: Focal IW T3Y 200 | D5: 1 | E5: 459 | F5: =D5*E5 | G5: Front woofer-set | H5: Offerte | I5: 314.1 | J5: =F5-I5 | K5: CURRENT INDEXED | L5: https://mbcaraudio.nl/autospecifieke-pasklare-speakersets/focal-iw-t3y-200.html | M5: Highland product family | N5: 2 × 200 mm woofers
A6: JA | B6: Speaker | C6: Focal ICC T3Y 100 | D6: 1 | E6: 179 | F6: =D6*E6 | G6: Dashboard center | H6: Offerte | I6: 129 | J6: =F6-I6 | K6: CURRENT/FR | L6: https://mbcaraudio.nl/autospecifieke-pasklare-speakersets/focal-icc-t3y-100.html | M6: Highland center | N6: Niet verwarren met de te verwijderen upper/headliner immersive posities
A7: JA | B7: Speaker | C7: Focal IC T3Y 100 | D7: 1 | E7: 319 | F7: =D7*E7 | G7: Rear / coaxial set | H7: Offerte | I7: 219 | J7: =F7-I7 | K7: CURRENT INDEXED | L7: https://mbcaraudio.nl/autospecifieke-pasklare-speakersets/focal-ic-t3y-100.html | M7: Highland product family | N7: 2-way coaxial kit
A8: JA | B8: Speaker | C8: Focal IS T3Y 100 | D8: 1 | E8: 369 | F8: =D8*E8 | G8: Front mids + tweeters | H8: Offerte | I8: 289 | J8: =F8-I8 | K8: CURRENT INDEXED | L8: https://mbcaraudio.nl/autospecifieke-pasklare-speakersets/focal-is-t3y-100.html | M8: Highland product family | N8: 2-way component kit
A9: JA | B9: Tesla harness | C9: MATCH PP-TES 1.7B Highland | D9: 1 | E9: 139.95 | F9: =D9*E9 | G9: Tesla signal interposer / harness basis | H9: Offerte | I9: 129 | J9: =F9-I9 | K9: CURRENT | L9: https://mbcaraudio.nl/autospecifieke-producten/mercedes-benz-autospecifieke-producten-en-accessoires/autospecifieke-versterker-audio-kabelbomen-mercedes-benz | M9: Officially MATCH UP10-specific | N9: Audison-side adaptation still must be engineered/confirmed
A10: JA | B10: DSP amplifier | C10: Audison AF M8.14 bit | D10: 1 | E10: 1199 | F10: =D10*E10 | G10: Alles vóór de voorstoelen / front stage DSP + amplification | H10: MB telefonisch bevestigd | I10: 999 | J10: =F10-I10 | K10: CURRENT INDEXED | L10: https://www.autosound24.nl/producten/AUD-DSPAMP-AF-M8-14BIT | M10: Installer architecture | N10: 8 amplified + 14 DSP processed channels
A11: JA | B11: Rear amplifier | C11: Audison AF M4D | D11: 1 | E11: 599 | F11: =D11*E11 | G11: Alles achter de voorstoelen: rear woofers, rear mids, optionele rear tweeters | H11: MB telefonisch bevestigd | I11: 462.48 | J11: =F11-I11 | K11: CURRENT INDEXED | L11: https://audison.com/product/af-m4d/ | M11: Installer architecture | N11: 4-channel companion amplifier
A12: JA | B12: Sub amplifier | C12: Audison AF M1D | D12: 1 | E12: 599 | F12: =D12*E12 | G12: Pioneer donor subwoofers | H12: Waarschijnlijk/bedoeld volgens gesprek; exact wiring nog verifiëren | I12: 595.9 | J12: =F12-I12 | K12: CURRENT INDEXED | L12: https://audison.com/product/af-m1d/ | M12: CONDITIONAL | N12: Donor-driver impedance/load must be measured before final wiring
A13: JA | B13: Interconnect | C13: Audison AF LINK | D13: 1 | E13: 18.95 | F13: =D13*E13 | G13: AF bit DSP OUT → AF D PRE IN | H13: Offerte | I13: 18.95 | J13: =F13-I13 | K13: CURRENT | L13: https://audison.com/collections/car-accessories/ | M13: Compatible accessory | N13: Signal link cable
A14: JA | B14: Controller | C14: Audison DRC AC | D14: 1 | E14: 129 | F14: =D14*E14 | G14: Master/sub/source/preset control | H14: Offerte | I14: 129 | J14: =F14-I14 | K14: CURRENT | L14: https://mbcaraudio.nl/bass-controls/audison-drc-ac.html | M14: Compatible with AF bit | N14: Compact DRCC remote
A16: MB hardware total | B16: =SUM(F5:F14) | C16: Received quote total, should equal €4.010,90
A17: Split-buy low-price basket | B17: =SUM(I5:I14) | C17: Lowest currently indexed/verified unit price used; shipping/transaction costs excluded
A18: Potential gross saving | B18: =B16-B17 | C18: Before shipping and stock/checkout verification
A19: Potential gross saving % | B19: =B18/B16 | C19: Before shipping and stock/checkout verification
A21: Critical scope note | B21: No cabling, damping, fusing/distribution, mounting materials or labour included. User performs installation.

Sheet Price_Benchmark_MBC
A1: MBCaraudio vs Duitsland / Frankrijk – onderhandelingsbenchmark
A2: MBCaraudio blijft de voorkeursleverancier voor één aanspreekpunt, garantie en fitmentadvies. Buitenlandse prijzen zijn benchmarkprijzen; verzendkosten, actueel checkout-totaal en SOP9-fitment altijd verifiëren.
A4: Product | B4: MBC NL | C4: DE benchmark | D4: FR benchmark / MSRP | E4: MBC vs DE | F4: MBC vs FR | G4: Aantal | H4: MBC totaal | I4: DE totaal | J4: FR totaal | K4: Bronnen | L4: Opmerking | M4: US current USD | N4: US EUR ex VAT | O4: US +21% VAT | P4: US review/source | Q4: China/direct import status | R4: China source
A5: Focal IW T3Y 200 | B5: 459 | C5: 359 | D5: 369 | E5: =IF(C5="","",B5-C5) | F5: =IF(D5="","",B5-D5) | G5: 1 | H5: =B5*G5 | I5: =IF(C5="","",C5*G5) | J5: =IF(D5="","",D5*G5) | K5: https://mbcaraudio.nl/autospecifieke-pasklare-speakersets/focal-iw-t3y-200.html | https://www.idealo.de/preisvergleich/OffersOfProduct/204855028_-iw-t3y-200-focal.html | https://www.focal.com/fr/produits/iw-t3y-200 | L5: DE Idealo €359; FR official suggested retail €369 | M5: 1049.99 | N5: =M5*$B$17 | O5: =N5*(1+$B$18) | P5: 5/5 (3) Crutchfield | Q5: Geen betrouwbare genuine Focal T3Y China-retailprijs gevonden; generieke Tesla kits zijn niet like-for-like en hebben counterfeit/fitmentrisico. | R5: https://bhyiming.en.made-in-china.com/product/IdetXGaKEOcp/China-Manufacturer-Plug-and-Play-System-Woofer-for-Tesla-Model-3-High-Sound-Quality-8-Inch-Car-Accesssories-Car-Audio-Subwoofers.html
A6: Focal IS T3Y 100 | B6: 369 | C6: 289 | D6: 299 | E6: =IF(C6="","",B6-C6) | F6: =IF(D6="","",B6-D6) | G6: 1 | H6: =B6*G6 | I6: =IF(C6="","",C6*G6) | J6: =IF(D6="","",D6*G6) | K6: https://mbcaraudio.nl/autospecifieke-pasklare-speakersets/focal-is-t3y-100.html | https://www.idealo.de/preisvergleich/Liste/123511081/focal-t3y.html | https://www.focal.com/fr/produits/is-t3y-100 | L6: DE Idealo list vanaf €289; FR official suggested retail €299 | M6: 719.99 | N6: =M6*$B$17 | O6: =N6*(1+$B$18) | P6: 5/5 (2) Crutchfield | Q6: Geen betrouwbare genuine Focal T3Y China-retailprijs gevonden; generieke Tesla kits zijn niet like-for-like en hebben counterfeit/fitmentrisico. | R6: https://bhyiming.en.made-in-china.com/product/IdetXGaKEOcp/China-Manufacturer-Plug-and-Play-System-Woofer-for-Tesla-Model-3-High-Sound-Quality-8-Inch-Car-Accesssories-Car-Audio-Subwoofers.html
A7: Focal ICC T3Y 100 | B7: 179 | C7: 149 | D7: 129 | E7: =IF(C7="","",B7-C7) | F7: =IF(D7="","",B7-D7) | G7: 1 | H7: =B7*G7 | I7: =IF(C7="","",C7*G7) | J7: =IF(D7="","",D7*G7) | K7: https://mbcaraudio.nl/autospecifieke-pasklare-speakersets/focal-icc-t3y-100.html | https://www.idealo.de/preisvergleich/OffersOfProduct/204855027_-inside-icc-t3y-100-focal.html | https://www.focal.com/fr/produits/icc-t3y-100 | L7: FR MSRP is lower; dealer availability/shipping verify | M7: 369.99 | N7: =M7*$B$17 | O7: =N7*(1+$B$18) | P7: 3/5 (1) Crutchfield | Q7: Geen betrouwbare genuine Focal T3Y China-retailprijs gevonden; generieke Tesla kits zijn niet like-for-like en hebben counterfeit/fitmentrisico. | R7: https://bhyiming.en.made-in-china.com/product/IdetXGaKEOcp/China-Manufacturer-Plug-and-Play-System-Woofer-for-Tesla-Model-3-High-Sound-Quality-8-Inch-Car-Accesssories-Car-Audio-Subwoofers.html
A8: Focal IC T3Y 100 | B8: 319 | C8: 229 | D8: 229 | E8: =IF(C8="","",B8-C8) | F8: =IF(D8="","",B8-D8) | G8: 2 | H8: =B8*G8 | I8: =IF(C8="","",C8*G8) | J8: =IF(D8="","",D8*G8) | K8: https://mbcaraudio.nl/autospecifieke-pasklare-speakersets/focal-ic-t3y-100.html | https://www.idealo.de/preisvergleich/OffersOfProduct/204105665_-ic-t3y-100-focal.html | https://www.focal.com/fr/produits/ic-t3y-100 | L8: Qty 2 sets | M8: 629.99 | N8: =M8*$B$17 | O8: =N8*(1+$B$18) | P8: No reviews; price per pair | Q8: Geen betrouwbare genuine Focal T3Y China-retailprijs gevonden; generieke Tesla kits zijn niet like-for-like en hebben counterfeit/fitmentrisico. | R8: https://bhyiming.en.made-in-china.com/product/IdetXGaKEOcp/China-Manufacturer-Plug-and-Play-System-Woofer-for-Tesla-Model-3-High-Sound-Quality-8-Inch-Car-Accesssories-Car-Audio-Subwoofers.html
A9: Audison AF M12.14 bit | B9: 1349 | C9: 1205.9 | D9: 1290 | E9: =IF(C9="","",B9-C9) | F9: =IF(D9="","",B9-D9) | G9: 1 | H9: =B9*G9 | I9: =IF(C9="","",C9*G9) | J9: =IF(D9="","",D9*G9) | K9: https://mbcaraudio.nl/10-12-16-en-18-kanaals/audison-af-m1214-bit.html | https://www.idealo.de/preisvergleich/OffersOfProduct/203736270_-af-m12-14-bit-audison.html | https://store.elettromedia.com/af-m12-14-bit/ | L9: MBC offers 5-year Audison warranty | Q9: Niet gebruikt voor aankoopadvies; MBC/EU heeft voorkeur wegens garantie, support en integratie.
A10: Audison DRC MP CAN | B10: 179 | E10: =IF(C10="","",B10-C10) | F10: =IF(D10="","",B10-D10) | G10: 1 | H10: =B10*G10 | I10: =IF(C10="","",C10*G10) | J10: =IF(D10="","",D10*G10) | K10: https://mbcaraudio.nl/bass-controls/audison-drc-mp-can.html | L10: Keep MBC unless a verified EU saving is material | Q10: Niet gebruikt voor aankoopadvies; MBC/EU heeft voorkeur wegens garantie, support en integratie.
A11: MATCH PP-TES-1.7B RYZEN | B11: 129 | E11: =IF(C11="","",B11-C11) | F11: =IF(D11="","",B11-D11) | G11: 1 | H11: =B11*G11 | I11: =IF(C11="","",C11*G11) | J11: =IF(D11="","",D11*G11) | K11: https://mbcaraudio.nl/autospecifieke-producten/tesla-autospecifieke-producten-en-accessoires/automodel-typenummer-en-bouwjaar-selectie-tesla/tesla-model-3-facelift-bouwjaar-2023- | L11: MBC price used; exact Audison integration must be confirmed | Q11: Niet gebruikt voor aankoopadvies; MBC/EU heeft voorkeur wegens garantie, support en integratie.
A13: Speaker subtotal (Focal core) | H13: =SUM(H5:H8) | I13: =SUM(I5:I8) | J13: =SUM(J5:J8) | M13: US speaker subtotal USD | N13: =SUM(M5:M8) | O13: =SUM(O5:O8) | P13: US incl. 21% import-VAT before shipping/duty
A14: Focal MBC premium vs DE | E14: =H13-I13 | M14: MBC saving vs US incl VAT | O14: =O13-H13 | P14: Positive value = MBC cheaper before US shipping/duty.
A15: Focal MBC premium vs FR MSRP | F15: =H13-J13
A17: USD→EUR koers | B17: =Overview!B10
A18: Indicatieve NL import-BTW | B18: 0.21

Sheet MBC_Quote_Mails
A1: Template e-mails voor MBCaraudio
